Workbook

Sheet README
A1: H.R. 1 Medicaid Coverage Loss and Life Expectancy by Arizona Legislative District
A2: Cornerstone Public Affairs — model workbook, September 4, 2026. Prepared for Brian.
A4: WHAT THIS IS
A5: Estimates, for each of Arizona's 30 legislative districts (2022 IRC map, used by both chambers), of (1) how many residents are projected to lose AHCCCS (Medicaid) coverage because of H.R. 1 (P.L. 119-21), (2) how many of them become uninsured, (3) the additional deaths per year that the peer-reviewed coverage-mortality literature implies, and (4) the resulting change in period life expectancy at birth, against a baseline built from CDC census-tract life expectancy (USALEEP) calibrated to the latest county figures.
A7: HOW TO READ THE NUMBERS (please read before quoting)
A8: • District figures are ALLOCATIONS of statewide projections (RAND for 2034; Urban Institute for the first full year; AHCCCS notice counts for the Oct. 2026 immigrant provision). AHCCCS publishes no enrollment by legislative district or ZIP code (HIPAA), so no district figure is an observed count. The allocation uses ACS 2020-2024 tract data on adults with Medicaid, calibrated to AHCCCS administrative enrollment by congressional district and county.
A9: • Two horizons: NEAR TERM = first full year of the Jan. 1, 2027 work requirement and six-month renewals (Urban Institute's 2028 projection) plus the Oct. 1, 2026 immigrant-eligibility change; FULL PHASE-IN = 2034, when the provider-tax and other provisions are fully in force (RAND).
A10: • Low / Central / High are a bounding ENVELOPE, not a statistical confidence interval: they combine the low and high ends of both the coverage-loss range and the mortality-effect range.
A11: • "Become uninsured" applies CBO's ratio of 7.8 million uninsured per 10.3 million fewer Medicaid enrollees (0.76). KFF's Arizona estimate of 290,000 newly uninsured by 2034 is higher than this model's 248,000, so the mortality results are conservative on this point.
A12: • Additional deaths per year are steady-state annual figures once coverage is lost (1.2 / 2.2 / 3.6 deaths per 1,000 uninsured person-years — Sommers et al. 2014; Gaffney et al. 2025 implied rate; Sommers 2017). The literature measures coverage GAINS; symmetric effects for losses are assumed, as every published projection of H.R. 1 does. Effects build over 3-4 years, so year-one deaths will be below steady state.
A13: • Life expectancy change is a PERIOD life-table shock: what life expectancy at birth in the district would be if the excess mortality persisted. It is not "years lost by each resident." The baseline is anchored to 2020-2022 county life expectancy (latest available), which embeds pandemic-period mortality, especially in Apache, Navajo and Gila counties (LDs 6 and 7).
A14: • Work-requirement losses exclude American Indians (exempt under Sec. 71119), consistent with RAND and Urban; six-month renewal losses do not (no exemption).
... A25: Assessment Inputs — rate schedule and statewide totals (ties to the CSPA one-pager: $1.80B payments lost, $565M assessment saved, $1.24B net per year at 3.5%; $9.9B net over FFY 2028-2037). Assessment by Facility — all 134 facilities in AHCCCS's SFY 2025 report with what each paid, received, and stands to lose, plus its legislative district. Assessment by System — the same rolled up by hospital system (e.g., Banner). Assessment by District — rolled up by the district where each facility sits.

Sheet District Results
A1: LD | B1: Main county | C1: 2020 population | D1: Adults 19-64 | E1: NEAR TERM: lose AHCCCS — Low | F1: NEAR TERM: lose AHCCCS — Central | G1: NEAR TERM: lose AHCCCS — High | H1: FULL PHASE-IN (2034): lose AHCCCS — Low | I1: FULL PHASE-IN: lose AHCCCS — Central | J1: FULL PHASE-IN: lose AHCCCS — High | K1: Full phase-in central as % of adults 19-64 | L1: Full phase-in central per 1,000 residents | M1: Full phase-in central excluding provider-tax component | N1: Become uninsured (full, central) | O1: Additional deaths per year (full) — Low | P1: Additional deaths per year (full) — Central | Q1: Additional deaths per year (full) — High | R1: Additional deaths per year (near term, central) | S1: Baseline life expectancy at birth (2020-22 calibrated) | T1: Life expectancy with H.R. 1 (full, central) | U1: Change (years) — Low | V1: Change (years) — Central | W1: Change (years) — High | X1: Change (months) — Central | Y1: Change (years) — near term, central
A2: 1 | B2: Yavapai | C2: ='Allocation Keys'!C2 | D2: ='Allocation Keys'!D2 | E2: =Assumptions!B2*'Allocation Keys'!F2+Assumptions!B3*'Allocation Keys'!G2+Assumptions!B4*'Allocation Keys'!K2 | F2: =Assumptions!C2*'Allocation Keys'!F2+Assumptions!C3*'Allocation Keys'!G2+Assumptions!C4*'Allocation Keys'!K2 | G2: =Assumptions!D2*'Allocation Keys'!F2+Assumptions!D3*'Allocation Keys'!G2+Assumptions!D4*'Allocation Keys'!K2 | H2: =Assumptions!B5*(Assumptions!B6*'Allocation Keys'!G2+Assumptions!B7*'Allocation Keys'!F2+Assumptions!B8*'Allocation Keys'!K2+Assumptions!B9*'Allocation Keys'!I2) | I2: =Assumptions!C5*(Assumptions!C6*'Allocation Keys'!G2+Assumptions!C7*'Allocation Keys'!F2+Assumptions!C8*'Allocation Keys'!K2+Assumptions!C9*'Allocation Keys'!I2) | J2: =Assumptions!D5*(Assumptions!D6*'Allocation Keys'!G2+Assumptions!D7*'Allocation Keys'!F2+Assumptions!D8*'Allocation Keys'!K2+Assumptions!D9*'Allocation Keys'!I2) | K2: =I2/D2 | L2: =I2/C2*1000 | M2: =I2-Assumptions!C5*Assumptions!C9*'Allocation Keys'!I2 | N2: =I2*Assumptions!C10 | O2: =H2*Assumptions!B10*Assumptions!B11/1000*'Allocation Keys'!Q2 | P2: =I2*Assumptions!C10*Assumptions!C11/1000*'Allocation Keys'!R2 | Q2: =J2*Assumptions!D10*Assumptions!D11/1000*'Allocation Keys'!S2 | R2: =F2*Assumptions!C10*Assumptions!C11/1000*'Allocation Keys'!R2 | S2: ='Life Expectancy'!F2 | T2: =S2+V2 | U2: =O2*-0.0083668 | V2: =P2*-0.00835543 | W2: =Q2*-0.00833549 | X2: =V2*12 | Y2: =R2*-0.00836229
A3: 2 | B3: Maricopa | C3: ='Allocation Keys'!C3 | D3: ='Allocation Keys'!D3 | E3: =Assumptions!B2*'Allocation Keys'!F3+Assumptions!B3*'Allocation Keys'!G3+Assumptions!B4*'Allocation Keys'!K3 | F3: =Assumptions!C2*'Allocation Keys'!F3+Assumptions!C3*'Allocation Keys'!G3+Assumptions!C4*'Allocation Keys'!K3 | G3: =Assumptions!D2*'Allocation Keys'!F3+Assumptions!D3*'Allocation Keys'!G3+Assumptions!D4*'Allocation Keys'!K3 | H3: =Assumptions!B5*(Assumptions!B6*'Allocation Keys'!G3+Assumptions!B7*'Allocation Keys'!F3+Assumptions!B8*'Allocation Keys'!K3+Assumptions!B9*'Allocation Keys'!I3) | I3: =Assumptions!C5*(Assumptions!C6*'Allocation Keys'!G3+Assumptions!C7*'Allocation Keys'!F3+Assumptions!C8*'Allocation Keys'!K3+Assumptions!C9*'Allocation Keys'!I3) | J3: =Assumptions!D5*(Assumptions!D6*'Allocation Keys'!G3+Assumptions!D7*'Allocation Keys'!F3+Assumptions!D8*'Allocation Keys'!K3+Assumptions!D9*'Allocation Keys'!I3) | K3: =I3/D3 | L3: =I3/C3*1000 | M3: =I3-Assumptions!C5*Assumptions!C9*'Allocation Keys'!I3 | N3: =I3*Assumptions!C10 | O3: =H3*Assumptions!B10*Assumptions!B11/1000*'Allocation Keys'!Q3 | P3: =I3*Assumptions!C10*Assumptions!C11/1000*'Allocation Keys'!R3 | Q3: =J3*Assumptions!D10*Assumptions!D11/1000*'Allocation Keys'!S3 | R3: =F3*Assumptions!C10*Assumptions!C11/1000*'Allocation Keys'!R3 | S3: ='Life Expectancy'!F3 | T3: =S3+V3 | U3: =O3*-0.00832313 | V3: =P3*-0.00831163 | W3: =Q3*-0.00829145 | X3: =V3*12 | Y3: =R3*-0.00831722
A4: 3 | B4: Maricopa | C4: ='Allocation Keys'!C4 | D4: ='Allocation Keys'!D4 | E4: =Assumptions!B2*'Allocation Keys'!F4+Assumptions!B3*'Allocation Keys'!G4+Assumptions!B4*'Allocation Keys'!K4 | F4: =Assumptions!C2*'Allocation Keys'!F4+Assumptions!C3*'Allocation Keys'!G4+Assumptions!C4*'Allocation Keys'!K4 | G4: =Assumptions!D2*'Allocation Keys'!F4+Assumptions!D3*'Allocation Keys'!G4+Assumptions!D4*'Allocation Keys'!K4 | H4: =Assumptions!B5*(Assumptions!B6*'Allocation Keys'!G4+Assumptions!B7*'Allocation Keys'!F4+Assumptions!B8*'Allocation Keys'!K4+Assumptions!B9*'Allocation Keys'!I4) | I4: =Assumptions!C5*(Assumptions!C6*'Allocation Keys'!G4+Assumptions!C7*'Allocation Keys'!F4+Assumptions!C8*'Allocation Keys'!K4+Assumptions!C9*'Allocation Keys'!I4) | J4: =Assumptions!D5*(Assumptions!D6*'Allocation Keys'!G4+Assumptions!D7*'Allocation Keys'!F4+Assumptions!D8*'Allocation Keys'!K4+Assumptions!D9*'Allocation Keys'!I4) | K4: =I4/D4 | L4: =I4/C4*1000 | M4: =I4-Assumptions!C5*Assumptions!C9*'Allocation Keys'!I4 | N4: =I4*Assumptions!C10 | O4: =H4*Assumptions!B10*Assumptions!B11/1000*'Allocation Keys'!Q4 | P4: =I4*Assumptions!C10*Assumptions!C11/1000*'Allocation Keys'!R4 | Q4: =J4*Assumptions!D10*Assumptions!D11/1000*'Allocation Keys'!S4 | R4: =F4*Assumptions!C10*Assumptions!C11/1000*'Allocation Keys'!R4 | S4: ='Life Expectancy'!F4 | T4: =S4+V4 | U4: =O4*-0.00981177 | V4: =P4*-0.00980735 | W4: =Q4*-0.00979957 | X4: =V4*12 | Y4: =R4*-0.00980886
A5: 4 | B5: Maricopa | C5: ='Allocation Keys'!C5 | D5: ='Allocation Keys'!D5 | E5: =Assumptions!B2*'Allocation Keys'!F5+Assumptions!B3*'Allocation Keys'!G5+Assumptions!B4*'Allocation Keys'!K5 | F5: =Assumptions!C2*'Allocation Keys'!F5+Assumptions!C3*'Allocation Keys'!G5+Assumptions!C4*'Allocation Keys'!K5 | G5: =Assumptions!D2*'Allocation Keys'!F5+Assumptions!D3*'Allocation Keys'!G5+Assumptions!D4*'Allocation Keys'!K5 | H5: =Assumptions!B5*(Assumptions!B6*'Allocation Keys'!G5+Assumptions!B7*'Allocation Keys'!F5+Assumptions!B8*'Allocation Keys'!K5+Assumptions!B9*'Allocation Keys'!I5) | I5: =Assumptions!C5*(Assumptions!C6*'Allocation Keys'!G5+Assumptions!C7*'Allocation Keys'!F5+Assumptions!C8*'Allocation Keys'!K5+Assumptions!C9*'Allocation Keys'!I5) | J5: =Assumptions!D5*(Assumptions!D6*'Allocation Keys'!G5+Assumptions!D7*'Allocation Keys'!F5+Assumptions!D8*'Allocation Keys'!K5+Assumptions!D9*'Allocation Keys'!I5) | K5: =I5/D5 | L5: =I5/C5*1000 | M5: =I5-Assumptions!C5*Assumptions!C9*'Allocation Keys'!I5 | N5: =I5*Assumptions!C10 | O5: =H5*Assumptions!B10*Assumptions!B11/1000*'Allocation Keys'!Q5 | P5: =I5*Assumptions!C10*Assumptions!C11/1000*'Allocation Keys'!R5 | Q5: =J5*Assumptions!D10*Assumptions!D11/1000*'Allocation Keys'!S5 | R5: =F5*Assumptions!C10*Assumptions!C11/1000*'Allocation Keys'!R5 | S5: ='Life Expectancy'!F5 | T5: =S5+V5 | U5: =O5*-0.00868436 | V5: =P5*-0.00867769 | W5: =Q5*-0.00866598 | X5: =V5*12 | Y5: =R5*-0.00868075
A6: 5 | B6: Maricopa | C6: ='Allocation Keys'!C6 | D6: ='Allocation Keys'!D6 | E6: =Assumptions!B2*'Allocation Keys'!F6+Assumptions!B3*'Allocation Keys'!G6+Assumptions!B4*'Allocation Keys'!K6 | F6: =Assumptions!C2*'Allocation Keys'!F6+Assumptions!C3*'Allocation Keys'!G6+Assumptions!C4*'Allocation Keys'!K6 | G6: =Assumptions!D2*'Allocation Keys'!F6+Assumptions!D3*'Allocation Keys'!G6+Assumptions!D4*'Allocation Keys'!K6 | H6: =Assumptions!B5*(Assumptions!B6*'Allocation Keys'!G6+Assumptions!B7*'Allocation Keys'!F6+Assumptions!B8*'Allocation Keys'!K6+Assumptions!B9*'Allocation Keys'!I6) | I6: =Assumptions!C5*(Assumptions!C6*'Allocation Keys'!G6+Assumptions!C7*'Allocation Keys'!F6+Assumptions!C8*'Allocation Keys'!K6+Assumptions!C9*'Allocation Keys'!I6) | J6: =Assumptions!D5*(Assumptions!D6*'Allocation Keys'!G6+Assumptions!D7*'Allocation Keys'!F6+Assumptions!D8*'Allocation Keys'!K6+Assumptions!D9*'Allocation Keys'!I6) | K6: =I6/D6 | L6: =I6/C6*1000 | M6: =I6-Assumptions!C5*Assumptions!C9*'Allocation Keys'!I6 | N6: =I6*Assumptions!C10 | O6: =H6*Assumptions!B10*Assumptions!B11/1000*'Allocation Keys'!Q6 | P6: =I6*Assumptions!C10*Assumptions!C11/1000*'Allocation Keys'!R6 | Q6: =J6*Assumptions!D10*Assumptions!D11/1000*'Allocation Keys'!S6 | R6: =F6*Assumptions!C10*Assumptions!C11/1000*'Allocation Keys'!R6 | S6: ='Life Expectancy'!F6 | T6: =S6+V6 | U6: =O6*-0.00828799 | V6: =P6*-0.0082744 | W6: =Q6*-0.00825055 | X6: =V6*12 | Y6: =R6*-0.00828218
A7: 6 | B7: Coconino | C7: ='Allocation Keys'!C7 | D7: ='Allocation Keys'!D7 | E7: =Assumptions!B2*'Allocation Keys'!F7+Assumptions!B3*'Allocation Keys'!G7+Assumptions!B4*'Allocation Keys'!K7 | F7: =Assumptions!C2*'Allocation Keys'!F7+Assumptions!C3*'Allocation Keys'!G7+Assumptions!C4*'Allocation Keys'!K7 | G7: =Assumptions!D2*'Allocation Keys'!F7+Assumptions!D3*'Allocation Keys'!G7+Assumptions!D4*'Allocation Keys'!K7 | H7: =Assumptions!B5*(Assumptions!B6*'Allocation Keys'!G7+Assumptions!B7*'Allocation Keys'!F7+Assumptions!B8*'Allocation Keys'!K7+Assumptions!B9*'Allocation Keys'!I7) | I7: =Assumptions!C5*(Assumptions!C6*'Allocation Keys'!G7+Assumptions!C7*'Allocation Keys'!F7+Assumptions!C8*'Allocation Keys'!K7+Assumptions!C9*'Allocation Keys'!I7) | J7: =Assumptions!D5*(Assumptions!D6*'Allocation Keys'!G7+Assumptions!D7*'Allocation Keys'!F7+Assumptions!D8*'Allocation Keys'!K7+Assumptions!D9*'Allocation Keys'!I7) | K7: =I7/D7 | L7: =I7/C7*1000 | M7: =I7-Assumptions!C5*Assumptions!C9*'Allocation Keys'!I7 | N7: =I7*Assumptions!C10 | O7: =H7*Assumptions!B10*Assumptions!B11/1000*'Allocation Keys'!Q7 | P7: =I7*Assumptions!C10*Assumptions!C11/1000*'Allocation Keys'!R7 | Q7: =J7*Assumptions!D10*Assumptions!D11/1000*'Allocation Keys'!S7 | R7: =F7*Assumptions!C10*Assumptions!C11/1000*'Allocation Keys'!R7 | S7: ='Life Expectancy'!F7 | T7: =S7+V7 | U7: =O7*-0.00788047 | V7: =P7*-0.00786818 | W7: =Q7*-0.00784661 | X7: =V7*12 | Y7: =R7*-0.00787468
A8: 7 | B8: Pinal | C8: ='Allocation Keys'!C8 | D8: ='Allocation Keys'!D8 | E8: =Assumptions!B2*'Allocation Keys'!F8+Assumptions!B3*'Allocation Keys'!G8+Assumptions!B4*'Allocation Keys'!K8 | F8: =Assumptions!C2*'Allocation Keys'!F8+Assumptions!C3*'Allocation Keys'!G8+Assumptions!C4*'Allocation Keys'!K8 | G8: =Assumptions!D2*'Allocation Keys'!F8+Assumptions!D3*'Allocation Keys'!G8+Assumptions!D4*'Allocation Keys'!K8 | H8: =Assumptions!B5*(Assumptions!B6*'Allocation Keys'!G8+Assumptions!B7*'Allocation Keys'!F8+Assumptions!B8*'Allocation Keys'!K8+Assumptions!B9*'Allocation Keys'!I8) | I8: =Assumptions!C5*(Assumptions!C6*'Allocation Keys'!G8+Assumptions!C7*'Allocation Keys'!F8+Assumptions!C8*'Allocation Keys'!K8+Assumptions!C9*'Allocation Keys'!I8) | J8: =Assumptions!D5*(Assumptions!D6*'Allocation Keys'!G8+Assumptions!D7*'Allocation Keys'!F8+Assumptions!D8*'Allocation Keys'!K8+Assumptions!D9*'Allocation Keys'!I8) | K8: =I8/D8 | L8: =I8/C8*1000 | M8: =I8-Assumptions!C5*Assumptions!C9*'Allocation Keys'!I8 | N8: =I8*Assumptions!C10 | O8: =H8*Assumptions!B10*Assumptions!B11/1000*'Allocation Keys'!Q8 | P8: =I8*Assumptions!C10*Assumptions!C11/1000*'Allocation Keys'!R8 | Q8: =J8*Assumptions!D10*Assumptions!D11/1000*'Allocation Keys'!S8 | R8: =F8*Assumptions!C10*Assumptions!C11/1000*'Allocation Keys'!R8 | S8: ='Life Expectancy'!F8 | T8: =S8+V8 | U8: =O8*-0.0087481 | V8: =P8*-0.00873584 | W8: =Q8*-0.00871431 | X8: =V8*12 | Y8: =R8*-0.00874291
A9: 8 | B9: Maricopa | C9: ='Allocation Keys'!C9 | D9: ='Allocation Keys'!D9 | E9: =Assumptions!B2*'Allocation Keys'!F9+Assumptions!B3*'Allocation Keys'!G9+Assumptions!B4*'Allocation Keys'!K9 | F9: =Assumptions!C2*'Allocation Keys'!F9+Assumptions!C3*'Allocation Keys'!G9+Assumptions!C4*'Allocation Keys'!K9 | G9: =Assumptions!D2*'Allocation Keys'!F9+Assumptions!D3*'Allocation Keys'!G9+Assumptions!D4*'Allocation Keys'!K9 | H9: =Assumptions!B5*(Assumptions!B6*'Allocation Keys'!G9+Assumptions!B7*'Allocation Keys'!F9+Assumptions!B8*'Allocation Keys'!K9+Assumptions!B9*'Allocation Keys'!I9) | I9: =Assumptions!C5*(Assumptions!C6*'Allocation Keys'!G9+Assumptions!C7*'Allocation Keys'!F9+Assumptions!C8*'Allocation Keys'!K9+Assumptions!C9*'Allocation Keys'!I9) | J9: =Assumptions!D5*(Assumptions!D6*'Allocation Keys'!G9+Assumptions!D7*'Allocation Keys'!F9+Assumptions!D8*'Allocation Keys'!K9+Assumptions!D9*'Allocation Keys'!I9) | K9: =I9/D9 | L9: =I9/C9*1000 | M9: =I9-Assumptions!C5*Assumptions!C9*'Allocation Keys'!I9 | N9: =I9*Assumptions!C10 | O9: =H9*Assumptions!B10*Assumptions!B11/1000*'Allocation Keys'!Q9 | P9: =I9*Assumptions!C10*Assumptions!C11/1000*'Allocation Keys'!R9 | Q9: =J9*Assumptions!D10*Assumptions!D11/1000*'Allocation Keys'!S9 | R9: =F9*Assumptions!C10*Assumptions!C11/1000*'Allocation Keys'!R9 | S9: ='Life Expectancy'!F9 | T9: =S9+V9 | U9: =O9*-0.00962387 | V9: =P9*-0.00961015 | W9: =Q9*-0.00958607 | X9: =V9*12 | Y9: =R9*-0.00961716
A10: 9 | B10: Maricopa | C10: ='Allocation Keys'!C10 | D10: ='Allocation Keys'!D10 | E10: =Assumptions!B2*'Allocation Keys'!F10+Assumptions!B3*'Allocation Keys'!G10+Assumptions!B4*'Allocation Keys'!K10 | F10: =Assumptions!C2*'Allocation Keys'!F10+Assumptions!C3*'Allocation Keys'!G10+Assumptions!C4*'Allocation Keys'!K10 | G10: =Assumptions!D2*'Allocation Keys'!F10+Assumptions!D3*'Allocation Keys'!G10+Assumptions!D4*'Allocation Keys'!K10 | H10: =Assumptions!B5*(Assumptions!B6*'Allocation Keys'!G10+Assumptions!B7*'Allocation Keys'!F10+Assumptions!B8*'Allocation Keys'!K10+Assumptions!B9*'Allocation Keys'!I10) | I10: =Assumptions!C5*(Assumptions!C6*'Allocation Keys'!G10+Assumptions!C7*'Allocation Keys'!F10+Assumptions!C8*'Allocation Keys'!K10+Assumptions!C9*'Allocation Keys'!I10) | J10: =Assumptions!D5*(Assumptions!D6*'Allocation Keys'!G10+Assumptions!D7*'Allocation Keys'!F10+Assumptions!D8*'Allocation Keys'!K10+Assumptions!D9*'Allocation Keys'!I10) | K10: =I10/D10 | L10: =I10/C10*1000 | M10: =I10-Assumptions!C5*Assumptions!C9*'Allocation Keys'!I10 | N10: =I10*Assumptions!C10 | O10: =H10*Assumptions!B10*Assumptions!B11/1000*'Allocation Keys'!Q10 | P10: =I10*Assumptions!C10*Assumptions!C11/1000*'Allocation Keys'!R10 | Q10: =J10*Assumptions!D10*Assumptions!D11/1000*'Allocation Keys'!S10 | R10: =F10*Assumptions!C10*Assumptions!C11/1000*'Allocation Keys'!R10 | S10: ='Life Expectancy'!F10 | T10: =S10+V10 | U10: =O10*-0.00959596 | V10: =P10*-0.00957996 | W10: =Q10*-0.00955188 | X10: =V10*12 | Y10: =R10*-0.0095895
A11: 10 | B11: Maricopa | C11: ='Allocation Keys'!C11 | D11: ='Allocation Keys'!D11 | E11: =Assumptions!B2*'Allocation Keys'!F11+Assumptions!B3*'Allocation Keys'!G11+Assumptions!B4*'Allocation Keys'!K11 | F11: =Assumptions!C2*'Allocation Keys'!F11+Assumptions!C3*'Allocation Keys'!G11+Assumptions!C4*'Allocation Keys'!K11 | G11: =Assumptions!D2*'Allocation Keys'!F11+Assumptions!D3*'Allocation Keys'!G11+Assumptions!D4*'Allocation Keys'!K11 | H11: =Assumptions!B5*(Assumptions!B6*'Allocation Keys'!G11+Assumptions!B7*'Allocation Keys'!F11+Assumptions!B8*'Allocation Keys'!K11+Assumptions!B9*'Allocation Keys'!I11) | I11: =Assumptions!C5*(Assumptions!C6*'Allocation Keys'!G11+Assumptions!C7*'Allocation Keys'!F11+Assumptions!C8*'Allocation Keys'!K11+Assumptions!C9*'Allocation Keys'!I11) | J11: =Assumptions!D5*(Assumptions!D6*'Allocation Keys'!G11+Assumptions!D7*'Allocation Keys'!F11+Assumptions!D8*'Allocation Keys'!K11+Assumptions!D9*'Allocation Keys'!I11) | K11: =I11/D11 | L11: =I11/C11*1000 | M11: =I11-Assumptions!C5*Assumptions!C9*'Allocation Keys'!I11 | N11: =I11*Assumptions!C10 | O11: =H11*Assumptions!B10*Assumptions!B11/1000*'Allocation Keys'!Q11 | P11: =I11*Assumptions!C10*Assumptions!C11/1000*'Allocation Keys'!R11 | Q11: =J11*Assumptions!D10*Assumptions!D11/1000*'Allocation Keys'!S11 | R11: =F11*Assumptions!C10*Assumptions!C11/1000*'Allocation Keys'!R11 | S11: ='Life Expectancy'!F11 | T11: =S11+V11 | U11: =O11*-0.008743 | V11: =P11*-0.00873295 | W11: =Q11*-0.00871529 | X11: =V11*12 | Y11: =R11*-0.0087384
A12: 11 | B12: Maricopa | C12: ='Allocation Keys'!C12 | D12: ='Allocation Keys'!D12 | E12: =Assumptions!B2*'Allocation Keys'!F12+Assumptions!B3*'Allocation Keys'!G12+Assumptions!B4*'Allocation Keys'!K12 | F12: =Assumptions!C2*'Allocation Keys'!F12+Assumptions!C3*'Allocation Keys'!G12+Assumptions!C4*'Allocation Keys'!K12 | G12: =Assumptions!D2*'Allocation Keys'!F12+Assumptions!D3*'Allocation Keys'!G12+Assumptions!D4*'Allocation Keys'!K12 | H12: =Assumptions!B5*(Assumptions!B6*'Allocation Keys'!G12+Assumptions!B7*'Allocation Keys'!F12+Assumptions!B8*'Allocation Keys'!K12+Assumptions!B9*'Allocation Keys'!I12) | I12: =Assumptions!C5*(Assumptions!C6*'Allocation Keys'!G12+Assumptions!C7*'Allocation Keys'!F12+Assumptions!C8*'Allocation Keys'!K12+Assumptions!C9*'Allocation Keys'!I12) | J12: =Assumptions!D5*(Assumptions!D6*'Allocation Keys'!G12+Assumptions!D7*'Allocation Keys'!F12+Assumptions!D8*'Allocation Keys'!K12+Assumptions!D9*'Allocation Keys'!I12) | K12: =I12/D12 | L12: =I12/C12*1000 | M12: =I12-Assumptions!C5*Assumptions!C9*'Allocation Keys'!I12 | N12: =I12*Assumptions!C10 | O12: =H12*Assumptions!B10*Assumptions!B11/1000*'Allocation Keys'!Q12 | P12: =I12*Assumptions!C10*Assumptions!C11/1000*'Allocation Keys'!R12 | Q12: =J12*Assumptions!D10*Assumptions!D11/1000*'Allocation Keys'!S12 | R12: =F12*Assumptions!C10*Assumptions!C11/1000*'Allocation Keys'!R12 | S12: ='Life Expectancy'!F12 | T12: =S12+V12 | U12: =O12*-0.00919463 | V12: =P12*-0.00917632 | W12: =Q12*-0.00914423 | X12: =V12*12 | Y12: =R12*-0.00918705
A13: 12 | B13: Maricopa | C13: ='Allocation Keys'!C13 | D13: ='Allocation Keys'!D13 | E13: =Assumptions!B2*'Allocation Keys'!F13+Assumptions!B3*'Allocation Keys'!G13+Assumptions!B4*'Allocation Keys'!K13 | F13: =Assumptions!C2*'Allocation Keys'!F13+Assumptions!C3*'Allocation Keys'!G13+Assumptions!C4*'Allocation Keys'!K13 | G13: =Assumptions!D2*'Allocation Keys'!F13+Assumptions!D3*'Allocation Keys'!G13+Assumptions!D4*'Allocation Keys'!K13 | H13: =Assumptions!B5*(Assumptions!B6*'Allocation Keys'!G13+Assumptions!B7*'Allocation Keys'!F13+Assumptions!B8*'Allocation Keys'!K13+Assumptions!B9*'Allocation Keys'!I13) | I13: =Assumptions!C5*(Assumptions!C6*'Allocation Keys'!G13+Assumptions!C7*'Allocation Keys'!F13+Assumptions!C8*'Allocation Keys'!K13+Assumptions!C9*'Allocation Keys'!I13) | J13: =Assumptions!D5*(Assumptions!D6*'Allocation Keys'!G13+Assumptions!D7*'Allocation Keys'!F13+Assumptions!D8*'Allocation Keys'!K13+Assumptions!D9*'Allocation Keys'!I13) | K13: =I13/D13 | L13: =I13/C13*1000 | M13: =I13-Assumptions!C5*Assumptions!C9*'Allocation Keys'!I13 | N13: =I13*Assumptions!C10 | O13: =H13*Assumptions!B10*Assumptions!B11/1000*'Allocation Keys'!Q13 | P13: =I13*Assumptions!C10*Assumptions!C11/1000*'Allocation Keys'!R13 | Q13: =J13*Assumptions!D10*Assumptions!D11/1000*'Allocation Keys'!S13 | R13: =F13*Assumptions!C10*Assumptions!C11/1000*'Allocation Keys'!R13 | S13: ='Life Expectancy'!F13 | T13: =S13+V13 | U13: =O13*-0.00915705 | V13: =P13*-0.00915048 | W13: =Q13*-0.00913894 | X13: =V13*12 | Y13: =R13*-0.00915379
A14: 13 | B14: Maricopa | C14: ='Allocation Keys'!C14 | D14: ='Allocation Keys'!D14 | E14: =Assumptions!B2*'Allocation Keys'!F14+Assumptions!B3*'Allocation Keys'!G14+Assumptions!B4*'Allocation Keys'!K14 | F14: =Assumptions!C2*'Allocation Keys'!F14+Assumptions!C3*'Allocation Keys'!G14+Assumptions!C4*'Allocation Keys'!K14 | G14: =Assumptions!D2*'Allocation Keys'!F14+Assumptions!D3*'Allocation Keys'!G14+Assumptions!D4*'Allocation Keys'!K14 | H14: =Assumptions!B5*(Assumptions!B6*'Allocation Keys'!G14+Assumptions!B7*'Allocation Keys'!F14+Assumptions!B8*'Allocation Keys'!K14+Assumptions!B9*'Allocation Keys'!I14) | I14: =Assumptions!C5*(Assumptions!C6*'Allocation Keys'!G14+Assumptions!C7*'Allocation Keys'!F14+Assumptions!C8*'Allocation Keys'!K14+Assumptions!C9*'Allocation Keys'!I14) | J14: =Assumptions!D5*(Assumptions!D6*'Allocation Keys'!G14+Assumptions!D7*'Allocation Keys'!F14+Assumptions!D8*'Allocation Keys'!K14+Assumptions!D9*'Allocation Keys'!I14) | K14: =I14/D14 | L14: =I14/C14*1000 | M14: =I14-Assumptions!C5*Assumptions!C9*'Allocation Keys'!I14 | N14: =I14*Assumptions!C10 | O14: =H14*Assumptions!B10*Assumptions!B11/1000*'Allocation Keys'!Q14 | P14: =I14*Assumptions!C10*Assumptions!C11/1000*'Allocation Keys'!R14 | Q14: =J14*Assumptions!D10*Assumptions!D11/1000*'Allocation Keys'!S14 | R14: =F14*Assumptions!C10*Assumptions!C11/1000*'Allocation Keys'!R14 | S14: ='Life Expectancy'!F14 | T14: =S14+V14 | U14: =O14*-0.00996349 | V14: =P14*-0.00995621 | W14: =Q14*-0.00994341 | X14: =V14*12 | Y14: =R14*-0.0099595
A15: 14 | B15: Maricopa | C15: ='Allocation Keys'!C15 | D15: ='Allocation Keys'!D15 | E15: =Assumptions!B2*'Allocation Keys'!F15+Assumptions!B3*'Allocation Keys'!G15+Assumptions!B4*'Allocation Keys'!K15 | F15: =Assumptions!C2*'Allocation Keys'!F15+Assumptions!C3*'Allocation Keys'!G15+Assumptions!C4*'Allocation Keys'!K15 | G15: =Assumptions!D2*'Allocation Keys'!F15+Assumptions!D3*'Allocation Keys'!G15+Assumptions!D4*'Allocation Keys'!K15 | H15: =Assumptions!B5*(Assumptions!B6*'Allocation Keys'!G15+Assumptions!B7*'Allocation Keys'!F15+Assumptions!B8*'Allocation Keys'!K15+Assumptions!B9*'Allocation Keys'!I15) | I15: =Assumptions!C5*(Assumptions!C6*'Allocation Keys'!G15+Assumptions!C7*'Allocation Keys'!F15+Assumptions!C8*'Allocation Keys'!K15+Assumptions!C9*'Allocation Keys'!I15) | J15: =Assumptions!D5*(Assumptions!D6*'Allocation Keys'!G15+Assumptions!D7*'Allocation Keys'!F15+Assumptions!D8*'Allocation Keys'!K15+Assumptions!D9*'Allocation Keys'!I15) | K15: =I15/D15 | L15: =I15/C15*1000 | M15: =I15-Assumptions!C5*Assumptions!C9*'Allocation Keys'!I15 | N15: =I15*Assumptions!C10 | O15: =H15*Assumptions!B10*Assumptions!B11/1000*'Allocation Keys'!Q15 | P15: =I15*Assumptions!C10*Assumptions!C11/1000*'Allocation Keys'!R15 | Q15: =J15*Assumptions!D10*Assumptions!D11/1000*'Allocation Keys'!S15 | R15: =F15*Assumptions!C10*Assumptions!C11/1000*'Allocation Keys'!R15 | S15: ='Life Expectancy'!F15 | T15: =S15+V15 | U15: =O15*-0.00980142 | V15: =P15*-0.00979558 | W15: =Q15*-0.00978531 | X15: =V15*12 | Y15: =R15*-0.00979832
A16: 15 | B16: Maricopa | C16: ='Allocation Keys'!C16 | D16: ='Allocation Keys'!D16 | E16: =Assumptions!B2*'Allocation Keys'!F16+Assumptions!B3*'Allocation Keys'!G16+Assumptions!B4*'Allocation Keys'!K16 | F16: =Assumptions!C2*'Allocation Keys'!F16+Assumptions!C3*'Allocation Keys'!G16+Assumptions!C4*'Allocation Keys'!K16 | G16: =Assumptions!D2*'Allocation Keys'!F16+Assumptions!D3*'Allocation Keys'!G16+Assumptions!D4*'Allocation Keys'!K16 | H16: =Assumptions!B5*(Assumptions!B6*'Allocation Keys'!G16+Assumptions!B7*'Allocation Keys'!F16+Assumptions!B8*'Allocation Keys'!K16+Assumptions!B9*'Allocation Keys'!I16) | I16: =Assumptions!C5*(Assumptions!C6*'Allocation Keys'!G16+Assumptions!C7*'Allocation Keys'!F16+Assumptions!C8*'Allocation Keys'!K16+Assumptions!C9*'Allocation Keys'!I16) | J16: =Assumptions!D5*(Assumptions!D6*'Allocation Keys'!G16+Assumptions!D7*'Allocation Keys'!F16+Assumptions!D8*'Allocation Keys'!K16+Assumptions!D9*'Allocation Keys'!I16) | K16: =I16/D16 | L16: =I16/C16*1000 | M16: =I16-Assumptions!C5*Assumptions!C9*'Allocation Keys'!I16 | N16: =I16*Assumptions!C10 | O16: =H16*Assumptions!B10*Assumptions!B11/1000*'Allocation Keys'!Q16 | P16: =I16*Assumptions!C10*Assumptions!C11/1000*'Allocation Keys'!R16 | Q16: =J16*Assumptions!D10*Assumptions!D11/1000*'Allocation Keys'!S16 | R16: =F16*Assumptions!C10*Assumptions!C11/1000*'Allocation Keys'!R16 | S16: ='Life Expectancy'!F16 | T16: =S16+V16 | U16: =O16*-0.00936631 | V16: =P16*-0.00935821 | W16: =Q16*-0.00934398 | X16: =V16*12 | Y16: =R16*-0.00936309
A17: 16 | B17: Pinal | C17: ='Allocation Keys'!C17 | D17: ='Allocation Keys'!D17 | E17: =Assumptions!B2*'Allocation Keys'!F17+Assumptions!B3*'Allocation Keys'!G17+Assumptions!B4*'Allocation Keys'!K17 | F17: =Assumptions!C2*'Allocation Keys'!F17+Assumptions!C3*'Allocation Keys'!G17+Assumptions!C4*'Allocation Keys'!K17 | G17: =Assumptions!D2*'Allocation Keys'!F17+Assumptions!D3*'Allocation Keys'!G17+Assumptions!D4*'Allocation Keys'!K17 | H17: =Assumptions!B5*(Assumptions!B6*'Allocation Keys'!G17+Assumptions!B7*'Allocation Keys'!F17+Assumptions!B8*'Allocation Keys'!K17+Assumptions!B9*'Allocation Keys'!I17) | I17: =Assumptions!C5*(Assumptions!C6*'Allocation Keys'!G17+Assumptions!C7*'Allocation Keys'!F17+Assumptions!C8*'Allocation Keys'!K17+Assumptions!C9*'Allocation Keys'!I17) | J17: =Assumptions!D5*(Assumptions!D6*'Allocation Keys'!G17+Assumptions!D7*'Allocation Keys'!F17+Assumptions!D8*'Allocation Keys'!K17+Assumptions!D9*'Allocation Keys'!I17) | K17: =I17/D17 | L17: =I17/C17*1000 | M17: =I17-Assumptions!C5*Assumptions!C9*'Allocation Keys'!I17 | N17: =I17*Assumptions!C10 | O17: =H17*Assumptions!B10*Assumptions!B11/1000*'Allocation Keys'!Q17 | P17: =I17*Assumptions!C10*Assumptions!C11/1000*'Allocation Keys'!R17 | Q17: =J17*Assumptions!D10*Assumptions!D11/1000*'Allocation Keys'!S17 | R17: =F17*Assumptions!C10*Assumptions!C11/1000*'Allocation Keys'!R17 | S17: ='Life Expectancy'!F17 | T17: =S17+V17 | U17: =O17*-0.00928222 | V17: =P17*-0.00926882 | W17: =Q17*-0.00924532 | X17: =V17*12 | Y17: =R17*-0.00927674
A18: 17 | B18: Pima | C18: ='Allocation Keys'!C18 | D18: ='Allocation Keys'!D18 | E18: =Assumptions!B2*'Allocation Keys'!F18+Assumptions!B3*'Allocation Keys'!G18+Assumptions!B4*'Allocation Keys'!K18 | F18: =Assumptions!C2*'Allocation Keys'!F18+Assumptions!C3*'Allocation Keys'!G18+Assumptions!C4*'Allocation Keys'!K18 | G18: =Assumptions!D2*'Allocation Keys'!F18+Assumptions!D3*'Allocation Keys'!G18+Assumptions!D4*'Allocation Keys'!K18 | H18: =Assumptions!B5*(Assumptions!B6*'Allocation Keys'!G18+Assumptions!B7*'Allocation Keys'!F18+Assumptions!B8*'Allocation Keys'!K18+Assumptions!B9*'Allocation Keys'!I18) | I18: =Assumptions!C5*(Assumptions!C6*'Allocation Keys'!G18+Assumptions!C7*'Allocation Keys'!F18+Assumptions!C8*'Allocation Keys'!K18+Assumptions!C9*'Allocation Keys'!I18) | J18: =Assumptions!D5*(Assumptions!D6*'Allocation Keys'!G18+Assumptions!D7*'Allocation Keys'!F18+Assumptions!D8*'Allocation Keys'!K18+Assumptions!D9*'Allocation Keys'!I18) | K18: =I18/D18 | L18: =I18/C18*1000 | M18: =I18-Assumptions!C5*Assumptions!C9*'Allocation Keys'!I18 | N18: =I18*Assumptions!C10 | O18: =H18*Assumptions!B10*Assumptions!B11/1000*'Allocation Keys'!Q18 | P18: =I18*Assumptions!C10*Assumptions!C11/1000*'Allocation Keys'!R18 | Q18: =J18*Assumptions!D10*Assumptions!D11/1000*'Allocation Keys'!S18 | R18: =F18*Assumptions!C10*Assumptions!C11/1000*'Allocation Keys'!R18 | S18: ='Life Expectancy'!F18 | T18: =S18+V18 | U18: =O18*-0.00981603 | V18: =P18*-0.00980728 | W18: =Q18*-0.00979191 | X18: =V18*12 | Y18: =R18*-0.00981233
A19: 18 | B19: Pima | C19: ='Allocation Keys'!C19 | D19: ='Allocation Keys'!D19 | E19: =Assumptions!B2*'Allocation Keys'!F19+Assumptions!B3*'Allocation Keys'!G19+Assumptions!B4*'Allocation Keys'!K19 | F19: =Assumptions!C2*'Allocation Keys'!F19+Assumptions!C3*'Allocation Keys'!G19+Assumptions!C4*'Allocation Keys'!K19 | G19: =Assumptions!D2*'Allocation Keys'!F19+Assumptions!D3*'Allocation Keys'!G19+Assumptions!D4*'Allocation Keys'!K19 | H19: =Assumptions!B5*(Assumptions!B6*'Allocation Keys'!G19+Assumptions!B7*'Allocation Keys'!F19+Assumptions!B8*'Allocation Keys'!K19+Assumptions!B9*'Allocation Keys'!I19) | I19: =Assumptions!C5*(Assumptions!C6*'Allocation Keys'!G19+Assumptions!C7*'Allocation Keys'!F19+Assumptions!C8*'Allocation Keys'!K19+Assumptions!C9*'Allocation Keys'!I19) | J19: =Assumptions!D5*(Assumptions!D6*'Allocation Keys'!G19+Assumptions!D7*'Allocation Keys'!F19+Assumptions!D8*'Allocation Keys'!K19+Assumptions!D9*'Allocation Keys'!I19) | K19: =I19/D19 | L19: =I19/C19*1000 | M19: =I19-Assumptions!C5*Assumptions!C9*'Allocation Keys'!I19 | N19: =I19*Assumptions!C10 | O19: =H19*Assumptions!B10*Assumptions!B11/1000*'Allocation Keys'!Q19 | P19: =I19*Assumptions!C10*Assumptions!C11/1000*'Allocation Keys'!R19 | Q19: =J19*Assumptions!D10*Assumptions!D11/1000*'Allocation Keys'!S19 | R19: =F19*Assumptions!C10*Assumptions!C11/1000*'Allocation Keys'!R19 | S19: ='Life Expectancy'!F19 | T19: =S19+V19 | U19: =O19*-0.00903863 | V19: =P19*-0.00902537 | W19: =Q19*-0.00900209 | X19: =V19*12 | Y19: =R19*-0.00903279
A20: 19 | B20: Cochise | C20: ='Allocation Keys'!C20 | D20: ='Allocation Keys'!D20 | E20: =Assumptions!B2*'Allocation Keys'!F20+Assumptions!B3*'Allocation Keys'!G20+Assumptions!B4*'Allocation Keys'!K20 | F20: =Assumptions!C2*'Allocation Keys'!F20+Assumptions!C3*'Allocation Keys'!G20+Assumptions!C4*'Allocation Keys'!K20 | G20: =Assumptions!D2*'Allocation Keys'!F20+Assumptions!D3*'Allocation Keys'!G20+Assumptions!D4*'Allocation Keys'!K20 | H20: =Assumptions!B5*(Assumptions!B6*'Allocation Keys'!G20+Assumptions!B7*'Allocation Keys'!F20+Assumptions!B8*'Allocation Keys'!K20+Assumptions!B9*'Allocation Keys'!I20) | I20: =Assumptions!C5*(Assumptions!C6*'Allocation Keys'!G20+Assumptions!C7*'Allocation Keys'!F20+Assumptions!C8*'Allocation Keys'!K20+Assumptions!C9*'Allocation Keys'!I20) | J20: =Assumptions!D5*(Assumptions!D6*'Allocation Keys'!G20+Assumptions!D7*'Allocation Keys'!F20+Assumptions!D8*'Allocation Keys'!K20+Assumptions!D9*'Allocation Keys'!I20) | K20: =I20/D20 | L20: =I20/C20*1000 | M20: =I20-Assumptions!C5*Assumptions!C9*'Allocation Keys'!I20 | N20: =I20*Assumptions!C10 | O20: =H20*Assumptions!B10*Assumptions!B11/1000*'Allocation Keys'!Q20 | P20: =I20*Assumptions!C10*Assumptions!C11/1000*'Allocation Keys'!R20 | Q20: =J20*Assumptions!D10*Assumptions!D11/1000*'Allocation Keys'!S20 | R20: =F20*Assumptions!C10*Assumptions!C11/1000*'Allocation Keys'!R20 | S20: ='Life Expectancy'!F20 | T20: =S20+V20 | U20: =O20*-0.01110737 | V20: =P20*-0.01108753 | W20: =Q20*-0.01105273 | X20: =V20*12 | Y20: =R20*-0.01109984
A21: 20 | B21: Pima | C21: ='Allocation Keys'!C21 | D21: ='Allocation Keys'!D21 | E21: =Assumptions!B2*'Allocation Keys'!F21+Assumptions!B3*'Allocation Keys'!G21+Assumptions!B4*'Allocation Keys'!K21 | F21: =Assumptions!C2*'Allocation Keys'!F21+Assumptions!C3*'Allocation Keys'!G21+Assumptions!C4*'Allocation Keys'!K21 | G21: =Assumptions!D2*'Allocation Keys'!F21+Assumptions!D3*'Allocation Keys'!G21+Assumptions!D4*'Allocation Keys'!K21 | H21: =Assumptions!B5*(Assumptions!B6*'Allocation Keys'!G21+Assumptions!B7*'Allocation Keys'!F21+Assumptions!B8*'Allocation Keys'!K21+Assumptions!B9*'Allocation Keys'!I21) | I21: =Assumptions!C5*(Assumptions!C6*'Allocation Keys'!G21+Assumptions!C7*'Allocation Keys'!F21+Assumptions!C8*'Allocation Keys'!K21+Assumptions!C9*'Allocation Keys'!I21) | J21: =Assumptions!D5*(Assumptions!D6*'Allocation Keys'!G21+Assumptions!D7*'Allocation Keys'!F21+Assumptions!D8*'Allocation Keys'!K21+Assumptions!D9*'Allocation Keys'!I21) | K21: =I21/D21 | L21: =I21/C21*1000 | M21: =I21-Assumptions!C5*Assumptions!C9*'Allocation Keys'!I21 | N21: =I21*Assumptions!C10 | O21: =H21*Assumptions!B10*Assumptions!B11/1000*'Allocation Keys'!Q21 | P21: =I21*Assumptions!C10*Assumptions!C11/1000*'Allocation Keys'!R21 | Q21: =J21*Assumptions!D10*Assumptions!D11/1000*'Allocation Keys'!S21 | R21: =F21*Assumptions!C10*Assumptions!C11/1000*'Allocation Keys'!R21 | S21: ='Life Expectancy'!F21 | T21: =S21+V21 | U21: =O21*-0.00958725 | V21: =P21*-0.0095656 | W21: =Q21*-0.00952765 | X21: =V21*12 | Y21: =R21*-0.00957895
A22: 21 | B22: Pima | C22: ='Allocation Keys'!C22 | D22: ='Allocation Keys'!D22 | E22: =Assumptions!B2*'Allocation Keys'!F22+Assumptions!B3*'Allocation Keys'!G22+Assumptions!B4*'Allocation Keys'!K22 | F22: =Assumptions!C2*'Allocation Keys'!F22+Assumptions!C3*'Allocation Keys'!G22+Assumptions!C4*'Allocation Keys'!K22 | G22: =Assumptions!D2*'Allocation Keys'!F22+Assumptions!D3*'Allocation Keys'!G22+Assumptions!D4*'Allocation Keys'!K22 | H22: =Assumptions!B5*(Assumptions!B6*'Allocation Keys'!G22+Assumptions!B7*'Allocation Keys'!F22+Assumptions!B8*'Allocation Keys'!K22+Assumptions!B9*'Allocation Keys'!I22) | I22: =Assumptions!C5*(Assumptions!C6*'Allocation Keys'!G22+Assumptions!C7*'Allocation Keys'!F22+Assumptions!C8*'Allocation Keys'!K22+Assumptions!C9*'Allocation Keys'!I22) | J22: =Assumptions!D5*(Assumptions!D6*'Allocation Keys'!G22+Assumptions!D7*'Allocation Keys'!F22+Assumptions!D8*'Allocation Keys'!K22+Assumptions!D9*'Allocation Keys'!I22) | K22: =I22/D22 | L22: =I22/C22*1000 | M22: =I22-Assumptions!C5*Assumptions!C9*'Allocation Keys'!I22 | N22: =I22*Assumptions!C10 | O22: =H22*Assumptions!B10*Assumptions!B11/1000*'Allocation Keys'!Q22 | P22: =I22*Assumptions!C10*Assumptions!C11/1000*'Allocation Keys'!R22 | Q22: =J22*Assumptions!D10*Assumptions!D11/1000*'Allocation Keys'!S22 | R22: =F22*Assumptions!C10*Assumptions!C11/1000*'Allocation Keys'!R22 | S22: ='Life Expectancy'!F22 | T22: =S22+V22 | U22: =O22*-0.00977367 | V22: =P22*-0.00975243 | W22: =Q22*-0.00971522 | X22: =V22*12 | Y22: =R22*-0.00976547
A23: 22 | B23: Maricopa | C23: ='Allocation Keys'!C23 | D23: ='Allocation Keys'!D23 | E23: =Assumptions!B2*'Allocation Keys'!F23+Assumptions!B3*'Allocation Keys'!G23+Assumptions!B4*'Allocation Keys'!K23 | F23: =Assumptions!C2*'Allocation Keys'!F23+Assumptions!C3*'Allocation Keys'!G23+Assumptions!C4*'Allocation Keys'!K23 | G23: =Assumptions!D2*'Allocation Keys'!F23+Assumptions!D3*'Allocation Keys'!G23+Assumptions!D4*'Allocation Keys'!K23 | H23: =Assumptions!B5*(Assumptions!B6*'Allocation Keys'!G23+Assumptions!B7*'Allocation Keys'!F23+Assumptions!B8*'Allocation Keys'!K23+Assumptions!B9*'Allocation Keys'!I23) | I23: =Assumptions!C5*(Assumptions!C6*'Allocation Keys'!G23+Assumptions!C7*'Allocation Keys'!F23+Assumptions!C8*'Allocation Keys'!K23+Assumptions!C9*'Allocation Keys'!I23) | J23: =Assumptions!D5*(Assumptions!D6*'Allocation Keys'!G23+Assumptions!D7*'Allocation Keys'!F23+Assumptions!D8*'Allocation Keys'!K23+Assumptions!D9*'Allocation Keys'!I23) | K23: =I23/D23 | L23: =I23/C23*1000 | M23: =I23-Assumptions!C5*Assumptions!C9*'Allocation Keys'!I23 | N23: =I23*Assumptions!C10 | O23: =H23*Assumptions!B10*Assumptions!B11/1000*'Allocation Keys'!Q23 | P23: =I23*Assumptions!C10*Assumptions!C11/1000*'Allocation Keys'!R23 | Q23: =J23*Assumptions!D10*Assumptions!D11/1000*'Allocation Keys'!S23 | R23: =F23*Assumptions!C10*Assumptions!C11/1000*'Allocation Keys'!R23 | S23: ='Life Expectancy'!F23 | T23: =S23+V23 | U23: =O23*-0.00901735 | V23: =P23*-0.00900199 | W23: =Q23*-0.00897505 | X23: =V23*12 | Y23: =R23*-0.00901126
A24: 23 | B24: Yuma | C24: ='Allocation Keys'!C24 | D24: ='Allocation Keys'!D24 | E24: =Assumptions!B2*'Allocation Keys'!F24+Assumptions!B3*'Allocation Keys'!G24+Assumptions!B4*'Allocation Keys'!K24 | F24: =Assumptions!C2*'Allocation Keys'!F24+Assumptions!C3*'Allocation Keys'!G24+Assumptions!C4*'Allocation Keys'!K24 | G24: =Assumptions!D2*'Allocation Keys'!F24+Assumptions!D3*'Allocation Keys'!G24+Assumptions!D4*'Allocation Keys'!K24 | H24: =Assumptions!B5*(Assumptions!B6*'Allocation Keys'!G24+Assumptions!B7*'Allocation Keys'!F24+Assumptions!B8*'Allocation Keys'!K24+Assumptions!B9*'Allocation Keys'!I24) | I24: =Assumptions!C5*(Assumptions!C6*'Allocation Keys'!G24+Assumptions!C7*'Allocation Keys'!F24+Assumptions!C8*'Allocation Keys'!K24+Assumptions!C9*'Allocation Keys'!I24) | J24: =Assumptions!D5*(Assumptions!D6*'Allocation Keys'!G24+Assumptions!D7*'Allocation Keys'!F24+Assumptions!D8*'Allocation Keys'!K24+Assumptions!D9*'Allocation Keys'!I24) | K24: =I24/D24 | L24: =I24/C24*1000 | M24: =I24-Assumptions!C5*Assumptions!C9*'Allocation Keys'!I24 | N24: =I24*Assumptions!C10 | O24: =H24*Assumptions!B10*Assumptions!B11/1000*'Allocation Keys'!Q24 | P24: =I24*Assumptions!C10*Assumptions!C11/1000*'Allocation Keys'!R24 | Q24: =J24*Assumptions!D10*Assumptions!D11/1000*'Allocation Keys'!S24 | R24: =F24*Assumptions!C10*Assumptions!C11/1000*'Allocation Keys'!R24 | S24: ='Life Expectancy'!F24 | T24: =S24+V24 | U24: =O24*-0.01038002 | V24: =P24*-0.01035873 | W24: =Q24*-0.01032141 | X24: =V24*12 | Y24: =R24*-0.01037203
A25: 24 | B25: Maricopa | C25: ='Allocation Keys'!C25 | D25: ='Allocation Keys'!D25 | E25: =Assumptions!B2*'Allocation Keys'!F25+Assumptions!B3*'Allocation Keys'!G25+Assumptions!B4*'Allocation Keys'!K25 | F25: =Assumptions!C2*'Allocation Keys'!F25+Assumptions!C3*'Allocation Keys'!G25+Assumptions!C4*'Allocation Keys'!K25 | G25: =Assumptions!D2*'Allocation Keys'!F25+Assumptions!D3*'Allocation Keys'!G25+Assumptions!D4*'Allocation Keys'!K25 | H25: =Assumptions!B5*(Assumptions!B6*'Allocation Keys'!G25+Assumptions!B7*'Allocation Keys'!F25+Assumptions!B8*'Allocation Keys'!K25+Assumptions!B9*'Allocation Keys'!I25) | I25: =Assumptions!C5*(Assumptions!C6*'Allocation Keys'!G25+Assumptions!C7*'Allocation Keys'!F25+Assumptions!C8*'Allocation Keys'!K25+Assumptions!C9*'Allocation Keys'!I25) | J25: =Assumptions!D5*(Assumptions!D6*'Allocation Keys'!G25+Assumptions!D7*'Allocation Keys'!F25+Assumptions!D8*'Allocation Keys'!K25+Assumptions!D9*'Allocation Keys'!I25) | K25: =I25/D25 | L25: =I25/C25*1000 | M25: =I25-Assumptions!C5*Assumptions!C9*'Allocation Keys'!I25 | N25: =I25*Assumptions!C10 | O25: =H25*Assumptions!B10*Assumptions!B11/1000*'Allocation Keys'!Q25 | P25: =I25*Assumptions!C10*Assumptions!C11/1000*'Allocation Keys'!R25 | Q25: =J25*Assumptions!D10*Assumptions!D11/1000*'Allocation Keys'!S25 | R25: =F25*Assumptions!C10*Assumptions!C11/1000*'Allocation Keys'!R25 | S25: ='Life Expectancy'!F25 | T25: =S25+V25 | U25: =O25*-0.00991382 | V25: =P25*-0.00988933 | W25: =Q25*-0.00984645 | X25: =V25*12 | Y25: =R25*-0.00990352
A26: 25 | B26: Maricopa | C26: ='Allocation Keys'!C26 | D26: ='Allocation Keys'!D26 | E26: =Assumptions!B2*'Allocation Keys'!F26+Assumptions!B3*'Allocation Keys'!G26+Assumptions!B4*'Allocation Keys'!K26 | F26: =Assumptions!C2*'Allocation Keys'!F26+Assumptions!C3*'Allocation Keys'!G26+Assumptions!C4*'Allocation Keys'!K26 | G26: =Assumptions!D2*'Allocation Keys'!F26+Assumptions!D3*'Allocation Keys'!G26+Assumptions!D4*'Allocation Keys'!K26 | H26: =Assumptions!B5*(Assumptions!B6*'Allocation Keys'!G26+Assumptions!B7*'Allocation Keys'!F26+Assumptions!B8*'Allocation Keys'!K26+Assumptions!B9*'Allocation Keys'!I26) | I26: =Assumptions!C5*(Assumptions!C6*'Allocation Keys'!G26+Assumptions!C7*'Allocation Keys'!F26+Assumptions!C8*'Allocation Keys'!K26+Assumptions!C9*'Allocation Keys'!I26) | J26: =Assumptions!D5*(Assumptions!D6*'Allocation Keys'!G26+Assumptions!D7*'Allocation Keys'!F26+Assumptions!D8*'Allocation Keys'!K26+Assumptions!D9*'Allocation Keys'!I26) | K26: =I26/D26 | L26: =I26/C26*1000 | M26: =I26-Assumptions!C5*Assumptions!C9*'Allocation Keys'!I26 | N26: =I26*Assumptions!C10 | O26: =H26*Assumptions!B10*Assumptions!B11/1000*'Allocation Keys'!Q26 | P26: =I26*Assumptions!C10*Assumptions!C11/1000*'Allocation Keys'!R26 | Q26: =J26*Assumptions!D10*Assumptions!D11/1000*'Allocation Keys'!S26 | R26: =F26*Assumptions!C10*Assumptions!C11/1000*'Allocation Keys'!R26 | S26: ='Life Expectancy'!F26 | T26: =S26+V26 | U26: =O26*-0.00981054 | V26: =P26*-0.00979661 | W26: =Q26*-0.00977217 | X26: =V26*12 | Y26: =R26*-0.00980428
A27: 26 | B27: Maricopa | C27: ='Allocation Keys'!C27 | D27: ='Allocation Keys'!D27 | E27: =Assumptions!B2*'Allocation Keys'!F27+Assumptions!B3*'Allocation Keys'!G27+Assumptions!B4*'Allocation Keys'!K27 | F27: =Assumptions!C2*'Allocation Keys'!F27+Assumptions!C3*'Allocation Keys'!G27+Assumptions!C4*'Allocation Keys'!K27 | G27: =Assumptions!D2*'Allocation Keys'!F27+Assumptions!D3*'Allocation Keys'!G27+Assumptions!D4*'Allocation Keys'!K27 | H27: =Assumptions!B5*(Assumptions!B6*'Allocation Keys'!G27+Assumptions!B7*'Allocation Keys'!F27+Assumptions!B8*'Allocation Keys'!K27+Assumptions!B9*'Allocation Keys'!I27) | I27: =Assumptions!C5*(Assumptions!C6*'Allocation Keys'!G27+Assumptions!C7*'Allocation Keys'!F27+Assumptions!C8*'Allocation Keys'!K27+Assumptions!C9*'Allocation Keys'!I27) | J27: =Assumptions!D5*(Assumptions!D6*'Allocation Keys'!G27+Assumptions!D7*'Allocation Keys'!F27+Assumptions!D8*'Allocation Keys'!K27+Assumptions!D9*'Allocation Keys'!I27) | K27: =I27/D27 | L27: =I27/C27*1000 | M27: =I27-Assumptions!C5*Assumptions!C9*'Allocation Keys'!I27 | N27: =I27*Assumptions!C10 | O27: =H27*Assumptions!B10*Assumptions!B11/1000*'Allocation Keys'!Q27 | P27: =I27*Assumptions!C10*Assumptions!C11/1000*'Allocation Keys'!R27 | Q27: =J27*Assumptions!D10*Assumptions!D11/1000*'Allocation Keys'!S27 | R27: =F27*Assumptions!C10*Assumptions!C11/1000*'Allocation Keys'!R27 | S27: ='Life Expectancy'!F27 | T27: =S27+V27 | U27: =O27*-0.00958228 | V27: =P27*-0.00955633 | W27: =Q27*-0.0095109 | X27: =V27*12 | Y27: =R27*-0.00956956
A28: 27 | B28: Maricopa | C28: ='Allocation Keys'!C28 | D28: ='Allocation Keys'!D28 | E28: =Assumptions!B2*'Allocation Keys'!F28+Assumptions!B3*'Allocation Keys'!G28+Assumptions!B4*'Allocation Keys'!K28 | F28: =Assumptions!C2*'Allocation Keys'!F28+Assumptions!C3*'Allocation Keys'!G28+Assumptions!C4*'Allocation Keys'!K28 | G28: =Assumptions!D2*'Allocation Keys'!F28+Assumptions!D3*'Allocation Keys'!G28+Assumptions!D4*'Allocation Keys'!K28 | H28: =Assumptions!B5*(Assumptions!B6*'Allocation Keys'!G28+Assumptions!B7*'Allocation Keys'!F28+Assumptions!B8*'Allocation Keys'!K28+Assumptions!B9*'Allocation Keys'!I28) | I28: =Assumptions!C5*(Assumptions!C6*'Allocation Keys'!G28+Assumptions!C7*'Allocation Keys'!F28+Assumptions!C8*'Allocation Keys'!K28+Assumptions!C9*'Allocation Keys'!I28) | J28: =Assumptions!D5*(Assumptions!D6*'Allocation Keys'!G28+Assumptions!D7*'Allocation Keys'!F28+Assumptions!D8*'Allocation Keys'!K28+Assumptions!D9*'Allocation Keys'!I28) | K28: =I28/D28 | L28: =I28/C28*1000 | M28: =I28-Assumptions!C5*Assumptions!C9*'Allocation Keys'!I28 | N28: =I28*Assumptions!C10 | O28: =H28*Assumptions!B10*Assumptions!B11/1000*'Allocation Keys'!Q28 | P28: =I28*Assumptions!C10*Assumptions!C11/1000*'Allocation Keys'!R28 | Q28: =J28*Assumptions!D10*Assumptions!D11/1000*'Allocation Keys'!S28 | R28: =F28*Assumptions!C10*Assumptions!C11/1000*'Allocation Keys'!R28 | S28: ='Life Expectancy'!F28 | T28: =S28+V28 | U28: =O28*-0.00870763 | V28: =P28*-0.00869489 | W28: =Q28*-0.00867254 | X28: =V28*12 | Y28: =R28*-0.00870183
A29: 28 | B29: Maricopa | C29: ='Allocation Keys'!C29 | D29: ='Allocation Keys'!D29 | E29: =Assumptions!B2*'Allocation Keys'!F29+Assumptions!B3*'Allocation Keys'!G29+Assumptions!B4*'Allocation Keys'!K29 | F29: =Assumptions!C2*'Allocation Keys'!F29+Assumptions!C3*'Allocation Keys'!G29+Assumptions!C4*'Allocation Keys'!K29 | G29: =Assumptions!D2*'Allocation Keys'!F29+Assumptions!D3*'Allocation Keys'!G29+Assumptions!D4*'Allocation Keys'!K29 | H29: =Assumptions!B5*(Assumptions!B6*'Allocation Keys'!G29+Assumptions!B7*'Allocation Keys'!F29+Assumptions!B8*'Allocation Keys'!K29+Assumptions!B9*'Allocation Keys'!I29) | I29: =Assumptions!C5*(Assumptions!C6*'Allocation Keys'!G29+Assumptions!C7*'Allocation Keys'!F29+Assumptions!C8*'Allocation Keys'!K29+Assumptions!C9*'Allocation Keys'!I29) | J29: =Assumptions!D5*(Assumptions!D6*'Allocation Keys'!G29+Assumptions!D7*'Allocation Keys'!F29+Assumptions!D8*'Allocation Keys'!K29+Assumptions!D9*'Allocation Keys'!I29) | K29: =I29/D29 | L29: =I29/C29*1000 | M29: =I29-Assumptions!C5*Assumptions!C9*'Allocation Keys'!I29 | N29: =I29*Assumptions!C10 | O29: =H29*Assumptions!B10*Assumptions!B11/1000*'Allocation Keys'!Q29 | P29: =I29*Assumptions!C10*Assumptions!C11/1000*'Allocation Keys'!R29 | Q29: =J29*Assumptions!D10*Assumptions!D11/1000*'Allocation Keys'!S29 | R29: =F29*Assumptions!C10*Assumptions!C11/1000*'Allocation Keys'!R29 | S29: ='Life Expectancy'!F29 | T29: =S29+V29 | U29: =O29*-0.01013992 | V29: =P29*-0.010131 | W29: =Q29*-0.01011532 | X29: =V29*12 | Y29: =R29*-0.01013511
A30: 29 | B30: Maricopa | C30: ='Allocation Keys'!C30 | D30: ='Allocation Keys'!D30 | E30: =Assumptions!B2*'Allocation Keys'!F30+Assumptions!B3*'Allocation Keys'!G30+Assumptions!B4*'Allocation Keys'!K30 | F30: =Assumptions!C2*'Allocation Keys'!F30+Assumptions!C3*'Allocation Keys'!G30+Assumptions!C4*'Allocation Keys'!K30 | G30: =Assumptions!D2*'Allocation Keys'!F30+Assumptions!D3*'Allocation Keys'!G30+Assumptions!D4*'Allocation Keys'!K30 | H30: =Assumptions!B5*(Assumptions!B6*'Allocation Keys'!G30+Assumptions!B7*'Allocation Keys'!F30+Assumptions!B8*'Allocation Keys'!K30+Assumptions!B9*'Allocation Keys'!I30) | I30: =Assumptions!C5*(Assumptions!C6*'Allocation Keys'!G30+Assumptions!C7*'Allocation Keys'!F30+Assumptions!C8*'Allocation Keys'!K30+Assumptions!C9*'Allocation Keys'!I30) | J30: =Assumptions!D5*(Assumptions!D6*'Allocation Keys'!G30+Assumptions!D7*'Allocation Keys'!F30+Assumptions!D8*'Allocation Keys'!K30+Assumptions!D9*'Allocation Keys'!I30) | K30: =I30/D30 | L30: =I30/C30*1000 | M30: =I30-Assumptions!C5*Assumptions!C9*'Allocation Keys'!I30 | N30: =I30*Assumptions!C10 | O30: =H30*Assumptions!B10*Assumptions!B11/1000*'Allocation Keys'!Q30 | P30: =I30*Assumptions!C10*Assumptions!C11/1000*'Allocation Keys'!R30 | Q30: =J30*Assumptions!D10*Assumptions!D11/1000*'Allocation Keys'!S30 | R30: =F30*Assumptions!C10*Assumptions!C11/1000*'Allocation Keys'!R30 | S30: ='Life Expectancy'!F30 | T30: =S30+V30 | U30: =O30*-0.00917811 | V30: =P30*-0.00916651 | W30: =Q30*-0.00914614 | X30: =V30*12 | Y30: =R30*-0.00917322
A31: 30 | B31: Mohave | C31: ='Allocation Keys'!C31 | D31: ='Allocation Keys'!D31 | E31: =Assumptions!B2*'Allocation Keys'!F31+Assumptions!B3*'Allocation Keys'!G31+Assumptions!B4*'Allocation Keys'!K31 | F31: =Assumptions!C2*'Allocation Keys'!F31+Assumptions!C3*'Allocation Keys'!G31+Assumptions!C4*'Allocation Keys'!K31 | G31: =Assumptions!D2*'Allocation Keys'!F31+Assumptions!D3*'Allocation Keys'!G31+Assumptions!D4*'Allocation Keys'!K31 | H31: =Assumptions!B5*(Assumptions!B6*'Allocation Keys'!G31+Assumptions!B7*'Allocation Keys'!F31+Assumptions!B8*'Allocation Keys'!K31+Assumptions!B9*'Allocation Keys'!I31) | I31: =Assumptions!C5*(Assumptions!C6*'Allocation Keys'!G31+Assumptions!C7*'Allocation Keys'!F31+Assumptions!C8*'Allocation Keys'!K31+Assumptions!C9*'Allocation Keys'!I31) | J31: =Assumptions!D5*(Assumptions!D6*'Allocation Keys'!G31+Assumptions!D7*'Allocation Keys'!F31+Assumptions!D8*'Allocation Keys'!K31+Assumptions!D9*'Allocation Keys'!I31) | K31: =I31/D31 | L31: =I31/C31*1000 | M31: =I31-Assumptions!C5*Assumptions!C9*'Allocation Keys'!I31 | N31: =I31*Assumptions!C10 | O31: =H31*Assumptions!B10*Assumptions!B11/1000*'Allocation Keys'!Q31 | P31: =I31*Assumptions!C10*Assumptions!C11/1000*'Allocation Keys'!R31 | Q31: =J31*Assumptions!D10*Assumptions!D11/1000*'Allocation Keys'!S31 | R31: =F31*Assumptions!C10*Assumptions!C11/1000*'Allocation Keys'!R31 | S31: ='Life Expectancy'!F31 | T31: =S31+V31 | U31: =O31*-0.00765604 | V31: =P31*-0.00764145 | W31: =Q31*-0.00761585 | X31: =V31*12 | Y31: =R31*-0.0076502
A32: Arizona | B32: statewide | C32: =SUM(C2:C31) | D32: =SUM(D2:D31) | E32: =SUM(E2:E31) | F32: =SUM(F2:F31) | G32: =SUM(G2:G31) | H32: =SUM(H2:H31) | I32: =SUM(I2:I31) | J32: =SUM(J2:J31) | K32: =I32/D32 | L32: =I32/C32*1000 | M32: =SUM(M2:M31) | N32: =SUM(N2:N31) | O32: =SUM(O2:O31) | P32: =SUM(P2:P31) | Q32: =SUM(Q2:Q31) | R32: =SUM(R2:R31) | S32: =SUMPRODUCT(S2:S31,C2:C31)/C32 | T32: =SUMPRODUCT(T2:T31,C2:C31)/C32 | U32: =SUMPRODUCT(U2:U31,C2:C31)/C32 | V32: =SUMPRODUCT(V2:V31,C2:C31)/C32 | W32: =SUMPRODUCT(W2:W31,C2:C31)/C32 | X32: =V32*12 | Y32: =SUMPRODUCT(Y2:Y31,C2:C31)/C32
A34: Near term = first full year after the Jan. 1, 2027 start of work requirements and six-month renewals (Urban Institute 2028 projection) plus the Oct. 1, 2026 immigrant-eligibility change. Full phase-in = 2034 (RAND). Low/Central/High is a bounding envelope. Deaths are steady-state annual figures. Life expectancy change is a period life-table effect (see README and Method & Caveats). Population-weighted statewide life expectancy values are shown in the Arizona row.

Sheet Assumptions
A1: Parameter | B1: Low | C1: Central | D1: High | E1: Units / population | F1: Source (see Sources sheet)
A2: NEAR TERM (first full year, 2028): six-month redeterminations, AZ expansion enrollment decline | B2: 56000 | C2: 91000 | D2: 91000 | E2: expansion adults (allocated by expansion-adult key) | F2: Urban Institute, Mar 25 2026, Appendix Table A.2 (high/medium/low mitigation) — https://www.urban.org/research/publication/projected-reductions-medicaid-expansion-enrollment-under-obbbas-work
A3: NEAR TERM: work requirement, incremental AZ expansion enrollment decline | B3: 67000 | C3: 106000 | D3: 155000 | E3: non-AIAN expansion adults (allocated by work-requirement key) | F3: Urban Institute, Mar 25 2026, Appendix Table A.2 (totals 123k / 197k / 246k, Table 3)
A4: NEAR TERM: Oct 1 2026 immigrant-eligibility provision (refugees, asylees, parolees) | B4: 11132 | C4: 22263 | D4: 34263 | E4: noncitizens with public coverage, excluding Mexico/Cuba/Haiti-born share | F4: AHCCCS advance notices: 22,263 (AzPHA Aug 31 2026). Low = half retain coverage; High = notices + ~12,000 SSI recipients under review
A5: FULL PHASE-IN (2034): total AZ Medicaid enrollment decline | B5: 248030.3 | C5: 327400 | D5: 406769.7 | E5: all enrollees; low/high = KFF/CBO band (250/330, 410/330) applied to RAND central | F5: RAND RRA4098-1-v2 (June 18 2026) Table B.15: -327,400; KFF Aug 20 2025 range
A6: share: work requirement (198.8k of 369.2k gross) | B6: 0.53846154 | C6: 0.53846154 | D6: 0.53846154 | E6: allocated by work-requirement key (AIAN excluded) | F6: RAND Table B.15 provision values, scaled to deduplicated total
A7: share: six-month redeterminations (65.7k) | B7: 0.17795233 | C7: 0.17795233 | D7: 0.17795233 | E7: allocated by expansion-adult key | F7: RAND Table B.15
A8: share: immigrant eligibility + emergency FMAP (5.0k + 2.3k) | B8: 0.019772481 | C8: 0.019772481 | D8: 0.019772481 | E8: allocated by noncitizen key | F8: RAND Table B.15
A9: share: provider-tax retrenchment + error-payment rule (94.2k + 3.2k) | B9: 0.26381365 | C9: 0.26381365 | D9: 0.26381365 | E9: allocated by adult (19-64) Medicaid key | F9: RAND Table B.15 (behavioral assumption: states trim optional eligibility as provider-tax revenue falls)
A10: Uninsured per person losing Medicaid enrollment | B10: 0.75728155 | C10: 0.75728155 | D10: 0.75728155 | E10: ratio | F10: CBO via KFF Jun 4 2025: 7.8M uninsured / 10.3M fewer enrollees (House bill). Enacted-law cross-check ~0.68 (KFF Feb 2026: -11M enrollees, +7.5M uninsured)
A11: Additional deaths per 1,000 uninsured person-years | B11: 1.2 | C11: 2.2 | D11: 3.6 | E11: deaths / 1,000 / year, adults 19-64 | F11: Low: Sommers, Long & Baicker 2014 (NNT 830). Central: Gaffney et al. 2025 implied (16,642/7.6M). High: Sommers 2017 (1 per 239-316)
A13: Calibration constant c (excess death rate of a person losing coverage ÷ Arizona age-specific death rate) | B13: 0.26504166 | C13: 0.48590971 | D13: 0.79512498 | E13: solved so statewide deaths per 1,000 uninsured equal the row above
A14: Note: near-term scenarios use the same death rates; c differs trivially (see assumptions.json).

Sheet Allocation Keys
A1: LD | B1: Main county | C1: 2020 population | D1: Adults 19-64 (ACS civ. noninst.) | E1: Expansion-adult key (calibrated count) | F1: Expansion-adult share | G1: Work-requirement key share (AIAN excluded) | H1: AIAN share of district expansion adults | I1: Adult (19-64) Medicaid key share | J1: Total Medicaid (all ages) key share | K1: Noncitizen (non-Mexico/Cuba/Haiti) public-coverage key share | L1: Age share 19-25 | M1: Age share 26-34 | N1: Age share 35-44 | O1: Age share 45-54 | P1: Age share 55-64 | Q1: Death-rate factor vs state (low) | R1: Death-rate factor (central) | S1: Death-rate factor (high)
A2: 1 | B2: Yavapai | C2: 237896 | D2: 120914 | E2: 12426.652 | F2: 0.026244284 | G2: 0.028313868 | H2: 0.040946688 | I2: 0.027213962 | J2: 0.027041639 | K2: 0.018813143 | L2: 0.11138458 | M2: 0.17210958 | N2: 0.16265221 | O2: 0.18034426 | P2: 0.37350936 | Q2: 1.2563173 | R2: 1.2563173 | S2: 1.2563173
A3: 2 | B3: Maricopa | C3: 246674 | D3: 159876 | E3: 16489.018 | F3: 0.034823736 | G3: 0.037260349 | H3: 0.048847788 | I3: 0.031941429 | J3: 0.031953256 | K3: 0.056766473 | L3: 0.1251577 | M3: 0.25850244 | N3: 0.20384734 | O3: 0.18999945 | P3: 0.22249306 | Q3: 0.9961552 | R3: 0.9961552 | S3: 0.9961552
A4: 3 | B4: Maricopa | C4: 236955 | D4: 125730 | E4: 4223.6725 | F4: 0.0089201223 | G4: 0.0094892322 | H4: 0.054329857 | I4: 0.0089902697 | J4: 0.010811207 | K4: 0.032548794 | L4: 0.1050948 | M4: 0.18029637 | N4: 0.17830112 | O4: 0.20373386 | P4: 0.33257384 | Q4: 1.2019897 | R4: 1.2019897 | S4: 1.2019897
A5: 4 | B5: Maricopa | C5: 244298 | D5: 146554 | E5: 8221.9863 | F5: 0.017364302 | G5: 0.018839894 | H5: 0.035506321 | I5: 0.015347771 | J5: 0.013689739 | K5: 0.03208145 | L5: 0.10316394 | M5: 0.18769124 | N5: 0.21793052 | O5: 0.1965691 | P5: 0.29464519 | Q5: 1.1381859 | R5: 1.1381859 | S5: 1.1381859
A6: 5 | B6: Maricopa | C6: 239088 | D6: 159734 | E6: 18566.09 | F6: 0.039210376 | G6: 0.040538174 | H6: 0.081299414 | I6: 0.040390859 | J6: 0.037578141 | K6: 0.040101309 | L6: 0.14020597 | M6: 0.25617104 | N6: 0.19869433 | O6: 0.18846875 | P6: 0.21645991 | Q6: 0.98015346 | R6: 0.98015346 | S6: 0.98015346
A7: 6 | B7: Coconino | C7: 225474 | D7: 125803 | E7: 30903.343 | F7: 0.065265856 | G7: 0.018948961 | H7: 0.74190617 | I7: 0.053675597 | J7: 0.050086375 | K7: 0.0098619278 | L7: 0.16894419 | M7: 0.23594162 | N7: 0.20600332 | O7: 0.16281266 | P7: 0.22629822 | Q7: 0.97757641 | R7: 0.97757641 | S7: 0.97757641
A8: 7 | B8: Pinal | C8: 240214 | D8: 128337 | E8: 13941.726 | F8: 0.02944402 | G8: 0.029522395 | H8: 0.10852114 | I8: 0.027381135 | J8: 0.028149325 | K8: 0.018680576 | L8: 0.15885086 | M8: 0.17619518 | N8: 0.18539407 | O8: 0.17479183 | P8: 0.30476806 | Q8: 1.1243253 | R8: 1.1243253 | S8: 1.1243253
A9: 8 | B9: Maricopa | C9: 244166 | D9: 181692 | E9: 16541.343 | F9: 0.034934244 | G9: 0.034046183 | H9: 0.13126631 | I9: 0.033869847 | J9: 0.030022708 | K9: 0.050146236 | L9: 0.21270505 | M9: 0.26342048 | N9: 0.19335877 | O9: 0.14372519 | P9: 0.18679052 | Q9: 0.88258369 | R9: 0.88258369 | S9: 0.88258369
A10: 9 | B10: Maricopa | C10: 238117 | D10: 147383 | E10: 18277.538 | F10: 0.038600973 | G10: 0.039558466 | H10: 0.08899775 | I10: 0.040705374 | J10: 0.040872502 | K10: 0.031878304 | L10: 0.17343243 | M10: 0.25030763 | N10: 0.21740776 | O10: 0.16619418 | P10: 0.192658 | Q10: 0.92062483 | R10: 0.92062483 | S10: 0.92062483
A11: 10 | B11: Maricopa | C11: 235579 | D11: 127492 | E11: 9979.5924 | F11: 0.021076252 | G11: 0.022652689 | H11: 0.044592054 | I11: 0.024951683 | J11: 0.024913855 | K11: 0.039933247 | L11: 0.11496395 | M11: 0.18159543 | N11: 0.1698216 | O11: 0.19003756 | P11: 0.34358146 | Q11: 1.209315 | R11: 1.209315 | S11: 1.209315
A12: 11 | B12: Maricopa | C12: 237844 | D12: 143724 | E12: 21846.939 | F12: 0.046139317 | G12: 0.047583863 | H12: 0.083216473 | I12: 0.04757338 | J12: 0.049680737 | K12: 0.040143628 | L12: 0.20006544 | M12: 0.20851643 | N12: 0.21626054 | O12: 0.17096603 | P12: 0.20419157 | Q12: 0.93897627 | R12: 0.93897627 | S12: 0.93897627
A13: 12 | B13: Maricopa | C13: 238923 | D13: 155532 | E13: 8755.0651 | F13: 0.018490129 | G13: 0.017851304 | H13: 0.14172159 | I13: 0.019450538 | J13: 0.018848944 | K13: 0.033104981 | L13: 0.13161292 | M13: 0.23349677 | N13: 0.24000039 | O13: 0.18508717 | P13: 0.20980275 | Q13: 0.97694191 | R13: 0.97694191 | S13: 0.97694191
... A31: 30 | B31: Mohave | C31: 237999 | D31: 118280 | E31: 17491.784 | F31: 0.036941512 | G31: 0.039130111 | H31: 0.058381576 | I31: 0.039516824 | J31: 0.038079742 | K31: 0.031560958 | L31: 0.10035761 | M31: 0.17519028 | N31: 0.1699825 | O31: 0.19337902 | P31: 0.36109058 | Q31: 1.2459929 | R31: 1.2459929 | S31: 1.2459929
A33: Total | C33: =SUM(C2:C31) | D33: =SUM(D2:D31) | E33: =SUM(E2:E31) | F33: =SUM(F2:F31) | G33: =SUM(G2:G31) | I33: =SUM(I2:I31) | J33: =SUM(J2:J31) | K33: =SUM(K2:K31)
A35: Keys: ACS 2020-2024 5-year tract tables (C27007, B27010, B18135, B27020, B05006, B27003, B27001) distributed to 2020 census blocks by population and summed to 2022 legislative districts; expansion-adult key = adults 19-64 with Medicaid, excluding Medicare dual-eligibles and adults reporting a disability, calibrated to AHCCCS expansion enrollment by congressional district (Jan 2025); all-ages and adult keys calibrated to AHCCCS enrollment by county (Aug 2026). AIAN share from 2020 Census P3 (AIAN alone, 18+) with the adult Medicaid rate of AIAN-majority tracts (40.4%). Death-rate factor = district deaths per uninsured relative to the statewide rate; it reflects only the district's age profile of adults with public coverage (older = higher).

Sheet Calibration
A1: Congressional district (118th) | B1: ACS-based expansion-adult key (uncalibrated) | C1: AHCCCS expansion enrollment, Jan 1 2025 (Prop 204 + ACA adults) | D1: ACS share | E1: AHCCCS share | F1: Calibration factor
A2: AZ-1 | B2: 32639.769 | C2: 38581 | D2: =B2/SUM($B$2:$B$10) | E2: =C2/SUM($C$2:$C$10) | F2: =E2/D2
A3: AZ-2 | B3: 63652.15 | C3: 67937 | D3: =B3/SUM($B$2:$B$10) | E3: =C3/SUM($C$2:$C$10) | F3: =E3/D3
A4: AZ-3 | B4: 85770.988 | C4: 87035 | D4: =B4/SUM($B$2:$B$10) | E4: =C4/SUM($C$2:$C$10) | F4: =E4/D4
A5: AZ-4 | B5: 44039.675 | C5: 45853 | D5: =B5/SUM($B$2:$B$10) | E5: =C5/SUM($C$2:$C$10) | F5: =E5/D5
A6: AZ-5 | B6: 27340.777 | C6: 29032 | D6: =B6/SUM($B$2:$B$10) | E6: =C6/SUM($C$2:$C$10) | F6: =E6/D6
A7: AZ-6 | B7: 44989.921 | C7: 46429 | D7: =B7/SUM($B$2:$B$10) | E7: =C7/SUM($C$2:$C$10) | F7: =E7/D7
A8: AZ-7 | B8: 85563.067 | C8: 81398 | D8: =B8/SUM($B$2:$B$10) | E8: =C8/SUM($C$2:$C$10) | F8: =E8/D8
A9: AZ-8 | B9: 40463.993 | C9: 47903 | D9: =B9/SUM($B$2:$B$10) | E9: =C9/SUM($C$2:$C$10) | F9: =E9/D9
A10: AZ-9 | B10: 49039.054 | C10: 54379 | D10: =B10/SUM($B$2:$B$10) | E10: =C10/SUM($C$2:$C$10) | F10: =E10/D10
A11: Total | B11: =SUM(B2:B10) | C11: =SUM(C2:C10)
A12: Source: Health Management Associates for AHCCCS, "AHCCCS Data to Inform Potential Federal Medicaid Changes — by Congressional District", Table 1 (Jan 1 2025). https://www.azahcccs.gov/AHCCCS/Downloads/AHCCCS_Data_to_Inform_by_Congressional%20District.pdf . The ACS-based key sums to 473,500 vs 500,151 actual; factors 0.90–1.12 indicate the ACS proxy tracks administrative enrollment closely.
A14: County | B14: ACS Medicaid (all ages) | C14: AHCCCS enrollment Aug 1 2026 | D14: ACS share | E14: AHCCCS share | F14: Calibration factor
A15: Apache | B15: 28958 | C15: 29191 | D15: =B15/SUM($B$15:$B$29) | E15: =C15/SUM($C$15:$C$29) | F15: =E15/D15
A16: Cochise | B16: 32497 | C16: 36658 | D16: =B16/SUM($B$15:$B$29) | E16: =C16/SUM($C$15:$C$29) | F16: =E16/D16
A17: Coconino | B17: 31643 | C17: 30136 | D17: =B17/SUM($B$15:$B$29) | E17: =C17/SUM($C$15:$C$29) | F17: =E17/D17
A18: Gila | B18: 13082 | C18: 11107 | D18: =B18/SUM($B$15:$B$29) | E18: =C18/SUM($C$15:$C$29) | F18: =E18/D18
A19: Graham | B19: 11243 | C19: 14834 | D19: =B19/SUM($B$15:$B$29) | E19: =C19/SUM($C$15:$C$29) | F19: =E19/D19
A20: Greenlee | B20: 933 | C20: 1455 | D20: =B20/SUM($B$15:$B$29) | E20: =C20/SUM($C$15:$C$29) | F20: =E20/D20
A21: La Paz | B21: 4014 | C21: 5467 | D21: =B21/SUM($B$15:$B$29) | E21: =C21/SUM($C$15:$C$29) | F21: =E21/D21
A22: Maricopa | B22: 822319 | C22: 1028695 | D22: =B22/SUM($B$15:$B$29) | E22: =C22/SUM($C$15:$C$29) | F22: =E22/D22
A23: Mohave | B23: 52190 | C23: 61164 | D23: =B23/SUM($B$15:$B$29) | E23: =C23/SUM($C$15:$C$29) | F23: =E23/D23
A24: Navajo | B24: 36826 | C24: 44195 | D24: =B24/SUM($B$15:$B$29) | E24: =C24/SUM($C$15:$C$29) | F24: =E24/D24
A25: Pima | B25: 229387 | C25: 258306 | D25: =B25/SUM($B$15:$B$29) | E25: =C25/SUM($C$15:$C$29) | F25: =E25/D25
A26: Pinal | B26: 89975 | C26: 103063 | D26: =B26/SUM($B$15:$B$29) | E26: =C26/SUM($C$15:$C$29) | F26: =E26/D26
... A29: Yuma | B29: 65139 | C29: 80652 | D29: =B29/SUM($B$15:$B$29) | E29: =C29/SUM($C$15:$C$29) | F29: =E29/D29
A30: Total | B30: =SUM(B15:B29) | C30: =SUM(C15:C29)
A31: Source: AHCCCS Population by County, Aug 1 2026 (report dated 08/06/2026). https://www.azahcccs.gov/Resources/Downloads/PopulationStatistics/PopulationbyCounty08062026.pdf . ACS understates administrative enrollment (~1.48M vs 1.77M) for well-known survey reasons; only shares are used.

Sheet Life Expectancy
A1: LD | B1: Main county | C1: USALEEP tract life expectancy, 2010-2015 (pop-weighted) | D1: Share of 2020 population in tracts with a USALEEP estimate | E1: Lowest / highest tract (calibrated) | F1: Baseline life expectancy, calibrated to 2020-2022 county data | G1: Reference: calibrated to CHR 2017-2019 county series (different method; see note) | H1: Model e0 with H.R. 1 — full phase-in Low | I1: Central | J1: High | K1: Model e0 — near term Central
A2: 1 | B2: Yavapai | C2: 78.884483 | D2: 0.92928843 | E2: 65.6 / 86.0 | F2: 76.456088 | G2: 79.049471 | H2: 76.391012 | I2: 76.298818 | J2: 76.137112 | K2: 76.354478
A3: 2 | B3: Maricopa | C3: 78.241091 | D3: 0.90154212 | E3: 69.5 / 82.1 | F3: 76.944711 | G3: 79.953905 | H3: 76.877792 | I3: 76.78299 | J3: 76.616721 | K3: 76.829065
A4: 3 | B4: Maricopa | C4: 82.428321 | D4: 0.87929354 | E4: 64.5 / 89.5 | F4: 81.131941 | G4: 84.141135 | H4: 81.106123 | I4: 81.069491 | J4: 81.005077 | K4: 81.08203
A5: 4 | B5: Maricopa | C5: 81.29392 | D5: 0.9439496 | E5: 73.8 / 89.2 | F5: 79.99754 | G5: 83.006734 | H5: 79.95762 | I5: 79.90101 | J5: 79.801553 | K5: 79.926935
A6: 5 | B6: Maricopa | C6: 76.393375 | D6: 0.88194305 | E6: 68.8 / 82.2 | F6: 75.096994 | G6: 78.106188 | H6: 75.023289 | I6: 74.91892 | J6: 74.736002 | K6: 74.978608
A7: 6 | B7: Coconino | C7: 76.423048 | D7: 0.94353673 | E7: 61.8 / 82.4 | F7: 68.759804 | G7: 74.847074 | H7: 68.696994 | I7: 68.608041 | J7: 68.452106 | K7: 68.655109
A8: 7 | B8: Pinal | C8: 79.910081 | D8: 0.81659687 | E8: 65.1 / 86.2 | F8: 74.792369 | G8: 79.605868 | H8: 74.728679 | I8: 74.638455 | J8: 74.480224 | K8: 74.69048
A9: 8 | B9: Maricopa | C9: 78.295486 | D9: 0.80759811 | E9: 64.5 / 89.2 | F9: 76.999106 | G9: 80.0083 | H9: 76.933102 | I9: 76.839605 | J9: 76.675645 | K9: 76.887386
A10: 9 | B10: Maricopa | C10: 77.300384 | D10: 1 | E10: 65.2 / 81.1 | F10: 76.004003 | G10: 79.013197 | H10: 75.925274 | I10: 75.813796 | J10: 75.618433 | K10: 75.880288
A11: 10 | B11: Maricopa | C11: 78.989166 | D11: 0.92557062 | E11: 64.5 / 83.5 | F11: 77.694924 | G11: 80.784812 | H11: 77.639349 | I11: 77.560587 | J11: 77.422362 | K11: 77.603277
A12: 11 | B12: Maricopa | C12: 76.306926 | D12: 0.81869208 | E12: 66.4 / 79.8 | F12: 75.010545 | G12: 78.019739 | H12: 74.918741 | I12: 74.788822 | J12: 74.561345 | K12: 74.864942
A13: 12 | B13: Maricopa | C13: 80.547516 | D13: 0.88090724 | E13: 75.1 / 82.9 | F13: 79.251135 | G13: 82.260329 | H13: 79.213453 | I13: 79.160009 | J13: 79.066103 | K13: 79.186926
... A31: 30 | B31: Mohave | C31: 75.945615 | D31: 0.87809613 | E31: 61.8 / 86.0 | F31: 72.809375 | G31: 76.376474 | H31: 72.726181 | I31: 72.608428 | J31: 72.402206 | K31: 72.679027
A34: County | B34: CHR 2025 life expectancy (NCHS 2020-2022) | C34: USALEEP 2010-2015 county mean (pop-weighted) | D34: Shift applied to every tract in county | E34: CHR 2021 life expectancy (NCHS 2017-2019) | F34: Shift (reference series)
A35: Apache | B35: 63.845346 | C35: 75.773496 | D35: =B35-C35 | E35: 73.099519 | F35: =E35-C35
A36: Cochise | B36: 76.089432 | C36: 78.558155 | D36: =B36-C36 | E36: 78.728998 | F36: =E36-C36
A37: Coconino | B37: 75.86447 | C37: 78.897733 | D37: =B37-C37 | E37: 79.120676 | F37: =E37-C37
A38: Gila | B38: 69.593727 | C38: 78.099426 | D38: =B38-C38 | E38: 74.321029 | F38: =E38-C38
A39: Graham | B39: 73.543255 | C39: 78.312828 | D39: =B39-C39 | E39: 77.709961 | F39: =E39-C39
A40: Greenlee | B40: 75.103455 | C40: 82.939332 | D40: =B40-C40 | E40: 81.003169 | F40: =E40-C40
A41: La Paz | B41: 69.329962 | C41: 76.511855 | D41: =B41-C41 | E41: 77.159998 | F41: =E41-C41
A42: Maricopa | B42: 77.470432 | C42: 78.766812 | D42: =B42-C42 | E42: 80.479626 | F42: =E42-C42
A43: Mohave | B43: 72.784225 | C43: 75.659962 | D43: =B43-C43 | E43: 76.011306 | F43: =E43-C43
A44: Navajo | B44: 67.131288 | C44: 76.880467 | D44: =B44-C44 | E44: 73.868617 | F44: =E44-C44
A45: Pima | B45: 76.485899 | C45: 78.569969 | D45: =B45-C45 | E45: 79.508356 | F45: =E45-C45
A46: Pinal | B46: 78.111968 | C46: 79.369761 | D46: =B46-C46 | E46: 82.577098 | F46: =E46-C46
... A49: Yuma | B49: 77.788101 | C49: 78.169918 | D49: =B49-C49 | E49: 82.94516 | F49: =E49-C49
A51: Method: CDC/NCHS USALEEP census-tract life expectancy (2010-2015, 2010 tracts) is assigned to 2020 census blocks, shifted by a county constant so the county population-weighted mean equals the County Health Rankings 2025 value (NCHS deaths 2020-2022), and population-weighted to legislative districts over blocks with an estimate. Statewide result 76.73 matches NCHS Arizona 2022 (76.7). The 2020-2022 anchor embeds pandemic-period mortality — the drop is largest in Apache (-11.9 yrs vs USALEEP), Navajo (-9.8) and Gila (-8.5), affecting LDs 6 and 7. The 2017-2019 reference column uses the CHR 2021 series, whose statewide value (80.0) runs about 1.2 years above NCHS 2019 (78.8) because of method differences; use it only to gauge the pandemic effect, not as a baseline. New life expectancy = Arizona 2022 single-year life table (NCHS NVSR 74-12) scaled to the district baseline, with age-specific death rates at 19-64 raised by the district's additional deaths divided by its population in each age band (Chiang single-year method).

Sheet ZIP Code Life Expectancy
A1: ZCTA (ZIP Code Tabulation Area) | B1: Main county | C1: 2020 population | D1: Share of population with a USALEEP estimate | E1: USALEEP life expectancy 2010-2015 | F1: Life expectancy calibrated to 2020-2022 county level | G1: Primary legislative district | H1: Share of ZCTA population in primary LD | I1: All overlapping LDs (>=2% of ZCTA population)
A2: 84531 | B2: Apache | C2: 9 | D2: 1 | E2: 75.1 | F2: 63.17185 | G2: 6 | H2: 1 | I2: LD6 (100%)
A3: 84536 | B3: Navajo | C3: 117 | D3: 1 | E3: 75.1 | F3: 65.350821 | G3: 6 | H3: 1 | I3: LD6 (100%)
A4: 85003 | B4: Maricopa | C4: 11042 | D4: 0.43542836 | E4: 78.310545 | F4: 77.014165 | G4: 5 | H4: 0.51548632 | I4: LD5 (52%); LD11 (48%)
A5: 85004 | B5: Maricopa | C5: 8833 | D5: 0.36839126 | E5: 78.169945 | F5: 76.873564 | G5: 5 | H5: 0.83301257 | I5: LD5 (83%); LD11 (17%)
A6: 85006 | B6: Maricopa | C6: 23797 | D6: 0.86582342 | E6: 76.005552 | F6: 74.709172 | G6: 5 | H6: 0.92994915 | I6: LD5 (93%); LD11 (7%)
A7: 85007 | B7: Maricopa | C7: 14442 | D7: 0.59500069 | E7: 74.716513 | F7: 73.420133 | G7: 11 | H7: 0.51412547 | I7: LD11 (51%); LD5 (49%)
A8: 85008 | B8: Maricopa | C8: 59047 | D8: 0.69807103 | E8: 76.613567 | F8: 75.317186 | G8: 8 | H8: 0.60555151 | I8: LD8 (61%); LD5 (35%); LD11 (5%)
A9: 85009 | B9: Maricopa | C9: 50439 | D9: 0.99978191 | E9: 76.017455 | F9: 74.721074 | G9: 26 | H9: 0.64862507 | I9: LD26 (65%); LD11 (34%)
A10: 85012 | B10: Maricopa | C10: 8201 | D10: 1 | E10: 76.433496 | F10: 75.137116 | G10: 5 | H10: 1 | I10: LD5 (100%)
A11: 85013 | B11: Maricopa | C11: 21970 | D11: 1 | E11: 74.548716 | F11: 73.252336 | G11: 5 | H11: 0.91556668 | I11: LD5 (92%); LD26 (8%)
A12: 85014 | B12: Maricopa | C12: 26381 | D12: 0.90739547 | E12: 77.622876 | F12: 76.326495 | G12: 5 | H12: 1 | I12: LD5 (100%)
A13: 85015 | B13: Maricopa | C13: 41436 | D13: 1 | E13: 75.747582 | F13: 74.451201 | G13: 26 | H13: 0.71915725 | I13: LD26 (72%); LD5 (28%)
... A49: 85120 | B49: Pinal | C49: 30605 | D49: 0.90161738 | E49: 76.222643 | F49: 74.962019 | G49: 10 | H49: 0.559157 | I49: LD10 (56%); LD7 (44%)
A50: 85121 | B50: Pinal | C50: 2802 | D50: 0 | G50: 16 | H50: 1 | I50: LD16 (100%)
A51: 85122 | B51: Pinal | C51: 55063 | D51: 1 | E51: 78.425338 | F51: 77.167545 | G51: 16 | H51: 1 | I51: LD16 (100%)
A52: 85123 | B52: Pinal | C52: 9965 | D52: 1 | E52: 77.019137 | F52: 75.761344 | G52: 16 | H52: 1 | I52: LD16 (100%)
A53: 85128 | B53: Pinal | C53: 15764 | D53: 1 | E53: 77.901643 | F53: 76.64385 | G53: 16 | H53: 1 | I53: LD16 (100%)
A54: 85131 | B54: Pinal | C54: 16723 | D54: 0.60383902 | E54: 78.576114 | F54: 77.318321 | G54: 16 | H54: 1 | I54: LD16 (100%)
A55: 85132 | B55: Pinal | C55: 38848 | D55: 0.57125206 | E55: 84.374635 | F55: 83.116842 | G55: 7 | H55: 0.72904654 | I55: LD7 (73%); LD16 (27%)
A56: 85135 | B56: Gila | C56: 519 | D56: 1 | E56: 77.8 | F56: 69.294301 | G56: 7 | H56: 1 | I56: LD7 (100%)
A57: 85137 | B57: Pinal | C57: 2021 | D57: 1 | E57: 81.214795 | F57: 79.957001 | G57: 7 | H57: 1 | I57: LD7 (100%)
A58: 85138 | B58: Pinal | C58: 46914 | D58: 0.76382317 | E58: 79.30281 | F58: 78.045017 | G58: 16 | H58: 1 | I58: LD16 (100%)
A59: 85139 | B59: Pinal | C59: 18137 | D59: 0.68748966 | E59: 78.083872 | F59: 76.825868 | G59: 16 | H59: 0.99575453 | I59: LD16 (100%)
A60: 85140 | B60: Pinal | C60: 45381 | D60: 0.76294044 | E60: 81.156052 | F60: 79.898259 | G60: 15 | H60: 1 | I60: LD15 (100%)
A61: 85141 | B61: Pinal | C61: 416 | D61: 1 | E61: 76.711058 | F61: 75.453265 | G61: 16 | H61: 1 | I61: LD16 (100%)
A62: 85142 | B62: Maricopa | C62: 80734 | D62: 0.84135556 | E62: 79.825305 | F62: 78.542106 | G62: 15 | H62: 0.96176332 | I62: LD15 (96%); LD14 (4%)
... A89: 85234 | B89: Maricopa | C89: 51051 | D89: 0.91716127 | E89: 80.465815 | F89: 79.169435 | G89: 14 | H89: 0.99234099 | I89: LD14 (99%)
A90: 85236 | B90: Maricopa | C90: 42 | D90: 0 | G90: 14 | H90: 1 | I90: LD14 (100%)
A91: 85248 | B91: Maricopa | C91: 38567 | D91: 0.62530142 | E91: 81.448296 | F91: 80.152467 | G91: 13 | H91: 0.97904945 | I91: LD13 (98%); LD16 (2%)
A92: 85249 | B92: Maricopa | C92: 47414 | D92: 0.93856245 | E92: 81.258767 | F92: 79.962387 | G92: 13 | H92: 0.81870334 | I92: LD13 (82%); LD14 (18%)
A93: 85250 | B93: Maricopa | C93: 16501 | D93: 0.99800012 | E93: 81.519553 | F93: 80.223173 | G93: 4 | H93: 0.9770923 | I93: LD4 (98%); LD8 (2%)
A94: 85251 | B94: Maricopa | C94: 40073 | D94: 0.75557108 | E94: 81.379979 | F94: 80.083599 | G94: 8 | H94: 0.92887979 | I94: LD8 (93%); LD4 (7%)
A95: 85253 | B95: Maricopa | C95: 17358 | D95: 1 | E95: 82.709085 | F95: 81.412705 | G95: 4 | H95: 1 | I95: LD4 (100%)
A96: 85254 | B96: Maricopa | C96: 46352 | D96: 1 | E96: 80.631578 | F96: 79.335198 | G96: 4 | H96: 1 | I96: LD4 (100%)
A97: 85255 | B97: Maricopa | C97: 44976 | D97: 0.90574973 | E97: 82.563588 | F97: 81.267208 | G97: 3 | H97: 0.91837869 | I97: LD3 (92%); LD4 (8%)
A98: 85256 | B98: Maricopa | C98: 4857 | D98: 1 | E98: 65.8 | F98: 64.50362 | G98: 8 | H98: 1 | I98: LD8 (100%)
A99: 85257 | B99: Maricopa | C99: 29187 | D99: 1 | E99: 78.066831 | F99: 76.770451 | G99: 8 | H99: 1 | I99: LD8 (100%)
A100: 85258 | B100: Maricopa | C100: 25203 | D100: 0.73066698 | E100: 82.578458 | F100: 81.282077 | G100: 4 | H100: 0.75986986 | I100: LD4 (76%); LD3 (24%)
A101: 85259 | B101: Maricopa | C101: 22548 | D101: 1 | E101: 81.199681 | F101: 79.9033 | G101: 3 | H101: 1 | I101: LD3 (100%)
A102: 85260 | B102: Maricopa | C102: 37967 | D102: 0.81059868 | E102: 81.240934 | F102: 79.944554 | G102: 4 | H102: 0.683699 | I102: LD4 (68%); LD3 (32%)
... A124: 85308 | B124: Maricopa | C124: 66540 | D124: 1 | E124: 79.228885 | F124: 77.932505 | G124: 27 | H124: 0.80676285 | I124: LD27 (81%); LD2 (19%)
A125: 85309 | B125: Maricopa | C125: 985 | D125: 0 | G125: 29 | H125: 1 | I125: LD29 (100%)
A126: 85310 | B126: Maricopa | C126: 19315 | D126: 0.66114419 | E126: 77.949468 | F126: 76.653087 | G126: 28 | H126: 0.68941237 | I126: LD28 (69%); LD27 (29%)
A127: 85320 | B127: Maricopa | C127: 800 | D127: 1 | E127: 82.4 | F127: 81.10362 | G127: 30 | H127: 1 | I127: LD30 (100%)
A128: 85321 | B128: Pima | C128: 3663 | D128: 0.10537811 | E128: 76.1 | F128: 74.015929 | G128: 23 | H128: 1 | I128: LD23 (100%)
A129: 85322 | B129: Maricopa | C129: 585 | D129: 1 | E129: 75.387521 | F129: 74.091141 | G129: 25 | H129: 1 | I129: LD25 (100%)
A130: 85323 | B130: Maricopa | C130: 44632 | D130: 0.59838233 | E130: 74.932351 | F130: 73.635971 | G130: 22 | H130: 1 | I130: LD22 (100%)
A131: 85324 | B131: Yavapai | C131: 2720 | D131: 0.99779412 | E131: 77.885999 | F131: 75.464653 | G131: 1 | H131: 1 | I131: LD1 (100%)
A132: 85325 | B132: La Paz | C132: 847 | D132: 1 | E132: 76.946281 | F132: 69.764388 | G132: 30 | H132: 1 | I132: LD30 (100%)
A133: 85326 | B133: Maricopa | C133: 72959 | D133: 0.93616963 | E133: 78.683166 | F133: 77.386786 | G133: 25 | H133: 0.92709604 | I133: LD25 (93%); LD23 (7%)
A134: 85328 | B134: La Paz | C134: 208 | D134: 1 | E134: 79.1 | F134: 71.918107 | G134: 30 | H134: 1 | I134: LD30 (100%)
A135: 85329 | B135: Maricopa | C135: 2438 | D135: 1 | E135: 76.3 | F135: 75.00362 | G135: 22 | H135: 1 | I135: LD22 (100%)
A136: 85331 | B136: Maricopa | C136: 31038 | D136: 0.82862942 | E136: 82.467899 | F136: 81.171519 | G136: 3 | H136: 1 | I136: LD3 (100%)
A137: 85332 | B137: Yavapai | C137: 1912 | D137: 1 | E137: 85.552301 | F137: 83.130956 | G137: 1 | H137: 1 | I137: LD1 (100%)
... A145: 85340 | B145: Maricopa | C145: 33778 | D145: 0.94073065 | E145: 78.827751 | F145: 77.53137 | G145: 29 | H145: 0.76558707 | I145: LD29 (77%); LD25 (21%); LD22 (3%)
A146: 85341 | B146: Pima | C146: 18 | D146: 0 | G146: 23 | H146: 1 | I146: LD23 (100%)
A147: 85342 | B147: Maricopa | C147: 1478 | D147: 1 | E147: 80.233221 | F147: 78.878994 | G147: 29 | H147: 0.94316644 | I147: LD29 (94%); LD1 (5%)
A148: 85343 | B148: Maricopa | C148: 164 | D148: 1 | E148: 74.5 | F148: 73.20362 | G148: 25 | H148: 1 | I148: LD25 (100%)
A149: 85344 | B149: La Paz | C149: 9137 | D149: 0.93641239 | E149: 75.214656 | F149: 68.032764 | G149: 30 | H149: 1 | I149: LD30 (100%)
A150: 85345 | B150: Maricopa | C150: 61024 | D150: 0.91791754 | E150: 77.868335 | F150: 76.571955 | G150: 27 | H150: 0.87418065 | I150: LD27 (87%); LD29 (7%); LD28 (3%); LD24 (2%)
A151: 85346 | B151: La Paz | C151: 2803 | D151: 1 | E151: 77.599465 | F151: 70.417572 | G151: 30 | H151: 1 | I151: LD30 (100%)
A152: 85347 | B152: Yuma | C152: 310 | D152: 0.90967742 | E152: 77.8 | F152: 77.418183 | G152: 25 | H152: 1 | I152: LD25 (100%)
A153: 85348 | B153: La Paz | C153: 2083 | D153: 1 | E153: 77.788334 | F153: 70.606441 | G153: 30 | H153: 1 | I153: LD30 (100%)
A154: 85349 | B154: Yuma | C154: 28039 | D154: 0.9820607 | E154: 77.353319 | F154: 76.971503 | G154: 23 | H154: 1 | I154: LD23 (100%)
A155: 85350 | B155: Yuma | C155: 18486 | D155: 1 | E155: 77.201331 | F155: 76.819514 | G155: 23 | H155: 0.98912691 | I155: LD23 (99%)
A156: 85351 | B156: Maricopa | C156: 29795 | D156: 0.17147172 | E156: 73.310511 | F156: 72.014131 | G156: 28 | H156: 1 | I156: LD28 (100%)
A157: 85352 | B157: Yuma | C157: 388 | D157: 1 | E157: 77.8 | F157: 77.418183 | G157: 25 | H157: 1 | I157: LD25 (100%)
A158: 85353 | B158: Maricopa | C158: 42936 | D158: 0.59558413 | E158: 77.821739 | F158: 76.525358 | G158: 22 | H158: 1 | I158: LD22 (100%)
... A194: 85539 | B194: Gila | C194: 3618 | D194: 0.96876727 | E194: 82.990157 | F194: 74.666431 | G194: 7 | H194: 1 | I194: LD7 (100%)
A195: 85540 | B195: Greenlee | C195: 4026 | D195: 0 | G195: 19 | H195: 1 | I195: LD19 (100%)
A196: 85541 | B196: Gila | C196: 22974 | D196: 0.99412379 | E196: 76.648794 | F196: 68.143095 | G196: 7 | H196: 1 | I196: LD7 (100%)
A197: 85542 | B197: Graham | C197: 3172 | D197: 0.81588903 | E197: 75.5 | F197: 70.730427 | G197: 6 | H197: 1 | I197: LD6 (100%)
A198: 85543 | B198: Graham | C198: 4283 | D198: 1 | E198: 78.89979 | F198: 74.130217 | G198: 19 | H198: 1 | I198: LD19 (100%)
A199: 85544 | B199: Gila | C199: 2905 | D199: 1 | E199: 79.5 | F199: 70.994301 | G199: 7 | H199: 1 | I199: LD7 (100%)
A200: 85545 | B200: Gila | C200: 523 | D200: 0.98852772 | E200: 81.783752 | F200: 73.375665 | G200: 7 | H200: 0.98661568 | I200: LD7 (99%)
A201: 85546 | B201: Graham | C201: 20100 | D201: 1 | E201: 78.396294 | F201: 73.626721 | G201: 19 | H201: 1 | I201: LD19 (100%)
A202: 85550 | B202: Gila | C202: 4934 | D202: 0 | G202: 6 | H202: 1 | I202: LD6 (100%)
A203: 85551 | B203: Graham | C203: 396 | D203: 1 | E203: 80 | F203: 75.230427 | G203: 19 | H203: 1 | I203: LD19 (100%)
A204: 85552 | B204: Graham | C204: 6887 | D204: 1 | E204: 79.369551 | F204: 74.599979 | G204: 19 | H204: 1 | I204: LD19 (100%)
A205: 85553 | B205: Gila | C205: 1491 | D205: 0 | G205: 7 | H205: 1 | I205: LD7 (100%)
A206: 85554 | B206: Gila | C206: 735 | D206: 0.94557823 | E206: 78.2 | F206: 69.694301 | G206: 7 | H206: 1 | I206: LD7 (100%)
A207: 85601 | B207: Pima | C207: 644 | D207: 1 | E207: 81 | F207: 78.915929 | G207: 21 | H207: 1 | I207: LD21 (100%)
A208: 85602 | B208: Cochise | C208: 10198 | D208: 1 | E208: 78.86163 | F208: 76.428136 | G208: 19 | H208: 0.95685429 | I208: LD19 (96%); LD17 (4%)
A209: 85603 | B209: Cochise | C209: 6342 | D209: 0.7811416 | E209: 77.995822 | F209: 75.527099 | G209: 21 | H209: 0.97839798 | I209: LD21 (98%); LD19 (2%)
A210: 85605 | B210: Cochise | C210: 629 | D210: 1 | E210: 89 | F210: 86.531277 | G210: 19 | H210: 1 | I210: LD19 (100%)
A211: 85606 | B211: Cochise | C211: 977 | D211: 1 | E211: 76.001535 | F211: 73.532813 | G211: 19 | H211: 1 | I211: LD19 (100%)
A212: 85607 | B212: Cochise | C212: 17738 | D212: 1 | E212: 73.868875 | F212: 71.400152 | G212: 19 | H212: 1 | I212: LD19 (100%)
A213: 85608 | B213: Cochise | C213: 1983 | D213: 1 | E213: 84.5 | F213: 82.031277 | G213: 19 | H213: 1 | I213: LD19 (100%)
A214: 85609 | B214: Cochise | C214: 325 | D214: 1 | E214: 84.525231 | F214: 82.056508 | G214: 19 | H214: 1 | I214: LD19 (100%)
A215: 85610 | B215: Cochise | C215: 1053 | D215: 1 | E215: 84.197436 | F215: 81.728713 | G215: 19 | H215: 1 | I215: LD19 (100%)
A216: 85611 | B216: Santa Cruz | C216: 1017 | D216: 0.23697148 | E216: 83.908714 | F216: 81.679401 | G216: 19 | H216: 0.98230088 | I216: LD19 (98%)
A217: 85613 | B217: Cochise | C217: 5239 | D217: 0 | G217: 19 | H217: 1 | I217: LD19 (100%)
A218: 85614 | B218: Pima | C218: 25789 | D218: 0.68502075 | E218: 80.922801 | F218: 78.83873 | G218: 19 | H218: 0.83547249 | I218: LD19 (84%); LD21 (16%)
A219: 85615 | B219: Cochise | C219: 9073 | D219: 1 | E219: 81.884283 | F219: 79.41556 | G219: 19 | H219: 0.78309269 | I219: LD19 (78%); LD21 (22%)
A220: 85616 | B220: Cochise | C220: 5110 | D220: 1 | E220: 76 | F220: 73.531277 | G220: 19 | H220: 1 | I220: LD19 (100%)
A221: 85617 | B221: Cochise | C221: 1086 | D221: 0.98987109 | E221: 84.5 | F221: 82.031277 | G221: 19 | H221: 0.99447514 | I221: LD19 (99%)
A222: 85618 | B222: Pinal | C222: 1271 | D222: 1 | E222: 78.338159 | F222: 77.080366 | G222: 7 | H222: 1 | I222: LD7 (100%)
A223: 85619 | B223: Pima | C223: 113 | D223: 1 | E223: 82.079646 | F223: 79.995576 | G223: 17 | H223: 1 | I223: LD17 (100%)
A224: 85620 | B224: Cochise | C224: 734 | D224: 1 | E224: 75.9 | F224: 73.431277 | G224: 21 | H224: 1 | I224: LD21 (100%)
...

Sheet Sources
A1: Used for | B1: Source | C1: Date | D1: URL
A2: Full phase-in enrollment loss, provision split | B2: RAND, "State-Level Impacts of Key Medicaid Provisions in the One Big Beautiful Bill Act" (Rao, Baker, Girosi, Li, Kerber, Eibner), RRA4098-1-v2, Appendix Table B.15 (Arizona: -327,400; work requirements -198,800; SDP/provider tax -94,200; redeterminations -65,700; immigrant -5,000; emergency FMAP -2,300; good-faith -3,200) | C2: Feb 2026; v2 June 18, 2026 | D2: https://www.rand.org/pubs/research_reports/RRA4098-1-v2.html
A3: Uncertainty band; uninsured cross-check (290,000) | B3: KFF, "How Will the 2025 Reconciliation Law Affect the Uninsured Rate in Each State?" — Arizona: +330,000 uninsured by 2034 (range 250,000-410,000), of which 290,000 from Medicaid provisions | C3: Aug 20, 2025 | D3: https://www.kff.org/uninsured/how-will-the-2025-reconciliation-law-affect-the-uninsured-rate-in-each-state/
A4: Near-term enrollment loss (2028) | B4: Urban Institute / RWJF, "Projected Reductions in Medicaid Expansion Enrollment Under OBBBA's Work Requirements and Six-Month Redeterminations" (Buettgens, Karpman, Haley, Carter, Kenney), Table 3 and Appendix Table A.2 — Arizona -123,000 / -197,000 / -246,000 | C4: Mar 25, 2026 | D4: https://www.urban.org/research/publication/projected-reductions-medicaid-expansion-enrollment-under-obbbas-work
A5: Immigrant provision count | B5: Arizona Public Health Association (Will Humble), "Arizona's First H.R. 1 Medicaid Cuts Arrive October 1" — AHCCCS sent advance notices to ~22,263 members; ~12,000 SSI recipients under separate review | C5: Aug 31, 2026 | D5: https://azpha.org/2026/08/31/arizonas-first-h-r-1-medicaid-cuts-arrive-october-1-refugees-asylees-other-legally-present-people-are-1st-in-line-for-cuts/
A6: State budget-staff estimate (context) | B6: JLBC Staff, "Analysis of the Federal Budget Reconciliation Bill (H.R. 1) on Arizona State Budget" — 171,000 fewer members by FY 2030 (144,000 work requirements + 27,000 redeterminations); expansion base 435,000 (Nov 2025) | C6: Jan 8, 2026 | D6: https://www.azjlbc.gov/revenues/2025federalbudgetreconciliationbill-stateimpact0108.pdf
A7: Federal funding loss (context) | B7: KFF, "Allocating CBO's Estimates of Federal Medicaid Spending Reductions Across the States: Enacted Reconciliation Package" — Arizona -$34.5 billion FFY 2025-2034 (range $25.9B-$43.1B), 18% of baseline | C7: Jul 23, 2025 | D7: https://www.kff.org/medicaid/allocating-cbos-estimates-of-federal-medicaid-spending-reductions-across-the-states-enacted-reconciliation-package/
A8: Uninsured-per-enrollee ratio | B8: KFF, "Allocating CBO's Estimates of Federal Medicaid Spending Reductions and Enrollment Loss Across the States" — CBO: 10.3 million fewer enrollees, 7.8 million more uninsured (House-passed bill) | C8: Jun 4, 2025 | D8: https://www.kff.org/medicaid/allocating-cbos-estimates-of-federal-medicaid-spending-reductions-and-enrollment-loss-across-the-states/
A9: CBO provision-level uninsured (context) | B9: CBO, Supplemental cost estimate, P.L. 119-21 Medicaid provisions — work requirements 5.3M, provider taxes 1.1M, redeterminations 0.7M, streamlining moratorium 0.4M; total 7.5M uninsured in 2034 | C9: Oct 28, 2025 | D9: https://www.cbo.gov/system/files/2025-10/PL-119-21-Medicaid%20_0.pdf
A10: AIAN exemption | B10: CMS, Section 71119 Community Engagement Requirement overview; CMS interim final rule fact sheet (June 1, 2026) — exempts Indians/IHS-eligible individuals, parents of children under 14, medically frail | C10: Jun 1, 2026 | D10: https://www.cms.gov/newsroom/fact-sheets/medicaid-community-engagement-requirement-certain-individuals-interim-final-rule-comment-period-cms
A11: Current AHCCCS enrollment | B11: AHCCCS, Population by Category / by County, Aug 1 2026 (total 1,771,977; Prop 204 346,960; Adult Expansion 53,005) | C11: Aug 6, 2026 | D11: https://www.azahcccs.gov/Resources/Downloads/PopulationStatistics/PopulationbyCategory08062026.pdf
A12: Expansion enrollment by congressional district (calibration) | B12: Health Management Associates for AHCCCS, "AHCCCS Data to Inform Potential Federal Medicaid Changes — by Congressional District", Table 1 | C12: Apr 2025 (Jan 1 2025 data) | D12: https://www.azahcccs.gov/AHCCCS/Downloads/AHCCCS_Data_to_Inform_by_Congressional%20District.pdf
... A24: Independent audit | B24: Independent statistical audit of this model (recomputation, source verification, logic review); findings and remaining caveats summarized in Method & Caveats | C24: Sep 4, 2026 | D24: research/audit_report.md (in data package)

Sheet Method & Caveats
A1: METHOD
A2: 1. Statewide anchors. Near term: Urban Institute's 2028 projection of Arizona expansion-enrollment decline from the Jan. 1, 2027 work requirement and six-month renewals (123,000 / 197,000 / 246,000 under high / medium / low state mitigation), plus AHCCCS's 22,263 advance notices for the Oct. 1, 2026 immigrant-eligibility change. Full phase-in: RAND's 2034 projection of -327,400 AHCCCS enrollees, with RAND's provision breakdown; the low/high envelope applies KFF/CBO's Arizona uncertainty band (-24% / +24%).
A3: 2. District allocation. ACS 2020-2024 tract estimates were spread to 2020 census blocks by population and summed to the 30 legislative districts (Census 2022 SLDU block file; district populations match the IRC map exactly). Work-requirement losses use adults 19-64 with Medicaid, excluding Medicare dual-eligibles, adults reporting a disability, and American Indians (exempt by statute; AIAN identified from 2020 Census adult counts and the 40.4% adult Medicaid rate observed in AIAN-majority tracts). Six-month-renewal losses use the same key without the AIAN exclusion. Provider-tax-driven losses use all adults 19-64 with Medicaid. The immigrant provision uses noncitizens with public coverage, down-weighted by the share of the foreign-born population born in Mexico, Cuba or Haiti (groups that keep eligibility). Keys were calibrated to AHCCCS expansion enrollment by congressional district (Jan 2025; factors 0.90-1.12) and total enrollment by county (Aug 2026).
A4: 3. Uninsured. 0.757 uninsured per enrollee lost (CBO). Deaths: uninsured x 1.2 / 2.2 / 3.6 per 1,000 per year, distributed across ages 19-64 in proportion to the district's age profile of adults with public coverage and Arizona's age-specific death rates (constant c solved so the statewide rate equals the literature value).
A5: 4. Life expectancy. Baseline: USALEEP tract estimates (2010-2015) shifted to County Health Rankings 2025 county values (NCHS 2020-2022) and population-weighted to districts (statewide 76.73 = NCHS 2022 Arizona 76.7). Impact: Arizona 2022 single-year life table scaled to each district's baseline; death rates at ages 19-64 raised by additional deaths / population in each band; e0 recomputed.
A7: CAVEATS (from the independent audit — every one applies)
A8: a. District figures are allocations of statewide projections, not observed counts; AHCCCS publishes no legislative-district or ZIP enrollment.
A9: b. Exemptions other than AIAN — parents of children under 14, medically frail, pregnant/postpartum (about 40% of expansion adults per AHCCCS) — cannot be located geographically with ACS; districts with many low-income families may be somewhat over-allocated and districts with more childless adults under-allocated. The congressional-district calibration corrects this only at the 9-district level.
A10: c. 26% of the 2034 loss is RAND's assumption that Arizona trims optional eligibility as provider-tax revenue falls; JLBC projects reduced hospital payments, not enrollment loss, from that provision. The "excluding provider-tax component" column shows results without it.
A11: d. The uninsured conversion (0.757) is conservative relative to KFF's 290,000 Arizona figure; deaths and life-expectancy effects would be ~17% larger using KFF.
A12: e. The immigrant-provision figure is a count of notices, not projected losses; refugee/asylee geography is approximated.
A13: f. Mortality evidence comes from coverage gains; symmetry for losses is assumed (as in every published H.R. 1 projection). Pre-ACA evidence behind the high estimate is contested (Koumpias et al. 2024); Wyse & Meyer is a working paper. Effects grow over 3-4 years, so first-year deaths are below steady state.
... A18: k. Independent audit (Sept 4, 2026) reproduced every allocation, life-table and calibration figure from scratch and confirmed all 13 spot-checked source claims against live sources; its two critical/major methodological findings (AIAN exemption; district-scaled death rates) were corrected in this version.

Sheet Assessment Inputs
A1: Hospital assessment step-down under H.R. 1 Sec. 71115 — inputs
A3: Current assessment rate (SFY 2026, effectively at the 6.0% federal ceiling) | B3: 0.06 | C3: AHCCCS / JLBC; CSPA one-pager Sept 4 2026 (5.999%)
A4: Ceiling FFY 2028 (Oct 1 2027) | B4: 0.055 | C4: P.L. 119-21 Sec. 71115: -0.5 pt per year for expansion states
A5: Ceiling FFY 2029 | B5: 0.05
A6: Ceiling FFY 2030 | B6: 0.045
A7: Ceiling FFY 2031 | B7: 0.04
A8: Ceiling FFY 2032 and after | B8: 0.035 | C8: Frozen at 3.5%
A9: SFY 2025 assessment collected, all hospitals (HAF + HCIF) | B9: 1.3551273e+09 | C9: AHCCCS SFY 2025 Hospital Assessment Report (June 1 2026), totals of both tables
A10: SFY 2025 payments funded by the assessment (coverage + HEALTHII) | B10: 4.3245554e+09 | C10: Same report: $1,498,893,446.63 coverage + $2,825,661,963 HEALTHII
A11: Number of facilities listed (either table) | B11: 134 | C11: Report lists 133 HAF rows and 114 HCIF rows; 134 distinct facilities after matching names across tables
A12: Ten-year (FFY 2028-2037) factor relative to a full 3.5% year | B12: 8 | C12: 0.2+0.4+0.6+0.8+1.0 for the phase-in years, then 1.0 for each of FFY 2033-2037
A14: Full-year reduction factor at 3.5% = (B3-B8)/B3 | B14: =(B3-B8)/B3
A15: Statewide payments lost per year at 3.5% | B15: =B10*B14
A16: Statewide assessment no longer collected per year at 3.5% | B16: =B9*B14
A17: Statewide net loss to hospitals per year at 3.5% (federal match leaving Arizona) | B17: =B15-B16
A18: Ten-year net loss FFY 2028-2037 | B18: =B17*B12
A20: Method: each facility's SFY 2025 assessment paid and assessment-funded payments received (AHCCCS report) are scaled by the share of the 6.0% rate that H.R. 1 removes; federal matching rates held constant; constant SFY 2025 dollars. "Payments lost" is the reduction in Medicaid revenue the facility receives; "net loss" subtracts the assessment the facility no longer pays. This is the same method as the CSPA one-pager (Sept 4 2026) and ties to its statewide totals. It assumes both funds (coverage match and HEALTHII directed payments) shrink proportionally; JLBC (Jan 8 2026) instead assumes AHCCCS protects the coverage match and concentrates the cut in HEALTHII, which would shift losses toward hospitals with large HEALTHII payments. Indian Health Service and tribal (638) facilities are flagged: their Medicaid services are matched at 100% federal funds, so their payments are not funded by the assessment and are shown separately. Facilities are assigned to legislative districts by geocoding their street addresses to 2020 census blocks (Census Geocoder) and mapping blocks to the 2022 IRC districts; a hospital's patients and staff come from many districts, so district totals describe where the facilities are located.

Sheet Assessment by Facility
A1: Facility | B1: Hospital system | C1: City | D1: County | E1: LD | F1: IHS / tribal (100% federal match; not assessment-funded) | G1: SFY 2025 assessment paid | H1: SFY 2025 coverage payments | I1: SFY 2025 HEALTHII payments | J1: Total payments | K1: Net gain (payments - assessment) | L1: Payments lost per year at 3.5% | M1: Assessment saved per year at 3.5% | N1: Net loss per year at 3.5% | O1: Net loss, FFY 2028 (5.5%) | P1: Ten-year net loss FFY 2028-2037 | Q1: Ten-year payments lost | R1: Geocode confidence | S1: Address
A2: Banner – University Medical Center Phoenix | B2: Banner Health | C2: Phoenix | D2: Maricopa | E2: 5 | G2: 66438127 | H2: 93020323 | I2: 213303893 | J2: =H2+I2 | K2: =J2-G2 | L2: =J2*'Assessment Inputs'!$B$14 | M2: =G2*'Assessment Inputs'!$B$14 | N2: =L2-M2 | O2: =K2*('Assessment Inputs'!$B$3-'Assessment Inputs'!$B$4)/'Assessment Inputs'!$B$3 | P2: =N2*'Assessment Inputs'!$B$12 | Q2: =L2*'Assessment Inputs'!$B$12 | R2: high | S2: 1111 E McDowell Rd, Phoenix, AZ 85006
A3: Banner – University Medical Center Tucson | B3: Banner Health | C3: Tucson | D3: Pima | E3: 20 | G3: 58603477 | H3: 77566617 | I3: 220688920 | J3: =H3+I3 | K3: =J3-G3 | L3: =J3*'Assessment Inputs'!$B$14 | M3: =G3*'Assessment Inputs'!$B$14 | N3: =L3-M3 | O3: =K3*('Assessment Inputs'!$B$3-'Assessment Inputs'!$B$4)/'Assessment Inputs'!$B$3 | P3: =N3*'Assessment Inputs'!$B$12 | Q3: =L3*'Assessment Inputs'!$B$12 | R3: high | S3: 1625 N Campbell Ave, Tucson, AZ 85719
A4: Banner Desert Medical Center | B4: Banner Health | C4: Mesa | D4: Maricopa | E4: 9 | G4: 45224407 | H4: 55424929 | I4: 180897534 | J4: =H4+I4 | K4: =J4-G4 | L4: =J4*'Assessment Inputs'!$B$14 | M4: =G4*'Assessment Inputs'!$B$14 | N4: =L4-M4 | O4: =K4*('Assessment Inputs'!$B$3-'Assessment Inputs'!$B$4)/'Assessment Inputs'!$B$3 | P4: =N4*'Assessment Inputs'!$B$12 | Q4: =L4*'Assessment Inputs'!$B$12 | R4: high | S4: 1400 S Dobson Rd, Mesa, AZ 85202
A5: St. Joseph's Hospital and Medical Center (Phoenix) | B5: Dignity Health | C5: Phoenix | D5: Maricopa | E5: 5 | G5: 77259632 | H5: 67297191 | I5: 146519715 | J5: =H5+I5 | K5: =J5-G5 | L5: =J5*'Assessment Inputs'!$B$14 | M5: =G5*'Assessment Inputs'!$B$14 | N5: =L5-M5 | O5: =K5*('Assessment Inputs'!$B$3-'Assessment Inputs'!$B$4)/'Assessment Inputs'!$B$3 | P5: =N5*'Assessment Inputs'!$B$12 | Q5: =L5*'Assessment Inputs'!$B$12 | R5: high | S5: 350 W Thomas Rd, Phoenix, AZ 85013
A6: Banner Thunderbird Medical Center | B6: Banner Health | C6: Glendale | D6: Maricopa | E6: 27 | G6: 48455135 | H6: 39525283 | I6: 146468579 | J6: =H6+I6 | K6: =J6-G6 | L6: =J6*'Assessment Inputs'!$B$14 | M6: =G6*'Assessment Inputs'!$B$14 | N6: =L6-M6 | O6: =K6*('Assessment Inputs'!$B$3-'Assessment Inputs'!$B$4)/'Assessment Inputs'!$B$3 | P6: =N6*'Assessment Inputs'!$B$12 | Q6: =L6*'Assessment Inputs'!$B$12 | R6: high | S6: 5555 W Thunderbird Rd, Glendale, AZ 85306
A7: Onvida Health – Yuma Regional Medical Center | B7: Onvida Health – Yuma Regional Medical Center | C7: Yuma | D7: Yuma | E7: 25 | G7: 45267400 | H7: 41275311 | I7: 124014484 | J7: =H7+I7 | K7: =J7-G7 | L7: =J7*'Assessment Inputs'!$B$14 | M7: =G7*'Assessment Inputs'!$B$14 | N7: =L7-M7 | O7: =K7*('Assessment Inputs'!$B$3-'Assessment Inputs'!$B$4)/'Assessment Inputs'!$B$3 | P7: =N7*'Assessment Inputs'!$B$12 | Q7: =L7*'Assessment Inputs'!$B$12 | R7: high | S7: 2400 S Avenue A, Yuma, AZ 85364
A8: Tucson Medical Center | B8: TMC Healthcare | C8: Tucson | D8: Pima | E8: 18 | G8: 48307845 | H8: 33221779 | I8: 127228834 | J8: =H8+I8 | K8: =J8-G8 | L8: =J8*'Assessment Inputs'!$B$14 | M8: =G8*'Assessment Inputs'!$B$14 | N8: =L8-M8 | O8: =K8*('Assessment Inputs'!$B$3-'Assessment Inputs'!$B$4)/'Assessment Inputs'!$B$3 | P8: =N8*'Assessment Inputs'!$B$12 | Q8: =L8*'Assessment Inputs'!$B$12 | R8: high | S8: 5301 E Grant Rd, Tucson, AZ 85712
A9: Valleywise Health Medical Center | B9: Valleywise Health | C9: Phoenix | D9: Maricopa | E9: 5 | G9: 0 | H9: 1.0926574e+08 | I9: 50311904 | J9: =H9+I9 | K9: =J9-G9 | L9: =J9*'Assessment Inputs'!$B$14 | M9: =G9*'Assessment Inputs'!$B$14 | N9: =L9-M9 | O9: =K9*('Assessment Inputs'!$B$3-'Assessment Inputs'!$B$4)/'Assessment Inputs'!$B$3 | P9: =N9*'Assessment Inputs'!$B$12 | Q9: =L9*'Assessment Inputs'!$B$12 | R9: high | S9: 2601 E Roosevelt St, Phoenix, AZ 85008
A10: HonorHealth John C. Lincoln Medical Center | B10: HonorHealth | C10: Phoenix | D10: Maricopa | E10: 5 | G10: 49080288 | H10: 39775834 | I10: 79620462 | J10: =H10+I10 | K10: =J10-G10 | L10: =J10*'Assessment Inputs'!$B$14 | M10: =G10*'Assessment Inputs'!$B$14 | N10: =L10-M10 | O10: =K10*('Assessment Inputs'!$B$3-'Assessment Inputs'!$B$4)/'Assessment Inputs'!$B$3 | P10: =N10*'Assessment Inputs'!$B$12 | Q10: =L10*'Assessment Inputs'!$B$12 | R10: high | S10: 250 E Dunlap Ave, Phoenix, AZ 85020
A11: Banner Estrella Medical Center | B11: Banner Health | C11: Phoenix | D11: Maricopa | E11: 22 | G11: 42228047 | H11: 27820919 | I11: 86782074 | J11: =H11+I11 | K11: =J11-G11 | L11: =J11*'Assessment Inputs'!$B$14 | M11: =G11*'Assessment Inputs'!$B$14 | N11: =L11-M11 | O11: =K11*('Assessment Inputs'!$B$3-'Assessment Inputs'!$B$4)/'Assessment Inputs'!$B$3 | P11: =N11*'Assessment Inputs'!$B$12 | Q11: =L11*'Assessment Inputs'!$B$12 | R11: medium | S11: 9201 W Thomas Rd, Phoenix, AZ 85037
A12: Phoenix Children's Hospital | B12: Phoenix Children's Hospital | C12: Phoenix | D12: Maricopa | E12: 5 | G12: 11551898 | H12: 5295926.9 | I12: 105335789 | J12: =H12+I12 | K12: =J12-G12 | L12: =J12*'Assessment Inputs'!$B$14 | M12: =G12*'Assessment Inputs'!$B$14 | N12: =L12-M12 | O12: =K12*('Assessment Inputs'!$B$3-'Assessment Inputs'!$B$4)/'Assessment Inputs'!$B$3 | P12: =N12*'Assessment Inputs'!$B$12 | Q12: =L12*'Assessment Inputs'!$B$12 | R12: high | S12: 1919 E Thomas Rd, Phoenix, AZ 85016
A13: Banner Gateway Medical Center | B13: Banner Health | C13: Gilbert | D13: Maricopa | E13: 14 | G13: 49603403 | H13: 28483799 | I13: 67197785 | J13: =H13+I13 | K13: =J13-G13 | L13: =J13*'Assessment Inputs'!$B$14 | M13: =G13*'Assessment Inputs'!$B$14 | N13: =L13-M13 | O13: =K13*('Assessment Inputs'!$B$3-'Assessment Inputs'!$B$4)/'Assessment Inputs'!$B$3 | P13: =N13*'Assessment Inputs'!$B$12 | Q13: =L13*'Assessment Inputs'!$B$12 | R13: high | S13: 1900 N Higley Rd, Gilbert, AZ 85234
... A33: Banner Casa Grande Medical Center | B33: Banner Health | C33: Casa Grande | D33: Pinal | E33: 16 | G33: 12412361 | H33: 9590304.4 | I33: 28852452 | J33: =H33+I33 | K33: =J33-G33 | L33: =J33*'Assessment Inputs'!$B$14 | M33: =G33*'Assessment Inputs'!$B$14 | N33: =L33-M33 | O33: =K33*('Assessment Inputs'!$B$3-'Assessment Inputs'!$B$4)/'Assessment Inputs'!$B$3 | P33: =N33*'Assessment Inputs'!$B$12 | Q33: =L33*'Assessment Inputs'!$B$12 | R33: high | S33: 1800 E Florence Blvd, Casa Grande, AZ 85122
A34: Hu Hu Kam Memorial Hospital | B34: IHS | C34: Sacaton | D34: Pinal | E34: 16 | F34: Yes | G34: 0 | H34: 36588202 | I34: 0 | J34: =H34+I34 | K34: =J34-G34 | L34: =J34*'Assessment Inputs'!$B$14 | M34: =G34*'Assessment Inputs'!$B$14 | N34: =L34-M34 | O34: =K34*('Assessment Inputs'!$B$3-'Assessment Inputs'!$B$4)/'Assessment Inputs'!$B$3 | P34: =N34*'Assessment Inputs'!$B$12 | Q34: =L34*'Assessment Inputs'!$B$12 | R34: medium | S34: 483 W Seed Farm Rd, Sacaton, AZ 85147
A35: Phoenix Indian Medical Center | B35: IHS | C35: Phoenix | D35: Maricopa | E35: 5 | F35: Yes | G35: 0 | H35: 33133565 | I35: 0 | J35: =H35+I35 | K35: =J35-G35 | L35: =J35*'Assessment Inputs'!$B$14 | M35: =G35*'Assessment Inputs'!$B$14 | N35: =L35-M35 | O35: =K35*('Assessment Inputs'!$B$3-'Assessment Inputs'!$B$4)/'Assessment Inputs'!$B$3 | P35: =N35*'Assessment Inputs'!$B$12 | Q35: =L35*'Assessment Inputs'!$B$12 | R35: high | S35: 4212 N 16th St, Phoenix, AZ 85016
A36: HonorHealth Four Peaks Medical Center (formerly Mountain Vista Medical Center) | B36: HonorHealth | C36: Mesa | D36: Maricopa | E36: 10 | G36: 19393901 | H36: 6268738.5 | I36: 25885239 | J36: =H36+I36 | K36: =J36-G36 | L36: =J36*'Assessment Inputs'!$B$14 | M36: =G36*'Assessment Inputs'!$B$14 | N36: =L36-M36 | O36: =K36*('Assessment Inputs'!$B$3-'Assessment Inputs'!$B$4)/'Assessment Inputs'!$B$3 | P36: =N36*'Assessment Inputs'!$B$12 | Q36: =L36*'Assessment Inputs'!$B$12 | R36: medium | S36: 1301 S Crismon Rd, Mesa, AZ 85209
A37: Havasu Regional Medical Center | B37: Lifepoint Health | C37: Lake Havasu City | D37: Mohave | E37: 30 | G37: 16429891 | H37: 8549514.8 | I37: 20520638 | J37: =H37+I37 | K37: =J37-G37 | L37: =J37*'Assessment Inputs'!$B$14 | M37: =G37*'Assessment Inputs'!$B$14 | N37: =L37-M37 | O37: =K37*('Assessment Inputs'!$B$3-'Assessment Inputs'!$B$4)/'Assessment Inputs'!$B$3 | P37: =N37*'Assessment Inputs'!$B$12 | Q37: =L37*'Assessment Inputs'!$B$12 | R37: high | S37: 101 Civic Center Ln, Lake Havasu City, AZ 86403
A38: Banner Ironwood Medical Center | B38: Banner Health | C38: Queen Creek | D38: Pinal | E38: 15 | G38: 11742127 | H38: 6286952.2 | I38: 20710771 | J38: =H38+I38 | K38: =J38-G38 | L38: =J38*'Assessment Inputs'!$B$14 | M38: =G38*'Assessment Inputs'!$B$14 | N38: =L38-M38 | O38: =K38*('Assessment Inputs'!$B$3-'Assessment Inputs'!$B$4)/'Assessment Inputs'!$B$3 | P38: =N38*'Assessment Inputs'!$B$12 | Q38: =L38*'Assessment Inputs'!$B$12 | R38: high | S38: 37000 N Gantzel Rd, Queen Creek, AZ 85140
A39: Cobre Valley Regional Medical Center | B39: Cobre Valley Regional Medical Center | C39: Globe | D39: Gila | E39: 7 | G39: 3642048.3 | H39: 7253104.5 | I39: 18995582 | J39: =H39+I39 | K39: =J39-G39 | L39: =J39*'Assessment Inputs'!$B$14 | M39: =G39*'Assessment Inputs'!$B$14 | N39: =L39-M39 | O39: =K39*('Assessment Inputs'!$B$3-'Assessment Inputs'!$B$4)/'Assessment Inputs'!$B$3 | P39: =N39*'Assessment Inputs'!$B$12 | Q39: =L39*'Assessment Inputs'!$B$12 | R39: medium | S39: 5880 S Hospital Dr, Globe, AZ 85501
A40: Tuba City Regional Health Care Corporation | B40: Tuba City Regional Health Care Corporation | C40: Tuba City | D40: Coconino | E40: 6 | F40: Yes | G40: 0 | H40: 25856568 | I40: 0 | J40: =H40+I40 | K40: =J40-G40 | L40: =J40*'Assessment Inputs'!$B$14 | M40: =G40*'Assessment Inputs'!$B$14 | N40: =L40-M40 | O40: =K40*('Assessment Inputs'!$B$3-'Assessment Inputs'!$B$4)/'Assessment Inputs'!$B$3 | P40: =N40*'Assessment Inputs'!$B$12 | Q40: =L40*'Assessment Inputs'!$B$12 | R40: medium | S40: 167 N Main St, Tuba City, AZ 86045
A41: Abrazo Scottsdale Campus | B41: Abrazo Health Care | C41: Phoenix | D41: Maricopa | E41: 4 | G41: 12837584 | H41: 8074448.3 | I41: 16705546 | J41: =H41+I41 | K41: =J41-G41 | L41: =J41*'Assessment Inputs'!$B$14 | M41: =G41*'Assessment Inputs'!$B$14 | N41: =L41-M41 | O41: =K41*('Assessment Inputs'!$B$3-'Assessment Inputs'!$B$4)/'Assessment Inputs'!$B$3 | P41: =N41*'Assessment Inputs'!$B$12 | Q41: =L41*'Assessment Inputs'!$B$12 | R41: high | S41: 3929 E Bell Rd, Phoenix, AZ 85032
A42: Canyon Vista Medical Center | B42: Lifepoint Health | C42: Sierra Vista | D42: Cochise | E42: 19 | G42: 10692028 | H42: 6654694.7 | I42: 17916741 | J42: =H42+I42 | K42: =J42-G42 | L42: =J42*'Assessment Inputs'!$B$14 | M42: =G42*'Assessment Inputs'!$B$14 | N42: =L42-M42 | O42: =K42*('Assessment Inputs'!$B$3-'Assessment Inputs'!$B$4)/'Assessment Inputs'!$B$3 | P42: =N42*'Assessment Inputs'!$B$12 | Q42: =L42*'Assessment Inputs'!$B$12 | R42: high | S42: 5700 E Highway 90, Sierra Vista, AZ 85635
A43: Verde Valley Medical Center | B43: Northern Arizona | C43: Cottonwood | D43: Yavapai | E43: 1 | G43: 12242352 | H43: 6797298.7 | I43: 16499712 | J43: =H43+I43 | K43: =J43-G43 | L43: =J43*'Assessment Inputs'!$B$14 | M43: =G43*'Assessment Inputs'!$B$14 | N43: =L43-M43 | O43: =K43*('Assessment Inputs'!$B$3-'Assessment Inputs'!$B$4)/'Assessment Inputs'!$B$3 | P43: =N43*'Assessment Inputs'!$B$12 | Q43: =L43*'Assessment Inputs'!$B$12 | R43: high | S43: 269 S Candy Ln, Cottonwood, AZ 86326
A44: Valley Hospital (Phoenix) | B44: Universal Health Services | C44: Phoenix | D44: Maricopa | E44: 5 | G44: 1750753.5 | H44: 17246628 | I44: 5892819 | J44: =H44+I44 | K44: =J44-G44 | L44: =J44*'Assessment Inputs'!$B$14 | M44: =G44*'Assessment Inputs'!$B$14 | N44: =L44-M44 | O44: =K44*('Assessment Inputs'!$B$3-'Assessment Inputs'!$B$4)/'Assessment Inputs'!$B$3 | P44: =N44*'Assessment Inputs'!$B$12 | Q44: =L44*'Assessment Inputs'!$B$12 | R44: high | S44: 3550 E Pinchot Ave, Phoenix, AZ 85018
A45: Western Arizona Regional Medical Center | B45: Community Health Systems | C45: Bullhead City | D45: Mohave | E45: 30 | G45: 8023682.3 | H45: 6062825.7 | I45: 15792592 | J45: =H45+I45 | K45: =J45-G45 | L45: =J45*'Assessment Inputs'!$B$14 | M45: =G45*'Assessment Inputs'!$B$14 | N45: =L45-M45 | O45: =K45*('Assessment Inputs'!$B$3-'Assessment Inputs'!$B$4)/'Assessment Inputs'!$B$3 | P45: =N45*'Assessment Inputs'!$B$12 | Q45: =L45*'Assessment Inputs'!$B$12 | R45: high | S45: 2735 Silver Creek Rd, Bullhead City, AZ 86442
A46: Mt. Graham Regional Medical Center | B46: Mt. Graham Regional Medical Center | C46: Safford | D46: Graham | E46: 19 | G46: 3076218.2 | H46: 4698626.6 | I46: 17053068 | J46: =H46+I46 | K46: =J46-G46 | L46: =J46*'Assessment Inputs'!$B$14 | M46: =G46*'Assessment Inputs'!$B$14 | N46: =L46-M46 | O46: =K46*('Assessment Inputs'!$B$3-'Assessment Inputs'!$B$4)/'Assessment Inputs'!$B$3 | P46: =N46*'Assessment Inputs'!$B$12 | Q46: =L46*'Assessment Inputs'!$B$12 | R46: high | S46: 1600 S 20th Ave, Safford, AZ 85546
A47: San Carlos Apache Healthcare Corporation | B47: IHS | C47: Peridot | D47: Graham | E47: 6 | F47: Yes | G47: 0 | H47: 21656571 | I47: 0 | J47: =H47+I47 | K47: =J47-G47 | L47: =J47*'Assessment Inputs'!$B$14 | M47: =G47*'Assessment Inputs'!$B$14 | N47: =L47-M47 | O47: =K47*('Assessment Inputs'!$B$3-'Assessment Inputs'!$B$4)/'Assessment Inputs'!$B$3 | P47: =N47*'Assessment Inputs'!$B$12 | Q47: =L47*'Assessment Inputs'!$B$12 | R47: medium | S47: 103 Medicine Way Rd, Peridot, AZ 85542
A48: Whiteriver Indian Hospital | B48: IHS | C48: Whiteriver | D48: Navajo | E48: 6 | F48: Yes | G48: 0 | H48: 21635791 | I48: 0 | J48: =H48+I48 | K48: =J48-G48 | L48: =J48*'Assessment Inputs'!$B$14 | M48: =G48*'Assessment Inputs'!$B$14 | N48: =L48-M48 | O48: =K48*('Assessment Inputs'!$B$3-'Assessment Inputs'!$B$4)/'Assessment Inputs'!$B$3 | P48: =N48*'Assessment Inputs'!$B$12 | Q48: =L48*'Assessment Inputs'!$B$12 | R48: high | S48: 200 W Hospital Dr, Whiteriver, AZ 85941
A49: Tséhootsooí Medical Center (Fort Defiance Indian Hospital) | B49: IHS | C49: Fort Defiance | D49: Apache | E49: 6 | F49: Yes | G49: 0 | H49: 20931271 | I49: 0 | J49: =H49+I49 | K49: =J49-G49 | L49: =J49*'Assessment Inputs'!$B$14 | M49: =G49*'Assessment Inputs'!$B$14 | N49: =L49-M49 | O49: =K49*('Assessment Inputs'!$B$3-'Assessment Inputs'!$B$4)/'Assessment Inputs'!$B$3 | P49: =N49*'Assessment Inputs'!$B$12 | Q49: =L49*'Assessment Inputs'!$B$12 | R49: medium | S49: Corner of Navajo Route N12 and N7, Fort Defiance, AZ 86504
A50: Chinle Comprehensive Health Care Facility | B50: IHS | C50: Chinle | D50: Apache | E50: 6 | F50: Yes | G50: 0 | H50: 19771794 | I50: 0 | J50: =H50+I50 | K50: =J50-G50 | L50: =J50*'Assessment Inputs'!$B$14 | M50: =G50*'Assessment Inputs'!$B$14 | N50: =L50-M50 | O50: =K50*('Assessment Inputs'!$B$3-'Assessment Inputs'!$B$4)/'Assessment Inputs'!$B$3 | P50: =N50*'Assessment Inputs'!$B$12 | Q50: =L50*'Assessment Inputs'!$B$12 | R50: medium | S50: US Highway 191 and Hospital Rd, Chinle, AZ 86503
A51: Northwest Medical Center Sahuarita | B51: Community Health Systems | C51: Sahuarita | D51: Pima | E51: 21 | G51: 10072065 | H51: 1773815.7 | I51: 17627115 | J51: =H51+I51 | K51: =J51-G51 | L51: =J51*'Assessment Inputs'!$B$14 | M51: =G51*'Assessment Inputs'!$B$14 | N51: =L51-M51 | O51: =K51*('Assessment Inputs'!$B$3-'Assessment Inputs'!$B$4)/'Assessment Inputs'!$B$3 | P51: =N51*'Assessment Inputs'!$B$12 | Q51: =L51*'Assessment Inputs'!$B$12 | R51: high | S51: 16260 S Rancho Sahuarita Blvd, Sahuarita, AZ 85629
A52: HonorHealth Tempe Medical Center (formerly Tempe St. Luke's) | B52: HonorHealth | C52: Tempe | D52: Maricopa | E52: 8 | G52: 7479524.5 | H52: 3800823.9 | I52: 15230857 | J52: =H52+I52 | K52: =J52-G52 | L52: =J52*'Assessment Inputs'!$B$14 | M52: =G52*'Assessment Inputs'!$B$14 | N52: =L52-M52 | O52: =K52*('Assessment Inputs'!$B$3-'Assessment Inputs'!$B$4)/'Assessment Inputs'!$B$3 | P52: =N52*'Assessment Inputs'!$B$12 | Q52: =L52*'Assessment Inputs'!$B$12 | R52: high | S52: 1500 S Mill Ave, Tempe, AZ 85281
A53: Holy Cross Hospital (Nogales) | B53: Abrazo Health Care | C53: Nogales | D53: Santa Cruz | E53: 21 | G53: 2094646.4 | H53: 3942122.7 | I53: 15034646 | J53: =H53+I53 | K53: =J53-G53 | L53: =J53*'Assessment Inputs'!$B$14 | M53: =G53*'Assessment Inputs'!$B$14 | N53: =L53-M53 | O53: =K53*('Assessment Inputs'!$B$3-'Assessment Inputs'!$B$4)/'Assessment Inputs'!$B$3 | P53: =N53*'Assessment Inputs'!$B$12 | Q53: =L53*'Assessment Inputs'!$B$12 | R53: high | S53: 1171 W Target Range Rd, Nogales, AZ 85621
A54: Copper Springs Hospital (Avondale) | B54: Lifepoint Health | C54: Avondale | D54: Maricopa | E54: 22 | G54: 2697554.8 | H54: 9617504.8 | I54: 8779227 | J54: =H54+I54 | K54: =J54-G54 | L54: =J54*'Assessment Inputs'!$B$14 | M54: =G54*'Assessment Inputs'!$B$14 | N54: =L54-M54 | O54: =K54*('Assessment Inputs'!$B$3-'Assessment Inputs'!$B$4)/'Assessment Inputs'!$B$3 | P54: =N54*'Assessment Inputs'!$B$12 | Q54: =L54*'Assessment Inputs'!$B$12 | R54: high | S54: 10550 W McDowell Rd, Avondale, AZ 85392
A55: Arizona General Hospital – Laveen | B55: Dignity Health | C55: Laveen | D55: Maricopa | E55: 11 | G55: 9108901.4 | H55: 4375598.4 | I55: 13763481 | J55: =H55+I55 | K55: =J55-G55 | L55: =J55*'Assessment Inputs'!$B$14 | M55: =G55*'Assessment Inputs'!$B$14 | N55: =L55-M55 | O55: =K55*('Assessment Inputs'!$B$3-'Assessment Inputs'!$B$4)/'Assessment Inputs'!$B$3 | P55: =N55*'Assessment Inputs'!$B$12 | Q55: =L55*'Assessment Inputs'!$B$12 | R55: high | S55: 7171 S 51st Ave, Laveen, AZ 85339
A56: Mayo Clinic Hospital | B56: Mayo | C56: Phoenix | D56: Maricopa | E56: 4 | G56: 0 | H56: 12280892 | I56: 5814615 | J56: =H56+I56 | K56: =J56-G56 | L56: =J56*'Assessment Inputs'!$B$14 | M56: =G56*'Assessment Inputs'!$B$14 | N56: =L56-M56 | O56: =K56*('Assessment Inputs'!$B$3-'Assessment Inputs'!$B$4)/'Assessment Inputs'!$B$3 | P56: =N56*'Assessment Inputs'!$B$12 | Q56: =L56*'Assessment Inputs'!$B$12 | R56: high | S56: 5777 E Mayo Blvd, Phoenix, AZ 85054
A57: Aurora Behavioral Healthcare – Tempe | B57: Aurora Behavioral Health System | C57: Tempe | D57: Maricopa | E57: 12 | G57: 1558739.7 | H57: 10811251 | I57: 6808019 | J57: =H57+I57 | K57: =J57-G57 | L57: =J57*'Assessment Inputs'!$B$14 | M57: =G57*'Assessment Inputs'!$B$14 | N57: =L57-M57 | O57: =K57*('Assessment Inputs'!$B$3-'Assessment Inputs'!$B$4)/'Assessment Inputs'!$B$3 | P57: =N57*'Assessment Inputs'!$B$12 | Q57: =L57*'Assessment Inputs'!$B$12 | R57: high | S57: 6350 S Maple Ave, Tempe, AZ 85283
A58: Aurora Behavioral Health System – Glendale | B58: Aurora Behavioral Health System | C58: Glendale | D58: Maricopa | E58: 24 | G58: 1455339 | H58: 10928243 | I58: 6199158 | J58: =H58+I58 | K58: =J58-G58 | L58: =J58*'Assessment Inputs'!$B$14 | M58: =G58*'Assessment Inputs'!$B$14 | N58: =L58-M58 | O58: =K58*('Assessment Inputs'!$B$3-'Assessment Inputs'!$B$4)/'Assessment Inputs'!$B$3 | P58: =N58*'Assessment Inputs'!$B$12 | Q58: =L58*'Assessment Inputs'!$B$12 | R58: high | S58: 6015 W Peoria Ave, Glendale, AZ 85302
A59: Copper Queen Community Hospital | B59: Copper Queen Community Hospital | C59: Bisbee | D59: Cochise | E59: 21 | G59: 1766516.8 | H59: 3922229.7 | I59: 13187462 | J59: =H59+I59 | K59: =J59-G59 | L59: =J59*'Assessment Inputs'!$B$14 | M59: =G59*'Assessment Inputs'!$B$14 | N59: =L59-M59 | O59: =K59*('Assessment Inputs'!$B$3-'Assessment Inputs'!$B$4)/'Assessment Inputs'!$B$3 | P59: =N59*'Assessment Inputs'!$B$12 | Q59: =L59*'Assessment Inputs'!$B$12 | R59: high | S59: 101 Cole Ave, Bisbee, AZ 85603
A60: Oro Valley Hospital | B60: Community Health Systems | C60: Oro Valley | D60: Pima | E60: 17 | G60: 14318556 | H60: 5462783.5 | I60: 11501129 | J60: =H60+I60 | K60: =J60-G60 | L60: =J60*'Assessment Inputs'!$B$14 | M60: =G60*'Assessment Inputs'!$B$14 | N60: =L60-M60 | O60: =K60*('Assessment Inputs'!$B$3-'Assessment Inputs'!$B$4)/'Assessment Inputs'!$B$3 | P60: =N60*'Assessment Inputs'!$B$12 | Q60: =L60*'Assessment Inputs'!$B$12 | R60: high | S60: 1551 E Tangerine Rd, Oro Valley, AZ 85755
A61: Banner Ocotillo Medical Center | B61: Banner Health | C61: Chandler | D61: Maricopa | E61: 13 | G61: 9525760.8 | H61: 5048270.5 | I61: 11271215 | J61: =H61+I61 | K61: =J61-G61 | L61: =J61*'Assessment Inputs'!$B$14 | M61: =G61*'Assessment Inputs'!$B$14 | N61: =L61-M61 | O61: =K61*('Assessment Inputs'!$B$3-'Assessment Inputs'!$B$4)/'Assessment Inputs'!$B$3 | P61: =N61*'Assessment Inputs'!$B$12 | Q61: =L61*'Assessment Inputs'!$B$12 | R61: high | S61: 1405 S Alma School Rd, Chandler, AZ 85286
A62: Valley View Medical Center | B62: Lifepoint Health | C62: Fort Mohave | D62: Mohave | E62: 30 | G62: 4434861.1 | H62: 3404880.5 | I62: 11458577 | J62: =H62+I62 | K62: =J62-G62 | L62: =J62*'Assessment Inputs'!$B$14 | M62: =G62*'Assessment Inputs'!$B$14 | N62: =L62-M62 | O62: =K62*('Assessment Inputs'!$B$3-'Assessment Inputs'!$B$4)/'Assessment Inputs'!$B$3 | P62: =N62*'Assessment Inputs'!$B$12 | Q62: =L62*'Assessment Inputs'!$B$12 | R62: high | S62: 5330 S Highway 95, Fort Mohave, AZ 86426
... A75: Quail Run Behavioral Health | B75: Universal Health Services | C75: Phoenix | D75: Maricopa | E75: 2 | G75: 1189312.1 | H75: 5567433 | I75: 3993422 | J75: =H75+I75 | K75: =J75-G75 | L75: =J75*'Assessment Inputs'!$B$14 | M75: =G75*'Assessment Inputs'!$B$14 | N75: =L75-M75 | O75: =K75*('Assessment Inputs'!$B$3-'Assessment Inputs'!$B$4)/'Assessment Inputs'!$B$3 | P75: =N75*'Assessment Inputs'!$B$12 | Q75: =L75*'Assessment Inputs'!$B$12 | R75: high | S75: 2545 W Quail Ave, Phoenix, AZ 85027
A76: Sage Memorial Hospital | B76: IHS | C76: Ganado | D76: Apache | E76: 6 | F76: Yes | G76: 0 | H76: 8775256.4 | I76: 0 | J76: =H76+I76 | K76: =J76-G76 | L76: =J76*'Assessment Inputs'!$B$14 | M76: =G76*'Assessment Inputs'!$B$14 | N76: =L76-M76 | O76: =K76*('Assessment Inputs'!$B$3-'Assessment Inputs'!$B$4)/'Assessment Inputs'!$B$3 | P76: =N76*'Assessment Inputs'!$B$12 | Q76: =L76*'Assessment Inputs'!$B$12 | R76: medium | S76: Highway 264 and Highway 191, Ganado, AZ 86505
A77: Destiny Springs Healthcare | B77: Destiny Springs Healthcare | C77: Surprise | D77: Maricopa | E77: 28 | G77: 936785.9 | H77: 3174791.3 | I77: 5203974 | J77: =H77+I77 | K77: =J77-G77 | L77: =J77*'Assessment Inputs'!$B$14 | M77: =G77*'Assessment Inputs'!$B$14 | N77: =L77-M77 | O77: =K77*('Assessment Inputs'!$B$3-'Assessment Inputs'!$B$4)/'Assessment Inputs'!$B$3 | P77: =N77*'Assessment Inputs'!$B$12 | Q77: =L77*'Assessment Inputs'!$B$12 | R77: high | S77: 17300 N Dysart Rd, Surprise, AZ 85378
A78: College Medical Center Phoenix (formerly St. Luke's Behavioral Hospital) | B78: College Health Enterprises | C78: Phoenix | D78: Maricopa | E78: 5 | G78: 1580313.9 | H78: 2083345.9 | I78: 5911125 | J78: =H78+I78 | K78: =J78-G78 | L78: =J78*'Assessment Inputs'!$B$14 | M78: =G78*'Assessment Inputs'!$B$14 | N78: =L78-M78 | O78: =K78*('Assessment Inputs'!$B$3-'Assessment Inputs'!$B$4)/'Assessment Inputs'!$B$3 | P78: =N78*'Assessment Inputs'!$B$12 | Q78: =L78*'Assessment Inputs'!$B$12 | R78: high | S78: 1800 E Van Buren St, Phoenix, AZ 85006
A79: Haven Behavioral Hospital of Phoenix | B79: Haven Senior Horizons | C79: Phoenix | D79: Maricopa | E79: 11 | G79: 0 | H79: 5375815.3 | I79: 2490947 | J79: =H79+I79 | K79: =J79-G79 | L79: =J79*'Assessment Inputs'!$B$14 | M79: =G79*'Assessment Inputs'!$B$14 | N79: =L79-M79 | O79: =K79*('Assessment Inputs'!$B$3-'Assessment Inputs'!$B$4)/'Assessment Inputs'!$B$3 | P79: =N79*'Assessment Inputs'!$B$12 | Q79: =L79*'Assessment Inputs'!$B$12 | R79: high | S79: 1201 S 7th Ave, Phoenix, AZ 85007
A80: Banner Goldfield Medical Center | B80: Banner Health | C80: Apache Junction | D80: Pinal | E80: 10 | G80: 2259520.8 | H80: 1930747.9 | I80: 5672556 | J80: =H80+I80 | K80: =J80-G80 | L80: =J80*'Assessment Inputs'!$B$14 | M80: =G80*'Assessment Inputs'!$B$14 | N80: =L80-M80 | O80: =K80*('Assessment Inputs'!$B$3-'Assessment Inputs'!$B$4)/'Assessment Inputs'!$B$3 | P80: =N80*'Assessment Inputs'!$B$12 | Q80: =L80*'Assessment Inputs'!$B$12 | R80: high | S80: 2050 W Southern Ave, Apache Junction, AZ 85120
A81: The CORE Institute Specialty Hospital (The Surgical Hospital of Phoenix) | B81: Surgical Specialty Hospital of Arizona | C81: Phoenix | D81: Maricopa | E81: 26 | G81: 0 | H81: 5304257.6 | I81: 2275081 | J81: =H81+I81 | K81: =J81-G81 | L81: =J81*'Assessment Inputs'!$B$14 | M81: =G81*'Assessment Inputs'!$B$14 | N81: =L81-M81 | O81: =K81*('Assessment Inputs'!$B$3-'Assessment Inputs'!$B$4)/'Assessment Inputs'!$B$3 | P81: =N81*'Assessment Inputs'!$B$12 | Q81: =L81*'Assessment Inputs'!$B$12 | R81: high | S81: 6501 N 19th Ave, Phoenix, AZ 85015
A82: Page Hospital | B82: Banner Health | C82: Page | D82: Coconino | E82: 6 | G82: 906547.69 | H82: 1464241.3 | I82: 5189227 | J82: =H82+I82 | K82: =J82-G82 | L82: =J82*'Assessment Inputs'!$B$14 | M82: =G82*'Assessment Inputs'!$B$14 | N82: =L82-M82 | O82: =K82*('Assessment Inputs'!$B$3-'Assessment Inputs'!$B$4)/'Assessment Inputs'!$B$3 | P82: =N82*'Assessment Inputs'!$B$12 | Q82: =L82*'Assessment Inputs'!$B$12 | R82: medium | S82: 501 N Navajo Dr, Page, AZ 86040
A83: La Paz Regional Hospital | B83: La Paz Regional Hospital | C83: Parker | D83: La Paz | E83: 30 | G83: 1295184 | H83: 1639858.7 | I83: 4634125 | J83: =H83+I83 | K83: =J83-G83 | L83: =J83*'Assessment Inputs'!$B$14 | M83: =G83*'Assessment Inputs'!$B$14 | N83: =L83-M83 | O83: =K83*('Assessment Inputs'!$B$3-'Assessment Inputs'!$B$4)/'Assessment Inputs'!$B$3 | P83: =N83*'Assessment Inputs'!$B$12 | Q83: =L83*'Assessment Inputs'!$B$12 | R83: high | S83: 1200 W Mohave Rd, Parker, AZ 85344
A84: Phoenix Medical Psychiatric Hospital | B84: NeuroPsychiatric Hospitals | C84: Phoenix | D84: Maricopa | E84: 5 | G84: 0 | H84: 5655720.3 | I84: 312280 | J84: =H84+I84 | K84: =J84-G84 | L84: =J84*'Assessment Inputs'!$B$14 | M84: =G84*'Assessment Inputs'!$B$14 | N84: =L84-M84 | O84: =K84*('Assessment Inputs'!$B$3-'Assessment Inputs'!$B$4)/'Assessment Inputs'!$B$3 | P84: =N84*'Assessment Inputs'!$B$12 | Q84: =L84*'Assessment Inputs'!$B$12 | R84: high | S84: 1346 E McDowell Rd, Phoenix, AZ 85006
A85: Benson Hospital | B85: TMC Healthcare | C85: Benson | D85: Cochise | E85: 19 | G85: 753286.2 | H85: 1223359.8 | I85: 3554398 | J85: =H85+I85 | K85: =J85-G85 | L85: =J85*'Assessment Inputs'!$B$14 | M85: =G85*'Assessment Inputs'!$B$14 | N85: =L85-M85 | O85: =K85*('Assessment Inputs'!$B$3-'Assessment Inputs'!$B$4)/'Assessment Inputs'!$B$3 | P85: =N85*'Assessment Inputs'!$B$12 | Q85: =L85*'Assessment Inputs'!$B$12 | R85: high | S85: 450 S Ocotillo Ave, Benson, AZ 85602
A86: Tohono O'odham Nation Sells Hospital | B86: IHS | C86: Sells | D86: Pima | E86: 23 | F86: Yes | G86: 0 | H86: 4676852.1 | I86: 0 | J86: =H86+I86 | K86: =J86-G86 | L86: =J86*'Assessment Inputs'!$B$14 | M86: =G86*'Assessment Inputs'!$B$14 | N86: =L86-M86 | O86: =K86*('Assessment Inputs'!$B$3-'Assessment Inputs'!$B$4)/'Assessment Inputs'!$B$3 | P86: =N86*'Assessment Inputs'!$B$12 | Q86: =L86*'Assessment Inputs'!$B$12 | R86: medium | S86: Highway 86 at Topawa Rd, Sells, AZ 85634
A87: St. Joseph's Westgate Medical Center | B87: Dignity Health | C87: Glendale | D87: Maricopa | E87: 27 | G87: 0 | H87: 4530953.2 | I87: 0 | J87: =H87+I87 | K87: =J87-G87 | L87: =J87*'Assessment Inputs'!$B$14 | M87: =G87*'Assessment Inputs'!$B$14 | N87: =L87-M87 | O87: =K87*('Assessment Inputs'!$B$3-'Assessment Inputs'!$B$4)/'Assessment Inputs'!$B$3 | P87: =N87*'Assessment Inputs'!$B$12 | Q87: =L87*'Assessment Inputs'!$B$12 | R87: high | S87: 7300 N 99th Ave, Glendale, AZ 85305
A88: Hopi Health Care Center | B88: IHS | C88: Polacca | D88: Navajo | E88: 6 | F88: Yes | G88: 0 | H88: 4199020 | I88: 0 | J88: =H88+I88 | K88: =J88-G88 | L88: =J88*'Assessment Inputs'!$B$14 | M88: =G88*'Assessment Inputs'!$B$14 | N88: =L88-M88 | O88: =K88*('Assessment Inputs'!$B$3-'Assessment Inputs'!$B$4)/'Assessment Inputs'!$B$3 | P88: =N88*'Assessment Inputs'!$B$12 | Q88: =L88*'Assessment Inputs'!$B$12 | R88: medium | S88: Highway 264 Milepost 388, Polacca, AZ 86042
A89: Banner Heart Hospital | B89: Banner Health | C89: Mesa | D89: Maricopa | E89: 10 | G89: 0 | H89: 3330110.6 | I89: 730636 | J89: =H89+I89 | K89: =J89-G89 | L89: =J89*'Assessment Inputs'!$B$14 | M89: =G89*'Assessment Inputs'!$B$14 | N89: =L89-M89 | O89: =K89*('Assessment Inputs'!$B$3-'Assessment Inputs'!$B$4)/'Assessment Inputs'!$B$3 | P89: =N89*'Assessment Inputs'!$B$12 | Q89: =L89*'Assessment Inputs'!$B$12 | R89: high | S89: 6750 E Baywood Ave, Mesa, AZ 85206
A90: Banner Rehabilitation Hospital West (Peoria) | B90: Select Medical | C90: Peoria | D90: Maricopa | E90: 28 | G90: 0 | H90: 2341947.6 | I90: 1672687 | J90: =H90+I90 | K90: =J90-G90 | L90: =J90*'Assessment Inputs'!$B$14 | M90: =G90*'Assessment Inputs'!$B$14 | N90: =L90-M90 | O90: =K90*('Assessment Inputs'!$B$3-'Assessment Inputs'!$B$4)/'Assessment Inputs'!$B$3 | P90: =N90*'Assessment Inputs'!$B$12 | Q90: =L90*'Assessment Inputs'!$B$12 | R90: high | S90: 12740 N Plaza Del Rio Blvd, Peoria, AZ 85381
A91: Wickenburg Community Hospital | B91: Wickenburg Community Hospital | C91: Wickenburg | D91: Maricopa | E91: 30 | G91: 1116899.2 | H91: 1043091.7 | I91: 2659926 | J91: =H91+I91 | K91: =J91-G91 | L91: =J91*'Assessment Inputs'!$B$14 | M91: =G91*'Assessment Inputs'!$B$14 | N91: =L91-M91 | O91: =K91*('Assessment Inputs'!$B$3-'Assessment Inputs'!$B$4)/'Assessment Inputs'!$B$3 | P91: =N91*'Assessment Inputs'!$B$12 | Q91: =L91*'Assessment Inputs'!$B$12 | R91: high | S91: 520 Rose Ln, Wickenburg, AZ 85390
A92: Avenir Behavioral Health Center | B92: Avenir | C92: Surprise | D92: Maricopa | E92: 29 | G92: 0 | H92: 3004036.4 | I92: 689363 | J92: =H92+I92 | K92: =J92-G92 | L92: =J92*'Assessment Inputs'!$B$14 | M92: =G92*'Assessment Inputs'!$B$14 | N92: =L92-M92 | O92: =K92*('Assessment Inputs'!$B$3-'Assessment Inputs'!$B$4)/'Assessment Inputs'!$B$3 | P92: =N92*'Assessment Inputs'!$B$12 | Q92: =L92*'Assessment Inputs'!$B$12 | R92: high | S92: 16561 N Parkview Pl, Surprise, AZ 85374
A93: White Mountain Regional Medical Center | B93: White Mountain Regional Medical Center | C93: Springerville | D93: Apache | E93: 6 | G93: 790968.61 | H93: 927806.91 | I93: 2509476 | J93: =H93+I93 | K93: =J93-G93 | L93: =J93*'Assessment Inputs'!$B$14 | M93: =G93*'Assessment Inputs'!$B$14 | N93: =L93-M93 | O93: =K93*('Assessment Inputs'!$B$3-'Assessment Inputs'!$B$4)/'Assessment Inputs'!$B$3 | P93: =N93*'Assessment Inputs'!$B$12 | Q93: =L93*'Assessment Inputs'!$B$12 | R93: high | S93: 118 S Mountain Ave, Springerville, AZ 85938
A94: Northwest Medical Center Houghton | B94: Community Health Systems | C94: Tucson | D94: Pima | E94: 17 | G94: 0 | H94: 3054126.4 | I94: 0 | J94: =H94+I94 | K94: =J94-G94 | L94: =J94*'Assessment Inputs'!$B$14 | M94: =G94*'Assessment Inputs'!$B$14 | N94: =L94-M94 | O94: =K94*('Assessment Inputs'!$B$3-'Assessment Inputs'!$B$4)/'Assessment Inputs'!$B$3 | P94: =N94*'Assessment Inputs'!$B$12 | Q94: =L94*'Assessment Inputs'!$B$12 | R94: high | S94: 2200 S Houghton Rd, Tucson, AZ 85748
A95: City of Hope Cancer Center Phoenix (formerly CTCA Western Regional) | B95: City of Hope | C95: Goodyear | D95: Maricopa | E95: 23 | G95: 0 | H95: 2876416.6 | I95: 64249 | J95: =H95+I95 | K95: =J95-G95 | L95: =J95*'Assessment Inputs'!$B$14 | M95: =G95*'Assessment Inputs'!$B$14 | N95: =L95-M95 | O95: =K95*('Assessment Inputs'!$B$3-'Assessment Inputs'!$B$4)/'Assessment Inputs'!$B$3 | P95: =N95*'Assessment Inputs'!$B$12 | Q95: =L95*'Assessment Inputs'!$B$12 | R95: medium | S95: 14200 W Celebrate Life Way, Goodyear, AZ 85338
A96: Northern Cochise Community Hospital | B96: TMC Healthcare | C96: Willcox | D96: Cochise | E96: 19 | G96: 504323.88 | H96: 709832.49 | I96: 1946874 | J96: =H96+I96 | K96: =J96-G96 | L96: =J96*'Assessment Inputs'!$B$14 | M96: =G96*'Assessment Inputs'!$B$14 | N96: =L96-M96 | O96: =K96*('Assessment Inputs'!$B$3-'Assessment Inputs'!$B$4)/'Assessment Inputs'!$B$3 | P96: =N96*'Assessment Inputs'!$B$12 | Q96: =L96*'Assessment Inputs'!$B$12 | R96: high | S96: 901 W Rex Allen Dr, Willcox, AZ 85643
A97: Windhaven Psychiatric Hospital (Polara Health) | B97: Polara Health | C97: Prescott Valley | D97: Yavapai | E97: 1 | G97: 0 | H97: 1995950.1 | I97: 621982 | J97: =H97+I97 | K97: =J97-G97 | L97: =J97*'Assessment Inputs'!$B$14 | M97: =G97*'Assessment Inputs'!$B$14 | N97: =L97-M97 | O97: =K97*('Assessment Inputs'!$B$3-'Assessment Inputs'!$B$4)/'Assessment Inputs'!$B$3 | P97: =N97*'Assessment Inputs'!$B$12 | Q97: =L97*'Assessment Inputs'!$B$12 | R97: high | S97: 3347 N Windsong Dr, Prescott Valley, AZ 86314
A98: Encompass Health Rehabilitation Hospital of East Valley | B98: Encompass Health | C98: Mesa | D98: Maricopa | E98: 10 | G98: 0 | H98: 1562409.7 | I98: 959829 | J98: =H98+I98 | K98: =J98-G98 | L98: =J98*'Assessment Inputs'!$B$14 | M98: =G98*'Assessment Inputs'!$B$14 | N98: =L98-M98 | O98: =K98*('Assessment Inputs'!$B$3-'Assessment Inputs'!$B$4)/'Assessment Inputs'!$B$3 | P98: =N98*'Assessment Inputs'!$B$12 | Q98: =L98*'Assessment Inputs'!$B$12 | R98: high | S98: 5652 E Baseline Rd, Mesa, AZ 85206
A99: Parker Indian Health Center | B99: IHS | C99: Parker | D99: La Paz | E99: 30 | F99: Yes | G99: 0 | H99: 2428650.6 | I99: 0 | J99: =H99+I99 | K99: =J99-G99 | L99: =J99*'Assessment Inputs'!$B$14 | M99: =G99*'Assessment Inputs'!$B$14 | N99: =L99-M99 | O99: =K99*('Assessment Inputs'!$B$3-'Assessment Inputs'!$B$4)/'Assessment Inputs'!$B$3 | P99: =N99*'Assessment Inputs'!$B$12 | Q99: =L99*'Assessment Inputs'!$B$12 | R99: medium | S99: 12033 Agency Rd, Parker, AZ 85344
A100: Encompass Health Valley of the Sun Rehabilitation Hospital | B100: Encompass Health | C100: Glendale | D100: Maricopa | E100: 27 | G100: 0 | H100: 1427578.9 | I100: 843458 | J100: =H100+I100 | K100: =J100-G100 | L100: =J100*'Assessment Inputs'!$B$14 | M100: =G100*'Assessment Inputs'!$B$14 | N100: =L100-M100 | O100: =K100*('Assessment Inputs'!$B$3-'Assessment Inputs'!$B$4)/'Assessment Inputs'!$B$3 | P100: =N100*'Assessment Inputs'!$B$12 | Q100: =L100*'Assessment Inputs'!$B$12 | R100: high | S100: 13460 N 67th Ave, Glendale, AZ 85304
A101: Reunion Rehabilitation Hospital Phoenix | B101: Reunion Rehabilitation Hospitals | C101: Phoenix | D101: Maricopa | E101: 5 | G101: 0 | H101: 1291683.5 | I101: 935718 | J101: =H101+I101 | K101: =J101-G101 | L101: =J101*'Assessment Inputs'!$B$14 | M101: =G101*'Assessment Inputs'!$B$14 | N101: =L101-M101 | O101: =K101*('Assessment Inputs'!$B$3-'Assessment Inputs'!$B$4)/'Assessment Inputs'!$B$3 | P101: =N101*'Assessment Inputs'!$B$12 | Q101: =L101*'Assessment Inputs'!$B$12 | R101: high | S101: 1675 E Villa St, Phoenix, AZ 85006
A102: Agave Ridge Behavioral Health Hospital | B102: Acadia Healthcare | C102: Mesa | D102: Maricopa | E102: 15 | G102: 0 | H102: 2014135.6 | I102: 0 | J102: =H102+I102 | K102: =J102-G102 | L102: =J102*'Assessment Inputs'!$B$14 | M102: =G102*'Assessment Inputs'!$B$14 | N102: =L102-M102 | O102: =K102*('Assessment Inputs'!$B$3-'Assessment Inputs'!$B$4)/'Assessment Inputs'!$B$3 | P102: =N102*'Assessment Inputs'!$B$12 | Q102: =L102*'Assessment Inputs'!$B$12 | R102: medium | S102: 3322 S Ellsworth Rd, Mesa, AZ 85212
A103: Select Specialty Hospital – Phoenix (St. Joseph's campus) | B103: Select Medical | C103: Phoenix | D103: Maricopa | E103: 5 | G103: 175394.13 | H103: 774184.58 | I103: 1156516 | J103: =H103+I103 | K103: =J103-G103 | L103: =J103*'Assessment Inputs'!$B$14 | M103: =G103*'Assessment Inputs'!$B$14 | N103: =L103-M103 | O103: =K103*('Assessment Inputs'!$B$3-'Assessment Inputs'!$B$4)/'Assessment Inputs'!$B$3 | P103: =N103*'Assessment Inputs'!$B$12 | Q103: =L103*'Assessment Inputs'!$B$12 | R103: high | S103: 350 W Thomas Rd, Phoenix, AZ 85013
A104: Arizona Specialty Hospital (Phoenix campus; formerly OASIS Hospital) | B104: United Surgical Partners | C104: Phoenix | D104: Maricopa | E104: 8 | G104: 0 | H104: 1512869.5 | I104: 391421 | J104: =H104+I104 | K104: =J104-G104 | L104: =J104*'Assessment Inputs'!$B$14 | M104: =G104*'Assessment Inputs'!$B$14 | N104: =L104-M104 | O104: =K104*('Assessment Inputs'!$B$3-'Assessment Inputs'!$B$4)/'Assessment Inputs'!$B$3 | P104: =N104*'Assessment Inputs'!$B$12 | Q104: =L104*'Assessment Inputs'!$B$12 | R104: high | S104: 750 N 40th St, Phoenix, AZ 85008
A105: Encompass Health Rehabilitation Institute of Tucson | B105: Encompass Health | C105: Tucson | D105: Pima | E105: 18 | G105: 0 | H105: 1100357.8 | I105: 745978 | J105: =H105+I105 | K105: =J105-G105 | L105: =J105*'Assessment Inputs'!$B$14 | M105: =G105*'Assessment Inputs'!$B$14 | N105: =L105-M105 | O105: =K105*('Assessment Inputs'!$B$3-'Assessment Inputs'!$B$4)/'Assessment Inputs'!$B$3 | P105: =N105*'Assessment Inputs'!$B$12 | Q105: =L105*'Assessment Inputs'!$B$12 | R105: high | S105: 2650 N Wyatt Dr, Tucson, AZ 85712
A106: ChangePoint Psychiatric Hospital | B106: Changepoint Integrated Health Centers | C106: Lakeside | D106: Navajo | E106: 7 | G106: 0 | H106: 1349622.5 | I106: 476078 | J106: =H106+I106 | K106: =J106-G106 | L106: =J106*'Assessment Inputs'!$B$14 | M106: =G106*'Assessment Inputs'!$B$14 | N106: =L106-M106 | O106: =K106*('Assessment Inputs'!$B$3-'Assessment Inputs'!$B$4)/'Assessment Inputs'!$B$3 | P106: =N106*'Assessment Inputs'!$B$12 | Q106: =L106*'Assessment Inputs'!$B$12 | R106: high | S106: 1920 W Commerce Dr, Lakeside, AZ 85929
A107: Rehabilitation Hospital of Northern Arizona | B107: Ernest Health, Inc. | C107: Flagstaff | D107: Coconino | E107: 6 | G107: 0 | H107: 1519078.6 | I107: 255697 | J107: =H107+I107 | K107: =J107-G107 | L107: =J107*'Assessment Inputs'!$B$14 | M107: =G107*'Assessment Inputs'!$B$14 | N107: =L107-M107 | O107: =K107*('Assessment Inputs'!$B$3-'Assessment Inputs'!$B$4)/'Assessment Inputs'!$B$3 | P107: =N107*'Assessment Inputs'!$B$12 | Q107: =L107*'Assessment Inputs'!$B$12 | R107: high | S107: 1851 N Gemini Dr, Flagstaff, AZ 86001
A108: Select Specialty Hospital – Phoenix Downtown (Banner UMC Phoenix campus) | B108: Select Medical | C108: Phoenix | D108: Maricopa | E108: 5 | G108: 144934.71 | H108: 1136946.5 | I108: 466100 | J108: =H108+I108 | K108: =J108-G108 | L108: =J108*'Assessment Inputs'!$B$14 | M108: =G108*'Assessment Inputs'!$B$14 | N108: =L108-M108 | O108: =K108*('Assessment Inputs'!$B$3-'Assessment Inputs'!$B$4)/'Assessment Inputs'!$B$3 | P108: =N108*'Assessment Inputs'!$B$12 | Q108: =L108*'Assessment Inputs'!$B$12 | R108: high | S108: 1111 E McDowell Rd, Phoenix, AZ 85006
A109: HonorHealth Rehabilitation Hospital | B109: Select Medical | C109: Scottsdale | D109: Maricopa | E109: 8 | G109: 0 | H109: 1023229.1 | I109: 463351 | J109: =H109+I109 | K109: =J109-G109 | L109: =J109*'Assessment Inputs'!$B$14 | M109: =G109*'Assessment Inputs'!$B$14 | N109: =L109-M109 | O109: =K109*('Assessment Inputs'!$B$3-'Assessment Inputs'!$B$4)/'Assessment Inputs'!$B$3 | P109: =N109*'Assessment Inputs'!$B$12 | Q109: =L109*'Assessment Inputs'!$B$12 | R109: high | S109: 8850 E Pima Center Pkwy, Scottsdale, AZ 85258
A110: Exceptional Community Hospital – Maricopa | B110: Exceptional Healthcare | C110: Maricopa | D110: Pinal | E110: 16 | G110: 0 | H110: 1297751.8 | I110: 116646 | J110: =H110+I110 | K110: =J110-G110 | L110: =J110*'Assessment Inputs'!$B$14 | M110: =G110*'Assessment Inputs'!$B$14 | N110: =L110-M110 | O110: =K110*('Assessment Inputs'!$B$3-'Assessment Inputs'!$B$4)/'Assessment Inputs'!$B$3 | P110: =N110*'Assessment Inputs'!$B$12 | Q110: =L110*'Assessment Inputs'!$B$12 | R110: medium | S110: 19060 N John Wayne Pkwy, Maricopa, AZ 85139
A111: Select Specialty Hospital – Tucson (Northwest) | B111: Select Medical | C111: Tucson | D111: Pima | E111: 18 | G111: 157582.09 | H111: 971530.1 | I111: 299209 | J111: =H111+I111 | K111: =J111-G111 | L111: =J111*'Assessment Inputs'!$B$14 | M111: =G111*'Assessment Inputs'!$B$14 | N111: =L111-M111 | O111: =K111*('Assessment Inputs'!$B$3-'Assessment Inputs'!$B$4)/'Assessment Inputs'!$B$3 | P111: =N111*'Assessment Inputs'!$B$12 | Q111: =L111*'Assessment Inputs'!$B$12 | R111: high | S111: 2025 W Orange Grove Rd, Tucson, AZ 85704
... A135: Talas Harbor at Buckeye (Phoenix) (closed) | B135: Talas Harbor | C135: Phoenix | D135: Maricopa | E135: 11 | G135: 0 | H135: 0 | I135: 0 | J135: =H135+I135 | K135: =J135-G135 | L135: =J135*'Assessment Inputs'!$B$14 | M135: =G135*'Assessment Inputs'!$B$14 | N135: =L135-M135 | O135: =K135*('Assessment Inputs'!$B$3-'Assessment Inputs'!$B$4)/'Assessment Inputs'!$B$3 | P135: =N135*'Assessment Inputs'!$B$12 | Q135: =L135*'Assessment Inputs'!$B$12 | R135: high | S135: 1407 S 9th Ave, Phoenix, AZ 85007
A136: All facilities | G136: =SUM(G2:G135) | H136: =SUM(H2:H135) | I136: =SUM(I2:I135) | J136: =SUM(J2:J135) | K136: =SUM(K2:K135) | L136: =SUM(L2:L135) | M136: =SUM(M2:M135) | N136: =SUM(N2:N135) | ... Q136: =SUM(Q2:Q135)
A137: Excluding IHS / tribal facilities | G137: =SUMIF($F$2:$F$135,"",G2:G135) | H137: =SUMIF($F$2:$F$135,"",H2:H135) | I137: =SUMIF($F$2:$F$135,"",I2:I135) | J137: =SUMIF($F$2:$F$135,"",J2:J135) | K137: =SUMIF($F$2:$F$135,"",K2:K135) | L137: =SUMIF($F$2:$F$135,"",L2:L135) | M137: =SUMIF($F$2:$F$135,"",M2:M135) | N137: =SUMIF($F$2:$F$135,"",N2:N135) | ... Q137: =SUMIF($F$2:$F$135,"",Q2:Q135)
A139: Source: AHCCCS, SFY 2025 Hospital Assessment Report to the Legislature (A.R.S. 36-2903.08), June 1 2026 — https://www.azahcccs.gov/shared/Downloads/Reporting/2026/2026HospitalAssessmentReport.pdf . Blue = figures as printed in the report (facilities appearing under two names are combined). Closed facilities (Talas Harbor x2, PAM Health Specialty, Medical Behavioral Hospital of Northern Arizona) had no SFY 2025 flows and are omitted from totals.

Sheet Assessment by System
A1: Hospital system | B1: Facilities | C1: SFY 2025 assessment paid | D1: SFY 2025 payments received | E1: Net gain | F1: Payments lost per year at 3.5% (revenue reduction) | G1: Assessment saved per year | H1: Net loss per year at 3.5% | I1: Net loss in FFY 2028 (first step) | J1: Ten-year payments lost | K1: Ten-year net loss | L1: IHS / tribal
A2: Banner Health | B2: 18 | C2: =SUMIF('Assessment by Facility'!$B$2:$B$135,A2,'Assessment by Facility'!$G$2:$G$135) | D2: =SUMIF('Assessment by Facility'!$B$2:$B$135,A2,'Assessment by Facility'!$J$2:$J$135) | E2: =D2-C2 | F2: =D2*'Assessment Inputs'!$B$14 | G2: =C2*'Assessment Inputs'!$B$14 | H2: =F2-G2 | I2: =E2*('Assessment Inputs'!$B$3-'Assessment Inputs'!$B$4)/'Assessment Inputs'!$B$3 | J2: =F2*'Assessment Inputs'!$B$12 | K2: =H2*'Assessment Inputs'!$B$12
A3: Dignity Health | B3: 8 | C3: =SUMIF('Assessment by Facility'!$B$2:$B$135,A3,'Assessment by Facility'!$G$2:$G$135) | D3: =SUMIF('Assessment by Facility'!$B$2:$B$135,A3,'Assessment by Facility'!$J$2:$J$135) | E3: =D3-C3 | F3: =D3*'Assessment Inputs'!$B$14 | G3: =C3*'Assessment Inputs'!$B$14 | H3: =F3-G3 | I3: =E3*('Assessment Inputs'!$B$3-'Assessment Inputs'!$B$4)/'Assessment Inputs'!$B$3 | J3: =F3*'Assessment Inputs'!$B$12 | K3: =H3*'Assessment Inputs'!$B$12
A4: HonorHealth | B4: 9 | C4: =SUMIF('Assessment by Facility'!$B$2:$B$135,A4,'Assessment by Facility'!$G$2:$G$135) | D4: =SUMIF('Assessment by Facility'!$B$2:$B$135,A4,'Assessment by Facility'!$J$2:$J$135) | E4: =D4-C4 | F4: =D4*'Assessment Inputs'!$B$14 | G4: =C4*'Assessment Inputs'!$B$14 | H4: =F4-G4 | I4: =E4*('Assessment Inputs'!$B$3-'Assessment Inputs'!$B$4)/'Assessment Inputs'!$B$3 | J4: =F4*'Assessment Inputs'!$B$12 | K4: =H4*'Assessment Inputs'!$B$12
A5: Abrazo Health Care | B5: 8 | C5: =SUMIF('Assessment by Facility'!$B$2:$B$135,A5,'Assessment by Facility'!$G$2:$G$135) | D5: =SUMIF('Assessment by Facility'!$B$2:$B$135,A5,'Assessment by Facility'!$J$2:$J$135) | E5: =D5-C5 | F5: =D5*'Assessment Inputs'!$B$14 | G5: =C5*'Assessment Inputs'!$B$14 | H5: =F5-G5 | I5: =E5*('Assessment Inputs'!$B$3-'Assessment Inputs'!$B$4)/'Assessment Inputs'!$B$3 | J5: =F5*'Assessment Inputs'!$B$12 | K5: =H5*'Assessment Inputs'!$B$12
A6: IHS | B6: 10 | C6: =SUMIF('Assessment by Facility'!$B$2:$B$135,A6,'Assessment by Facility'!$G$2:$G$135) | D6: =SUMIF('Assessment by Facility'!$B$2:$B$135,A6,'Assessment by Facility'!$J$2:$J$135) | E6: =D6-C6 | F6: =D6*'Assessment Inputs'!$B$14 | G6: =C6*'Assessment Inputs'!$B$14 | H6: =F6-G6 | I6: =E6*('Assessment Inputs'!$B$3-'Assessment Inputs'!$B$4)/'Assessment Inputs'!$B$3 | J6: =F6*'Assessment Inputs'!$B$12 | K6: =H6*'Assessment Inputs'!$B$12 | L6: Yes
A7: TMC Healthcare | B7: 3 | C7: =SUMIF('Assessment by Facility'!$B$2:$B$135,A7,'Assessment by Facility'!$G$2:$G$135) | D7: =SUMIF('Assessment by Facility'!$B$2:$B$135,A7,'Assessment by Facility'!$J$2:$J$135) | E7: =D7-C7 | F7: =D7*'Assessment Inputs'!$B$14 | G7: =C7*'Assessment Inputs'!$B$14 | H7: =F7-G7 | I7: =E7*('Assessment Inputs'!$B$3-'Assessment Inputs'!$B$4)/'Assessment Inputs'!$B$3 | J7: =F7*'Assessment Inputs'!$B$12 | K7: =H7*'Assessment Inputs'!$B$12
A8: Onvida Health | B8: 1 | C8: =SUMIF('Assessment by Facility'!$B$2:$B$135,A8,'Assessment by Facility'!$G$2:$G$135) | D8: =SUMIF('Assessment by Facility'!$B$2:$B$135,A8,'Assessment by Facility'!$J$2:$J$135) | E8: =D8-C8 | F8: =D8*'Assessment Inputs'!$B$14 | G8: =C8*'Assessment Inputs'!$B$14 | H8: =F8-G8 | I8: =E8*('Assessment Inputs'!$B$3-'Assessment Inputs'!$B$4)/'Assessment Inputs'!$B$3 | J8: =F8*'Assessment Inputs'!$B$12 | K8: =H8*'Assessment Inputs'!$B$12
A9: Valleywise Health | B9: 1 | C9: =SUMIF('Assessment by Facility'!$B$2:$B$135,A9,'Assessment by Facility'!$G$2:$G$135) | D9: =SUMIF('Assessment by Facility'!$B$2:$B$135,A9,'Assessment by Facility'!$J$2:$J$135) | E9: =D9-C9 | F9: =D9*'Assessment Inputs'!$B$14 | G9: =C9*'Assessment Inputs'!$B$14 | H9: =F9-G9 | I9: =E9*('Assessment Inputs'!$B$3-'Assessment Inputs'!$B$4)/'Assessment Inputs'!$B$3 | J9: =F9*'Assessment Inputs'!$B$12 | K9: =H9*'Assessment Inputs'!$B$12
A10: Community Health Systems | B10: 5 | C10: =SUMIF('Assessment by Facility'!$B$2:$B$135,A10,'Assessment by Facility'!$G$2:$G$135) | D10: =SUMIF('Assessment by Facility'!$B$2:$B$135,A10,'Assessment by Facility'!$J$2:$J$135) | E10: =D10-C10 | F10: =D10*'Assessment Inputs'!$B$14 | G10: =C10*'Assessment Inputs'!$B$14 | H10: =F10-G10 | I10: =E10*('Assessment Inputs'!$B$3-'Assessment Inputs'!$B$4)/'Assessment Inputs'!$B$3 | J10: =F10*'Assessment Inputs'!$B$12 | K10: =H10*'Assessment Inputs'!$B$12
A11: Phoenix Children's Hospital | B11: 1 | C11: =SUMIF('Assessment by Facility'!$B$2:$B$135,A11,'Assessment by Facility'!$G$2:$G$135) | D11: =SUMIF('Assessment by Facility'!$B$2:$B$135,A11,'Assessment by Facility'!$J$2:$J$135) | E11: =D11-C11 | F11: =D11*'Assessment Inputs'!$B$14 | G11: =C11*'Assessment Inputs'!$B$14 | H11: =F11-G11 | I11: =E11*('Assessment Inputs'!$B$3-'Assessment Inputs'!$B$4)/'Assessment Inputs'!$B$3 | J11: =F11*'Assessment Inputs'!$B$12 | K11: =H11*'Assessment Inputs'!$B$12
A12: Lifepoint Health | B12: 7 | C12: =SUMIF('Assessment by Facility'!$B$2:$B$135,A12,'Assessment by Facility'!$G$2:$G$135) | D12: =SUMIF('Assessment by Facility'!$B$2:$B$135,A12,'Assessment by Facility'!$J$2:$J$135) | E12: =D12-C12 | F12: =D12*'Assessment Inputs'!$B$14 | G12: =C12*'Assessment Inputs'!$B$14 | H12: =F12-G12 | I12: =E12*('Assessment Inputs'!$B$3-'Assessment Inputs'!$B$4)/'Assessment Inputs'!$B$3 | J12: =F12*'Assessment Inputs'!$B$12 | K12: =H12*'Assessment Inputs'!$B$12
A13: Northern Arizona | B13: 2 | C13: =SUMIF('Assessment by Facility'!$B$2:$B$135,A13,'Assessment by Facility'!$G$2:$G$135) | D13: =SUMIF('Assessment by Facility'!$B$2:$B$135,A13,'Assessment by Facility'!$J$2:$J$135) | E13: =D13-C13 | F13: =D13*'Assessment Inputs'!$B$14 | G13: =C13*'Assessment Inputs'!$B$14 | H13: =F13-G13 | I13: =E13*('Assessment Inputs'!$B$3-'Assessment Inputs'!$B$4)/'Assessment Inputs'!$B$3 | J13: =F13*'Assessment Inputs'!$B$12 | K13: =H13*'Assessment Inputs'!$B$12
A14: Kingman Regional Medical Center | B14: 1 | C14: =SUMIF('Assessment by Facility'!$B$2:$B$135,A14,'Assessment by Facility'!$G$2:$G$135) | D14: =SUMIF('Assessment by Facility'!$B$2:$B$135,A14,'Assessment by Facility'!$J$2:$J$135) | E14: =D14-C14 | F14: =D14*'Assessment Inputs'!$B$14 | G14: =C14*'Assessment Inputs'!$B$14 | H14: =F14-G14 | I14: =E14*('Assessment Inputs'!$B$3-'Assessment Inputs'!$B$4)/'Assessment Inputs'!$B$3 | J14: =F14*'Assessment Inputs'!$B$12 | K14: =H14*'Assessment Inputs'!$B$12
A15: Summit Healthcare | B15: 1 | C15: =SUMIF('Assessment by Facility'!$B$2:$B$135,A15,'Assessment by Facility'!$G$2:$G$135) | D15: =SUMIF('Assessment by Facility'!$B$2:$B$135,A15,'Assessment by Facility'!$J$2:$J$135) | E15: =D15-C15 | F15: =D15*'Assessment Inputs'!$B$14 | G15: =C15*'Assessment Inputs'!$B$14 | H15: =F15-G15 | I15: =E15*('Assessment Inputs'!$B$3-'Assessment Inputs'!$B$4)/'Assessment Inputs'!$B$3 | J15: =F15*'Assessment Inputs'!$B$12 | K15: =H15*'Assessment Inputs'!$B$12
A16: Universal Health Services | B16: 4 | C16: =SUMIF('Assessment by Facility'!$B$2:$B$135,A16,'Assessment by Facility'!$G$2:$G$135) | D16: =SUMIF('Assessment by Facility'!$B$2:$B$135,A16,'Assessment by Facility'!$J$2:$J$135) | E16: =D16-C16 | F16: =D16*'Assessment Inputs'!$B$14 | G16: =C16*'Assessment Inputs'!$B$14 | H16: =F16-G16 | I16: =E16*('Assessment Inputs'!$B$3-'Assessment Inputs'!$B$4)/'Assessment Inputs'!$B$3 | J16: =F16*'Assessment Inputs'!$B$12 | K16: =H16*'Assessment Inputs'!$B$12
A17: Aurora Behavioral Health System | B17: 2 | C17: =SUMIF('Assessment by Facility'!$B$2:$B$135,A17,'Assessment by Facility'!$G$2:$G$135) | D17: =SUMIF('Assessment by Facility'!$B$2:$B$135,A17,'Assessment by Facility'!$J$2:$J$135) | E17: =D17-C17 | F17: =D17*'Assessment Inputs'!$B$14 | G17: =C17*'Assessment Inputs'!$B$14 | H17: =F17-G17 | I17: =E17*('Assessment Inputs'!$B$3-'Assessment Inputs'!$B$4)/'Assessment Inputs'!$B$3 | J17: =F17*'Assessment Inputs'!$B$12 | K17: =H17*'Assessment Inputs'!$B$12
A18: Acadia Healthcare | B18: 3 | C18: =SUMIF('Assessment by Facility'!$B$2:$B$135,A18,'Assessment by Facility'!$G$2:$G$135) | D18: =SUMIF('Assessment by Facility'!$B$2:$B$135,A18,'Assessment by Facility'!$J$2:$J$135) | E18: =D18-C18 | F18: =D18*'Assessment Inputs'!$B$14 | G18: =C18*'Assessment Inputs'!$B$14 | H18: =F18-G18 | I18: =E18*('Assessment Inputs'!$B$3-'Assessment Inputs'!$B$4)/'Assessment Inputs'!$B$3 | J18: =F18*'Assessment Inputs'!$B$12 | K18: =H18*'Assessment Inputs'!$B$12
A19: Cobre Valley Regional Medical Center | B19: 1 | C19: =SUMIF('Assessment by Facility'!$B$2:$B$135,A19,'Assessment by Facility'!$G$2:$G$135) | D19: =SUMIF('Assessment by Facility'!$B$2:$B$135,A19,'Assessment by Facility'!$J$2:$J$135) | E19: =D19-C19 | F19: =D19*'Assessment Inputs'!$B$14 | G19: =C19*'Assessment Inputs'!$B$14 | H19: =F19-G19 | I19: =E19*('Assessment Inputs'!$B$3-'Assessment Inputs'!$B$4)/'Assessment Inputs'!$B$3 | J19: =F19*'Assessment Inputs'!$B$12 | K19: =H19*'Assessment Inputs'!$B$12
A20: Tuba City Regional Health Care Corporation | B20: 1 | C20: =SUMIF('Assessment by Facility'!$B$2:$B$135,A20,'Assessment by Facility'!$G$2:$G$135) | D20: =SUMIF('Assessment by Facility'!$B$2:$B$135,A20,'Assessment by Facility'!$J$2:$J$135) | E20: =D20-C20 | F20: =D20*'Assessment Inputs'!$B$14 | G20: =C20*'Assessment Inputs'!$B$14 | H20: =F20-G20 | I20: =E20*('Assessment Inputs'!$B$3-'Assessment Inputs'!$B$4)/'Assessment Inputs'!$B$3 | J20: =F20*'Assessment Inputs'!$B$12 | K20: =H20*'Assessment Inputs'!$B$12 | L20: Yes
A21: Mt. Graham Regional Medical Center | B21: 1 | C21: =SUMIF('Assessment by Facility'!$B$2:$B$135,A21,'Assessment by Facility'!$G$2:$G$135) | D21: =SUMIF('Assessment by Facility'!$B$2:$B$135,A21,'Assessment by Facility'!$J$2:$J$135) | E21: =D21-C21 | F21: =D21*'Assessment Inputs'!$B$14 | G21: =C21*'Assessment Inputs'!$B$14 | H21: =F21-G21 | I21: =E21*('Assessment Inputs'!$B$3-'Assessment Inputs'!$B$4)/'Assessment Inputs'!$B$3 | J21: =F21*'Assessment Inputs'!$B$12 | K21: =H21*'Assessment Inputs'!$B$12
A22: Mayo | B22: 1 | C22: =SUMIF('Assessment by Facility'!$B$2:$B$135,A22,'Assessment by Facility'!$G$2:$G$135) | D22: =SUMIF('Assessment by Facility'!$B$2:$B$135,A22,'Assessment by Facility'!$J$2:$J$135) | E22: =D22-C22 | F22: =D22*'Assessment Inputs'!$B$14 | G22: =C22*'Assessment Inputs'!$B$14 | H22: =F22-G22 | I22: =E22*('Assessment Inputs'!$B$3-'Assessment Inputs'!$B$4)/'Assessment Inputs'!$B$3 | J22: =F22*'Assessment Inputs'!$B$12 | K22: =H22*'Assessment Inputs'!$B$12
A23: Copper Queen Community Hospital | B23: 1 | C23: =SUMIF('Assessment by Facility'!$B$2:$B$135,A23,'Assessment by Facility'!$G$2:$G$135) | D23: =SUMIF('Assessment by Facility'!$B$2:$B$135,A23,'Assessment by Facility'!$J$2:$J$135) | E23: =D23-C23 | F23: =D23*'Assessment Inputs'!$B$14 | G23: =C23*'Assessment Inputs'!$B$14 | H23: =F23-G23 | I23: =E23*('Assessment Inputs'!$B$3-'Assessment Inputs'!$B$4)/'Assessment Inputs'!$B$3 | J23: =F23*'Assessment Inputs'!$B$12 | K23: =H23*'Assessment Inputs'!$B$12
A24: Select Medical | B24: 5 | C24: =SUMIF('Assessment by Facility'!$B$2:$B$135,A24,'Assessment by Facility'!$G$2:$G$135) | D24: =SUMIF('Assessment by Facility'!$B$2:$B$135,A24,'Assessment by Facility'!$J$2:$J$135) | E24: =D24-C24 | F24: =D24*'Assessment Inputs'!$B$14 | G24: =C24*'Assessment Inputs'!$B$14 | H24: =F24-G24 | I24: =E24*('Assessment Inputs'!$B$3-'Assessment Inputs'!$B$4)/'Assessment Inputs'!$B$3 | J24: =F24*'Assessment Inputs'!$B$12 | K24: =H24*'Assessment Inputs'!$B$12
A25: Little Colorado | B25: 1 | C25: =SUMIF('Assessment by Facility'!$B$2:$B$135,A25,'Assessment by Facility'!$G$2:$G$135) | D25: =SUMIF('Assessment by Facility'!$B$2:$B$135,A25,'Assessment by Facility'!$J$2:$J$135) | E25: =D25-C25 | F25: =D25*'Assessment Inputs'!$B$14 | G25: =C25*'Assessment Inputs'!$B$14 | H25: =F25-G25 | I25: =E25*('Assessment Inputs'!$B$3-'Assessment Inputs'!$B$4)/'Assessment Inputs'!$B$3 | J25: =F25*'Assessment Inputs'!$B$12 | K25: =H25*'Assessment Inputs'!$B$12
A26: Encompass Health | B26: 6 | C26: =SUMIF('Assessment by Facility'!$B$2:$B$135,A26,'Assessment by Facility'!$G$2:$G$135) | D26: =SUMIF('Assessment by Facility'!$B$2:$B$135,A26,'Assessment by Facility'!$J$2:$J$135) | E26: =D26-C26 | F26: =D26*'Assessment Inputs'!$B$14 | G26: =C26*'Assessment Inputs'!$B$14 | H26: =F26-G26 | I26: =E26*('Assessment Inputs'!$B$3-'Assessment Inputs'!$B$4)/'Assessment Inputs'!$B$3 | J26: =F26*'Assessment Inputs'!$B$12 | K26: =H26*'Assessment Inputs'!$B$12
A27: Destiny Springs Healthcare | B27: 1 | C27: =SUMIF('Assessment by Facility'!$B$2:$B$135,A27,'Assessment by Facility'!$G$2:$G$135) | D27: =SUMIF('Assessment by Facility'!$B$2:$B$135,A27,'Assessment by Facility'!$J$2:$J$135) | E27: =D27-C27 | F27: =D27*'Assessment Inputs'!$B$14 | G27: =C27*'Assessment Inputs'!$B$14 | H27: =F27-G27 | I27: =E27*('Assessment Inputs'!$B$3-'Assessment Inputs'!$B$4)/'Assessment Inputs'!$B$3 | J27: =F27*'Assessment Inputs'!$B$12 | K27: =H27*'Assessment Inputs'!$B$12
A28: College Health Enterprises | B28: 1 | C28: =SUMIF('Assessment by Facility'!$B$2:$B$135,A28,'Assessment by Facility'!$G$2:$G$135) | D28: =SUMIF('Assessment by Facility'!$B$2:$B$135,A28,'Assessment by Facility'!$J$2:$J$135) | E28: =D28-C28 | F28: =D28*'Assessment Inputs'!$B$14 | G28: =C28*'Assessment Inputs'!$B$14 | H28: =F28-G28 | I28: =E28*('Assessment Inputs'!$B$3-'Assessment Inputs'!$B$4)/'Assessment Inputs'!$B$3 | J28: =F28*'Assessment Inputs'!$B$12 | K28: =H28*'Assessment Inputs'!$B$12
A29: Haven Senior Horizons | B29: 1 | C29: =SUMIF('Assessment by Facility'!$B$2:$B$135,A29,'Assessment by Facility'!$G$2:$G$135) | D29: =SUMIF('Assessment by Facility'!$B$2:$B$135,A29,'Assessment by Facility'!$J$2:$J$135) | E29: =D29-C29 | F29: =D29*'Assessment Inputs'!$B$14 | G29: =C29*'Assessment Inputs'!$B$14 | H29: =F29-G29 | I29: =E29*('Assessment Inputs'!$B$3-'Assessment Inputs'!$B$4)/'Assessment Inputs'!$B$3 | J29: =F29*'Assessment Inputs'!$B$12 | K29: =H29*'Assessment Inputs'!$B$12
A30: Surgical Specialty Hospital of Arizona | B30: 1 | C30: =SUMIF('Assessment by Facility'!$B$2:$B$135,A30,'Assessment by Facility'!$G$2:$G$135) | D30: =SUMIF('Assessment by Facility'!$B$2:$B$135,A30,'Assessment by Facility'!$J$2:$J$135) | E30: =D30-C30 | F30: =D30*'Assessment Inputs'!$B$14 | G30: =C30*'Assessment Inputs'!$B$14 | H30: =F30-G30 | I30: =E30*('Assessment Inputs'!$B$3-'Assessment Inputs'!$B$4)/'Assessment Inputs'!$B$3 | J30: =F30*'Assessment Inputs'!$B$12 | K30: =H30*'Assessment Inputs'!$B$12
A31: La Paz Regional Hospital | B31: 1 | C31: =SUMIF('Assessment by Facility'!$B$2:$B$135,A31,'Assessment by Facility'!$G$2:$G$135) | D31: =SUMIF('Assessment by Facility'!$B$2:$B$135,A31,'Assessment by Facility'!$J$2:$J$135) | E31: =D31-C31 | F31: =D31*'Assessment Inputs'!$B$14 | G31: =C31*'Assessment Inputs'!$B$14 | H31: =F31-G31 | I31: =E31*('Assessment Inputs'!$B$3-'Assessment Inputs'!$B$4)/'Assessment Inputs'!$B$3 | J31: =F31*'Assessment Inputs'!$B$12 | K31: =H31*'Assessment Inputs'!$B$12
A32: NeuroPsychiatric Hospitals | B32: 1 | C32: =SUMIF('Assessment by Facility'!$B$2:$B$135,A32,'Assessment by Facility'!$G$2:$G$135) | D32: =SUMIF('Assessment by Facility'!$B$2:$B$135,A32,'Assessment by Facility'!$J$2:$J$135) | E32: =D32-C32 | F32: =D32*'Assessment Inputs'!$B$14 | G32: =C32*'Assessment Inputs'!$B$14 | H32: =F32-G32 | I32: =E32*('Assessment Inputs'!$B$3-'Assessment Inputs'!$B$4)/'Assessment Inputs'!$B$3 | J32: =F32*'Assessment Inputs'!$B$12 | K32: =H32*'Assessment Inputs'!$B$12
... A52: Sana Behavioral Hospital | B52: 1 | C52: =SUMIF('Assessment by Facility'!$B$2:$B$135,A52,'Assessment by Facility'!$G$2:$G$135) | D52: =SUMIF('Assessment by Facility'!$B$2:$B$135,A52,'Assessment by Facility'!$J$2:$J$135) | E52: =D52-C52 | F52: =D52*'Assessment Inputs'!$B$14 | G52: =C52*'Assessment Inputs'!$B$14 | H52: =F52-G52 | I52: =E52*('Assessment Inputs'!$B$3-'Assessment Inputs'!$B$4)/'Assessment Inputs'!$B$3 | J52: =F52*'Assessment Inputs'!$B$12 | K52: =H52*'Assessment Inputs'!$B$12
A53: Total | B53: =SUM(B2:B52) | C53: =SUM(C2:C52) | D53: =SUM(D2:D52) | E53: =SUM(E2:E52) | F53: =SUM(F2:F52) | G53: =SUM(G2:G52) | H53: =SUM(H2:H52) | I53: =SUM(I2:I52) | ... K53: =SUM(K2:K52)

Sheet Assessment by District
A1: LD | B1: Facilities located in district | C1: SFY 2025 assessment paid | D1: SFY 2025 payments received | E1: Payments lost per year at 3.5% | F1: Assessment saved per year | G1: Net loss per year at 3.5% | H1: Ten-year net loss | I1: Hospitals
A2: 1 | B2: 5 | C2: =SUMIF('Assessment by Facility'!$E$2:$E$135,A2,'Assessment by Facility'!$G$2:$G$135) | D2: =SUMIF('Assessment by Facility'!$E$2:$E$135,A2,'Assessment by Facility'!$J$2:$J$135) | E2: =D2*'Assessment Inputs'!$B$14 | F2: =C2*'Assessment Inputs'!$B$14 | G2: =E2-F2 | H2: =G2*'Assessment Inputs'!$B$12 | I2: (no assessment-program hospital located in district)
A3: 2 | B3: 2 | C3: =SUMIF('Assessment by Facility'!$E$2:$E$135,A3,'Assessment by Facility'!$G$2:$G$135) | D3: =SUMIF('Assessment by Facility'!$E$2:$E$135,A3,'Assessment by Facility'!$J$2:$J$135) | E3: =D3*'Assessment Inputs'!$B$14 | F3: =C3*'Assessment Inputs'!$B$14 | G3: =E3-F3 | H3: =G3*'Assessment Inputs'!$B$12 | I3: Medical Behavioral Hospital of Northern Arizona (closed); Mountain Valley Regional Rehabilitation Hospital; Verde Valley Medical Center; Windhaven Psychiatric Hospital (Polara Health); Yavapai Regional Medical Center
A4: 3 | B4: 3 | C4: =SUMIF('Assessment by Facility'!$E$2:$E$135,A4,'Assessment by Facility'!$G$2:$G$135) | D4: =SUMIF('Assessment by Facility'!$E$2:$E$135,A4,'Assessment by Facility'!$J$2:$J$135) | E4: =D4*'Assessment Inputs'!$B$14 | F4: =C4*'Assessment Inputs'!$B$14 | G4: =E4-F4 | H4: =G4*'Assessment Inputs'!$B$12 | I4: HonorHealth Deer Valley Medical Center; Quail Run Behavioral Health
A5: 4 | B5: 3 | C5: =SUMIF('Assessment by Facility'!$E$2:$E$135,A5,'Assessment by Facility'!$G$2:$G$135) | D5: =SUMIF('Assessment by Facility'!$E$2:$E$135,A5,'Assessment by Facility'!$J$2:$J$135) | E5: =D5*'Assessment Inputs'!$B$14 | F5: =C5*'Assessment Inputs'!$B$14 | G5: =E5-F5 | H5: =G5*'Assessment Inputs'!$B$12 | I5: Encompass Health Rehabilitation Hospital of Scottsdale; HonorHealth Scottsdale Thompson Peak Medical Center; HonorHealth Sonoran Crossing Medical Center
A6: 5 | B6: 12 | C6: =SUMIF('Assessment by Facility'!$E$2:$E$135,A6,'Assessment by Facility'!$G$2:$G$135) | D6: =SUMIF('Assessment by Facility'!$E$2:$E$135,A6,'Assessment by Facility'!$J$2:$J$135) | E6: =D6*'Assessment Inputs'!$B$14 | F6: =C6*'Assessment Inputs'!$B$14 | G6: =E6-F6 | H6: =G6*'Assessment Inputs'!$B$12 | I6: Abrazo Scottsdale Campus; HonorHealth Scottsdale Shea Medical Center; Mayo Clinic Hospital
A7: 6 | B7: 13 | C7: =SUMIF('Assessment by Facility'!$E$2:$E$135,A7,'Assessment by Facility'!$G$2:$G$135) | D7: =SUMIF('Assessment by Facility'!$E$2:$E$135,A7,'Assessment by Facility'!$J$2:$J$135) | E7: =D7*'Assessment Inputs'!$B$14 | F7: =C7*'Assessment Inputs'!$B$14 | G7: =E7-F7 | H7: =G7*'Assessment Inputs'!$B$12 | I7: Banner – University Medical Center Phoenix; College Medical Center Phoenix (formerly St. Luke's Behavioral Hospital); HonorHealth John C. Lincoln Medical Center; Phoenix Children's Hospital; Phoenix Indian Medical Center; Phoenix Medical Psychiatric Hospital; Reunion Rehabilitation Hospital Phoenix; Select Specialty Hospital – Phoenix (St. Joseph's campus); Select Specialty Hospital – Phoenix Downtown (Banner UMC Phoenix campus); St. Joseph's Hospital and Medical Center (Phoenix); Valley Hospital (Phoenix); Valleywise Health Medical Center
A8: 7 | B8: 5 | C8: =SUMIF('Assessment by Facility'!$E$2:$E$135,A8,'Assessment by Facility'!$G$2:$G$135) | D8: =SUMIF('Assessment by Facility'!$E$2:$E$135,A8,'Assessment by Facility'!$J$2:$J$135) | E8: =D8*'Assessment Inputs'!$B$14 | F8: =C8*'Assessment Inputs'!$B$14 | G8: =E8-F8 | H8: =G8*'Assessment Inputs'!$B$12 | I8: Chinle Comprehensive Health Care Facility; Flagstaff Medical Center; Hopi Health Care Center; Little Colorado Medical Center; Page Hospital; Rehabilitation Hospital of Northern Arizona; Sage Memorial Hospital; San Carlos Apache Healthcare Corporation; The Guidance Center; Tséhootsooí Medical Center (Fort Defiance Indian Hospital); Tuba City Regional Health Care Corporation; White Mountain Regional Medical Center; Whiteriver Indian Hospital
A9: 8 | B9: 6 | C9: =SUMIF('Assessment by Facility'!$E$2:$E$135,A9,'Assessment by Facility'!$G$2:$G$135) | D9: =SUMIF('Assessment by Facility'!$E$2:$E$135,A9,'Assessment by Facility'!$J$2:$J$135) | E9: =D9*'Assessment Inputs'!$B$14 | F9: =C9*'Assessment Inputs'!$B$14 | G9: =E9-F9 | H9: =G9*'Assessment Inputs'!$B$12 | I9: Banner Payson Medical Center; ChangePoint Psychiatric Hospital; Cobre Valley Regional Medical Center; HonorHealth Florence Medical Center (formerly Florence Hospital); Summit Healthcare Regional Medical Center
A10: 9 | B10: 2 | C10: =SUMIF('Assessment by Facility'!$E$2:$E$135,A10,'Assessment by Facility'!$G$2:$G$135) | D10: =SUMIF('Assessment by Facility'!$E$2:$E$135,A10,'Assessment by Facility'!$J$2:$J$135) | E10: =D10*'Assessment Inputs'!$B$14 | F10: =C10*'Assessment Inputs'!$B$14 | G10: =E10-F10 | H10: =G10*'Assessment Inputs'!$B$12 | I10: Arizona Specialty Hospital (Phoenix campus; formerly OASIS Hospital); Banner Behavioral Health Hospital; HonorHealth Rehabilitation Hospital; HonorHealth Scottsdale Osborn Medical Center; HonorHealth Tempe Medical Center (formerly Tempe St. Luke's); Via Linda Behavioral Hospital
A11: 10 | B11: 6 | C11: =SUMIF('Assessment by Facility'!$E$2:$E$135,A11,'Assessment by Facility'!$G$2:$G$135) | D11: =SUMIF('Assessment by Facility'!$E$2:$E$135,A11,'Assessment by Facility'!$J$2:$J$135) | E11: =D11*'Assessment Inputs'!$B$14 | F11: =C11*'Assessment Inputs'!$B$14 | G11: =E11-F11 | H11: =G11*'Assessment Inputs'!$B$12 | I11: Banner Desert Medical Center; Phoenix Specialty Hospital (formerly KPC Promise Hospital of Phoenix)
A12: 11 | B12: 4 | C12: =SUMIF('Assessment by Facility'!$E$2:$E$135,A12,'Assessment by Facility'!$G$2:$G$135) | D12: =SUMIF('Assessment by Facility'!$E$2:$E$135,A12,'Assessment by Facility'!$J$2:$J$135) | E12: =D12*'Assessment Inputs'!$B$14 | F12: =C12*'Assessment Inputs'!$B$14 | G12: =E12-F12 | H12: =G12*'Assessment Inputs'!$B$12 | I12: Arizona Spine and Joint Hospital; Banner Baywood Medical Center; Banner Goldfield Medical Center; Banner Heart Hospital; Encompass Health Rehabilitation Hospital of East Valley; HonorHealth Four Peaks Medical Center (formerly Mountain Vista Medical Center)
A13: 12 | B13: 3 | C13: =SUMIF('Assessment by Facility'!$E$2:$E$135,A13,'Assessment by Facility'!$G$2:$G$135) | D13: =SUMIF('Assessment by Facility'!$E$2:$E$135,A13,'Assessment by Facility'!$J$2:$J$135) | E13: =D13*'Assessment Inputs'!$B$14 | F13: =C13*'Assessment Inputs'!$B$14 | G13: =E13-F13 | H13: =G13*'Assessment Inputs'!$B$12 | I13: Arizona General Hospital – Laveen; Arizona State Hospital; Haven Behavioral Hospital of Phoenix; Talas Harbor at Buckeye (Phoenix) (closed)
... A31: 30 | B31: 9 | C31: =SUMIF('Assessment by Facility'!$E$2:$E$135,A31,'Assessment by Facility'!$G$2:$G$135) | D31: =SUMIF('Assessment by Facility'!$E$2:$E$135,A31,'Assessment by Facility'!$J$2:$J$135) | E31: =D31*'Assessment Inputs'!$B$14 | F31: =C31*'Assessment Inputs'!$B$14 | G31: =E31-F31 | H31: =G31*'Assessment Inputs'!$B$12 | I31: Avenir Behavioral Health Center
A32: Total | B32: =SUM(B2:B31) | C32: =SUM(C2:C31) | D32: =SUM(D2:D31) | E32: =SUM(E2:E31) | F32: =SUM(F2:F31) | G32: =SUM(G2:G31) | H32: =SUM(H2:H31)
A34: District = location of the facility (street address geocoded to a 2020 census block, mapped to the 2022 IRC district). Hospitals serve patients from many districts; these totals describe where the facilities and their jobs are. LD 5 (central Phoenix) is high because it contains Banner – University Medical Center Phoenix, St. Joseph's, Valleywise, Phoenix Children's, John C. Lincoln and Phoenix Indian Medical Center.

Sheet Providers by District
A1: LD | B1: Main county | C1: 2020 population | D1: Primary care physicians (FTE-split) | E1: All physicians MD/DO | F1: Psychiatrists | G1: Behavioral health clinicians | H1: Nurse practitioners | I1: Physician assistants | J1: Primary care physicians per 100k | K1: Physicians per 100k | L1: Psychiatrists per 100k | M1: Behavioral health per 100k | N1: NPs + PAs per 100k
A2: 1 | B2: Yavapai | C2: 237896 | D2: 84.2 | E2: 342.2 | F2: 6.5 | G2: 85.6 | H2: 213.6 | I2: 111.8 | J2: 35.4 | K2: 143.8 | L2: 2.7 | M2: 36 | N2: 136.8
A3: 2 | B3: Maricopa | C3: 246674 | D3: 112.4 | E3: 428.7 | F3: 10.9 | G3: 104.8 | H3: 213.3 | I3: 105.4 | J3: 45.6 | K3: 173.8 | L3: 4.4 | M3: 42.5 | N3: 129.2
A4: 3 | B4: Maricopa | C4: 236955 | D4: 173.7 | E4: 1159.4 | F4: 14.7 | G4: 86.1 | H4: 331.4 | I4: 251.5 | J4: 73.3 | K4: 489.3 | L4: 6.2 | M4: 36.3 | N4: 245.9
A5: 4 | B5: Maricopa | C5: 244298 | D5: 270.6 | E5: 1221.4 | F5: 34.6 | G5: 240.4 | H5: 400.4 | I5: 338.3 | J5: 110.8 | K5: 500 | L5: 14.2 | M5: 98.4 | N5: 302.4
A6: 5 | B6: Maricopa | C6: 239088 | D6: 555.8 | E6: 2050.8 | F6: 59 | G6: 435 | H6: 711.9 | I6: 301.6 | J6: 232.5 | K6: 857.8 | L6: 24.7 | M6: 181.9 | N6: 424
A7: 6 | B7: Coconino | C7: 225474 | D7: 247.3 | E7: 774.9 | F7: 27.7 | G7: 70.2 | H7: 238.9 | I7: 88.5 | J7: 109.7 | K7: 343.7 | L7: 12.3 | M7: 31.1 | N7: 145.2
A8: 7 | B8: Pinal | C8: 240214 | D8: 94.5 | E8: 392.6 | F8: 8.6 | G8: 47.7 | H8: 147 | I8: 72.2 | J8: 39.3 | K8: 163.4 | L8: 3.6 | M8: 19.9 | N8: 91.3
A9: 8 | B9: Maricopa | C9: 244166 | D9: 142.2 | E9: 594 | F9: 57.4 | G9: 955.9 | H9: 369.9 | I9: 158.2 | J9: 58.2 | K9: 243.3 | L9: 23.5 | M9: 391.5 | N9: 216.3
A10: 9 | B10: Maricopa | C10: 238117 | D10: 133.2 | E10: 479.4 | F10: 28 | G10: 107.8 | H10: 219.2 | I10: 91.1 | J10: 55.9 | K10: 201.3 | L10: 11.8 | M10: 45.3 | N10: 130.3
A11: 10 | B11: Maricopa | C11: 235579 | D11: 116.2 | E11: 420.2 | F11: 3.2 | G11: 50.8 | H11: 236.3 | I11: 105.2 | J11: 49.3 | K11: 178.4 | L11: 1.4 | M11: 21.5 | N11: 145
A12: 11 | B12: Maricopa | C12: 237844 | D12: 71.3 | E12: 292 | F12: 11.7 | G12: 60.8 | H12: 161 | I12: 69 | J12: 30 | K12: 122.8 | L12: 4.9 | M12: 25.6 | N12: 96.7
A13: 12 | B13: Maricopa | C13: 238923 | D13: 146.7 | E13: 451.9 | F13: 33.5 | G13: 99.4 | H13: 223.1 | I13: 120.7 | J13: 61.4 | K13: 189.1 | L13: 14 | M13: 41.6 | N13: 143.9
... A31: 30 | B31: Mohave | C31: 237999 | D31: 144.8 | E31: 600.5 | F31: 7.2 | G31: 31.3 | H31: 227.4 | I31: 72.5 | J31: 60.9 | K31: 252.3 | L31: 3 | M31: 13.2 | N31: 126
A33: Source: CMS Doctors and Clinicians National Downloadable File (https://data.cms.gov/provider-data/dataset/mj5m-pzi6), data refreshed July 31 2026; Arizona practice-location rows (70,180; 35,922 clinicians). Each clinician counted once per practice ZIP and split equally across their locations; ZIP mapped to ZCTA (UDS Mapper 2022) and allocated to 2022 legislative districts by 2020 block population. Primary care = family practice, internal medicine, general practice, pediatric medicine, geriatric medicine with MD/DO credential. Behavioral health = psychiatry, clinical psychologist, clinical social worker, mental health counselor, marriage & family therapist, addiction medicine. Medicare-enrolled clinicians only (excludes clinicians who do not bill Medicare and most IHS clinicians); counts reflect where practices are located, not where residents receive care. Statewide: 59.8 primary care physicians, 219.8 physicians, 7.3 psychiatrists per 100,000.

Sheet Providers by County
A1: County | B1: Population 2024 | C1: Active MD+DO per 100k (2023) | D1: Primary care physicians per 100k (patient care, excl. residents, 2023) | E1: Psychiatrists per 100k | F1: Dentists per 100k | G1: NPs per 100k (2024) | H1: PAs per 100k (2024) | I1: Primary care HPSAs (designated) | J1: Primary care FTE shortage | K1: Dental HPSAs | L1: Dental FTE shortage | M1: Mental health HPSAs | N1: Mental health FTE shortage
A2: Apache | B2: 64800 | C2: 89.2 | D2: 40 | E2: 1.5 | F2: 49.2 | G2: 84.9 | H2: 34 | I2: 13 | J2: 7.5 | K2: 14 | L2: 4.4 | M2: 14 | N2: 1.3
A3: Cochise | B3: 125773 | C3: 142.8 | D3: 57 | E3: 1.6 | F3: 40.9 | G3: 127.2 | H3: 20.7 | I3: 15 | J3: 12 | K3: 15 | L3: 8.6 | M3: 15 | N3: 6.8
A4: Coconino | B4: 145161 | C4: 296.9 | D4: 81.7 | E4: 13.2 | F4: 68.5 | G4: 122.6 | H4: 60.6 | I4: 17 | J4: 15.1 | K4: 16 | L4: 9.8 | M4: 16 | N4: 2.4
A5: Gila | B5: 54073 | C5: 129.6 | D5: 48.1 | E5: 3.7 | F5: 42.6 | G5: 62.9 | H5: 44.4 | I5: 12 | J5: 6.2 | K5: 12 | L5: 5.4 | M5: 12 | N5: 1.9
A6: Graham | B6: 40242 | C6: 83.5 | D6: 48.1 | E6: 0 | F6: 30.4 | G6: 84.5 | H6: 59.6 | I6: 9 | J6: 8.3 | K6: 9 | L6: 5.4 | M6: 9 | N6: 3.4
A7: Greenlee | B7: 9410 | C7: 74.7 | D7: 64 | E7: 0 | F7: 0 | G7: 42.5 | H7: 53.1 | I7: 1 | J7: 2.7 | K7: 1 | L7: 1.9 | M7: 1 | N7: 0.5
A8: La Paz | B8: 16992 | C8: 83.8 | D8: 23.9 | E8: 0 | F8: 29.9 | G8: 82.4 | H8: 29.4 | I8: 10 | J8: 3.6 | K8: 10 | L8: 1.7 | M8: 10 | N8: 0.8
A9: Maricopa | B9: 4673096 | C9: 304.1 | D9: 67.3 | E9: 8.6 | F9: 68.3 | G9: 133.9 | H9: 72.2 | I9: 50 | J9: 188.6 | K9: 43 | L9: 73.3 | M9: 37 | N9: 19.8
A10: Mohave | B10: 226479 | C10: 174.4 | D10: 48.7 | E10: 3.1 | F10: 35.8 | G10: 92.3 | H10: 37.5 | I10: 12 | J10: 26.4 | K10: 11 | L10: 15.5 | M10: 11 | N10: 7
A11: Navajo | B11: 109516 | C11: 142.9 | D11: 58.6 | E11: 1.8 | F11: 53.1 | G11: 99.5 | H11: 44.7 | I11: 21 | J11: 10.2 | K11: 20 | L11: 8 | M11: 21 | N11: 5
A12: Pima | B12: 1080149 | C12: 435.6 | D12: 85.3 | E12: 17.4 | F12: 53.7 | G12: 139.9 | H12: 34.4 | I12: 29 | J12: 70.8 | K12: 27 | L12: 45.8 | M12: 29 | N12: 19.8
A13: Pinal | B13: 513862 | C13: 41.7 | D13: 17.3 | E13: 1.7 | F13: 23.7 | G13: 63.2 | H13: 20.2 | I13: 26 | J13: 71.9 | K13: 20 | L13: 27.3 | M13: 24 | N13: 25.5
... A16: Yuma | B16: 220310 | C16: 151 | D16: 41.7 | E16: 2.3 | F16: 23.9 | G16: 85.8 | H16: 33.6 | I16: 7 | J16: 24.9 | K16: 7 | L16: 17.6 | M16: 7 | N16: 8.2
A18: Sources: HRSA Area Health Resources File 2024-2025 (https://data.hrsa.gov/topics/health-workforce/ahrf; physician counts from AMA/AOA 2023, NP/PA from NPPES 2024); HRSA HPSA designation files for Primary Care, Dental Health and Mental Health (https://data.hrsa.gov/data/download), Designated status only, warehouse date Sept 5 2026. Facility HPSAs counted in the county of the facility; multi-county HPSAs counted in each county with the FTE shortage split equally. Statewide designated HPSAs: primary care 227 (468.8 FTE short), dental 210 (241.9), mental health 212 (110.5). Context: UA Center for Rural Health (Dec 2024) - Arizona needs 493 PCP FTEs and meets 35.4%% of need; Derksen (Feb 2025) - 80 PCPs per 100,000 (rank 42) and 256 active physicians per 100,000 (rank 32).
